{
  "technique": "T1003",
  "source": "arda_bpf",
  "events": [
    {
      "raw": "2026-04-26 15:15:08,697 - services.os_enforcement_service - INFO - ARDA_LSM: Disabled via ARDA_LSM_ENABLED env var \u2014 running in simulation mode.",
      "source": "arda_bpf_backend"
    },
    {
      "raw": "ARDA_LSM Ring-0 deny: technique=T1003 deny_count_delta=3 exec_rc=126 verdict=kernel_prevented",
      "source": "arda_bpf_kernel",
      "verdict": "kernel_prevented",
      "evidence_mode": "kernel_observed",
      "session_id": "arda-T1003-r1-c5a4ce5c",
      "evidence_hash": "f1c051d849ea12fa8c6b15885e907b5d0d076e8a35819ec58726cd1b9d87f77d"
    },
    {
      "raw": "ARDA_LSM Ring-0 deny: technique=T1003 deny_count_delta=2 exec_rc=126 verdict=kernel_prevented",
      "source": "arda_bpf_kernel",
      "verdict": "kernel_prevented",
      "evidence_mode": "kernel_observed",
      "session_id": "arda-T1003-r2-41dd6c5a",
      "evidence_hash": "e424ebb68a5c7cca1755a8509ae4ccacb66d08e40f731abc583a6915eb8495c4"
    },
    {
      "raw": "ARDA_LSM Ring-0 deny: technique=T1003 deny_count_delta=3 exec_rc=126 verdict=kernel_prevented",
      "source": "arda_bpf_kernel",
      "verdict": "kernel_prevented",
      "evidence_mode": "kernel_observed",
      "session_id": "arda-T1003-r3-636883b7",
      "evidence_hash": "f6ea17fea8eb6713ba0a95bbc81647432d4db244bf033dbe2ae18937faa92cdb"
    },
    {
      "raw": "ARDA_LSM Ring-0 deny: technique=T1003 deny_count_delta=3 exec_rc=126 verdict=kernel_prevented",
      "source": "arda_bpf_kernel",
      "verdict": "kernel_prevented",
      "evidence_mode": "kernel_observed",
      "session_id": "arda-T1003-r1-4ddda831",
      "evidence_hash": "b17c222170ea3507ca6ef55a53b9d6a8db1c6c07b12f955e437a1fd0a2ce5292"
    },
    {
      "raw": "ARDA_LSM Ring-0 deny: technique=T1003 deny_count_delta=2 exec_rc=126 verdict=kernel_prevented",
      "source": "arda_bpf_kernel",
      "verdict": "kernel_prevented",
      "evidence_mode": "kernel_observed",
      "session_id": "arda-T1003-r2-377aec40",
      "evidence_hash": "67a33ab9cd247796cfa90b3e5069cbfff378a0ca6e5c96087ae11e4fe2af3674"
    },
    {
      "raw": "ARDA_LSM Ring-0 deny: technique=T1003 deny_count_delta=3 exec_rc=126 verdict=kernel_prevented",
      "source": "arda_bpf_kernel",
      "verdict": "kernel_prevented",
      "evidence_mode": "kernel_observed",
      "session_id": "arda-T1003-r3-c98e83f2",
      "evidence_hash": "2203e2d0568917375a8c7700494da9e4a3798d1c579bf5aabffd4191d78f45b5"
    },
    {
      "raw": "ARDA_LSM Ring-0 deny: technique=T1003 deny_count_delta=3 exec_rc=126 verdict=kernel_prevented",
      "source": "arda_bpf_kernel",
      "verdict": "kernel_prevented",
      "evidence_mode": "kernel_observed",
      "session_id": "arda-T1003-r1-1e736972",
      "evidence_hash": "e78b91c93e51b46e263b86ed1942b3b2b05b4110d12b13df68d69368abe30365"
    },
    {
      "raw": "ARDA_LSM Ring-0 deny: technique=T1003 deny_count_delta=2 exec_rc=126 verdict=kernel_prevented",
      "source": "arda_bpf_kernel",
      "verdict": "kernel_prevented",
      "evidence_mode": "kernel_observed",
      "session_id": "arda-T1003-r2-d81ef255",
      "evidence_hash": "970073c730f664663fa4c02b6d5977ae557c1a846bf85bf0a43d70d3d543e82b"
    },
    {
      "raw": "ARDA_LSM Ring-0 deny: technique=T1003 deny_count_delta=3 exec_rc=126 verdict=kernel_prevented",
      "source": "arda_bpf_kernel",
      "verdict": "kernel_prevented",
      "evidence_mode": "kernel_observed",
      "session_id": "arda-T1003-r3-878ab8f6",
      "evidence_hash": "ac00d5ed82110806f553c5ae04fcc04655331a920aa489b357959c128711a06c"
    },
    {
      "raw": "ARDA_LSM Ring-0 deny: technique=T1003 deny_count_delta=2 exec_rc=126 verdict=kernel_prevented",
      "source": "arda_bpf_kernel",
      "verdict": "kernel_prevented",
      "evidence_mode": "kernel_observed",
      "session_id": "arda-T1003-r4-c56a41df",
      "evidence_hash": "54bc222d31898347439113dae12fa544096a6eb4fd4011b2920ecb00befae3cf"
    },
    {
      "raw": "ARDA_LSM Ring-0 deny: technique=T1003 deny_count_delta=1 exec_rc=-1 verdict=kernel_would_prevent",
      "source": "arda_bpf_kernel",
      "verdict": "kernel_would_prevent",
      "evidence_mode": "kernel_deductive",
      "session_id": "arda-deduct-T1003-r5-60f8da43",
      "evidence_hash": "30167beb3d1abc78f221d07b4f8f18d34bc29e9cc36bf928f3ee5112fede1ad6"
    },
    {
      "raw": "ARDA_LSM Ring-0 deny: technique=T1003 deny_count_delta=None exec_rc=126 verdict=kernel_prevented",
      "source": "arda_bpf_kernel",
      "verdict": "kernel_prevented",
      "evidence_mode": "kernel_observed",
      "session_id": "arda-T1003-r1-539beb1a",
      "evidence_hash": "def64349f0f6e91ea481b2ee49f27b3ba06f779086c647b5b9443534706dc76d"
    },
    {
      "raw": "ARDA_LSM Ring-0 deny: technique=T1003 deny_count_delta=3 exec_rc=126 verdict=kernel_prevented",
      "source": "arda_bpf_kernel",
      "verdict": "kernel_prevented",
      "evidence_mode": "kernel_observed",
      "session_id": "arda-T1003-r2-5a11f082",
      "evidence_hash": "3a7e9b287f5a910d036c0742c967b593f18901ad48505d127e969e9ef262eb32"
    },
    {
      "raw": "ARDA_LSM Ring-0 deny: technique=T1003 deny_count_delta=2 exec_rc=126 verdict=kernel_prevented",
      "source": "arda_bpf_kernel",
      "verdict": "kernel_prevented",
      "evidence_mode": "kernel_observed",
      "session_id": "arda-T1003-r3-b13cc79e",
      "evidence_hash": "f31676baffa96711725efe64d6192ea00b72ec3652fe6d83e4ee2494e76bd5b6"
    },
    {
      "raw": "ARDA_LSM Ring-0 deny: technique=T1003 deny_count_delta=3 exec_rc=126 verdict=kernel_prevented",
      "source": "arda_bpf_kernel",
      "verdict": "kernel_prevented",
      "evidence_mode": "kernel_observed",
      "session_id": "arda-T1003-r4-59e0f5ed",
      "evidence_hash": "8a1e7727bcec685aaacc4f9758e8150c583c40af7587ef99ec723a767d6accad"
    },
    {
      "raw": "ARDA_LSM Ring-0 deny: technique=T1003 deny_count_delta=2 exec_rc=126 verdict=kernel_prevented",
      "source": "arda_bpf_kernel",
      "verdict": "kernel_prevented",
      "evidence_mode": "kernel_observed",
      "session_id": "arda-T1003-r5-9b03162a",
      "evidence_hash": "c1210fda182270e58d6cc97a12a6baa9a450c16448b8dbd713c0a4de1ee44f7f"
    }
  ],
  "arda_bpf_status": "live_ring0_enforcement",
  "arda_substrate_proof": "026b2876abd7ca12d2f15d5251a0912baaf2ce78ed258cd5ac27d9222bb19efd"
}