{
  "record_type": "technique_validation_record",
  "schema_version": "1.0.0",
  "validation_id": "TVR-T1104-2026-04-27-022",
  "technique": {
    "attack_id": "T1104",
    "name": "T1104",
    "tactics": [],
    "platforms": [
      "Linux"
    ]
  },
  "procedure": {
    "source": "atomic_red_team",
    "procedure_id": "ART-T1104-1",
    "name": "Atomic Red Team validation for T1104",
    "description": "Automated emulation procedure for T1104 executed via Invoke-AtomicRedTeam inside the Metatron lab environment.",
    "test_ref": "atomics/T1104/T1104.yaml#test-1"
  },
  "environment": {
    "lab_id": "metatron-lab-a",
    "hostname": "debian-node-01",
    "asset_id": "asset-001",
    "os": {
      "family": "linux",
      "name": "Debian",
      "version": "12"
    },
    "kernel_version": "6.12.74+deb12-amd64",
    "sensor_stack": [
      {
        "name": "sigma-engine",
        "version": "2026.04.27",
        "rules_loaded": 505
      },
      {
        "name": "osquery",
        "version": "5.15.0"
      },
      {
        "name": "atomic_red_team",
        "version": "2025.01"
      }
    ]
  },
  "execution": {
    "started_at": "2026-04-27T10:09:08.128287+00:00",
    "ended_at": "2026-04-27T10:09:08.128287+00:00",
    "executor": "atomic_red_team",
    "operator": "Byron Bunt",
    "status": "completed",
    "exit_code": 0,
    "real_execution": true,
    "execution_mode": "docker_sandbox",
    "execution_trust_level": "docker_sandbox_verified",
    "sandbox_verified": true,
    "evidence_inheritance": "direct",
    "expected_outcome": "detect",
    "command_line": "Invoke-AtomicTest T1104 -PathToAtomicsFolder '/opt/atomic-red-team/atomics'",
    "run_count": 22,
    "direct_run_count": 22,
    "run_ids": [
      "0ee121e7b010417a_T1104",
      "19c8f027d99e4dbe_T1104",
      "1fe7b0052aab4d32_T1104",
      "38f945bd402e4900_T1104",
      "401874dcebd243f3_T1104",
      "4d88beb65df94713_T1104",
      "530f956d8d754afa_T1104",
      "5980b09764c14726_T1104",
      "59c5891731cd4275_T1104",
      "5ab7fea961ee454b_T1104",
      "6c85bb43d63347bd_T1104",
      "6e825e26e9664fd4_T1104",
      "7b18097e84d044e4_T1104",
      "81608275e05e4461_T1104",
      "9019b42e6ff340ad_T1104",
      "962c4dee70d2451a_T1104",
      "a0384ce3386540cd_T1104",
      "aceff3707fb94858_T1104",
      "c7611e0b74854458_T1104",
      "ead45bc241494f5e_T1104",
      "f93081127833474c_T1104",
      "ff0f5d61c67a4495_T1104"
    ],
    "job_ids": [
      "bronze-fixed-sweep",
      "bronze-multipass",
      "bronze-sweep-20260427",
      "bronze-sweep-pass-extra"
    ],
    "runs": [
      {
        "run_id": "0ee121e7b010417a_T1104",
        "job_id": "bronze-multipass",
        "job_name": "Bronze Multi-Pass",
        "finished_at": "2026-04-27T10:09:06.585147+00:00",
        "exit_code": 0,
        "sandbox": "docker-network-none-cap-drop-all",
        "status": "success",
        "outcome": "",
        "command": null,
        "stdout": "PathToAtomicsFolder = /opt/atomic-red-team/atomics\nExecuting test: T1104\nHTTP/1.1 404 Not Found\ndate: Mon, 27 Apr 2026 10:09:05 GMT\nserver: uvicorn\ncontent-length: 22\ncontent-type: application/json\n",
        "stdout_sha256": "f8565c05ddbe3a05ace5ba95d28067c1f3ca85cd06c82e5065a99e37fe89b751",
        "stderr_sha256": "e3b0c44298fc1c149afbf4c8996fb92427ae41e4649b934ca495991b7852b855",
        "real_execution": true
      },
      {
        "run_id": "19c8f027d99e4dbe_T1104",
        "job_id": "bronze-fixed-sweep",
        "job_name": "Bronze Fixed Sweep",
        "finished_at": "2026-04-27T10:14:54.898131+00:00",
        "exit_code": 0,
        "sandbox": "docker-network-none-cap-drop-all",
        "status": "success",
        "outcome": "",
        "command": null,
        "stdout": "PathToAtomicsFolder = /opt/atomic-red-team/atomics\nExecuting test: T1104\nHTTP/1.1 404 Not Found\ndate: Mon, 27 Apr 2026 10:14:53 GMT\nserver: uvicorn\ncontent-length: 22\ncontent-type: application/json\nHTTP/1.1 405 Method Not Allowed\ndate: Mon, 27 Apr 2026 10:14:54 GMT\nserver: uvicorn\n",
        "stdout_sha256": "4ee986c89c1179692bb5f123f3fdd33247c190303bd956874f60ff1a536b7148",
        "stderr_sha256": "e3b0c44298fc1c149afbf4c8996fb92427ae41e4649b934ca495991b7852b855",
        "real_execution": true
      },
      {
        "run_id": "1fe7b0052aab4d32_T1104",
        "job_id": "bronze-sweep-pass-extra",
        "job_name": "Bronze Sweep Extra Pass",
        "finished_at": "2026-04-27T10:01:43.926359+00:00",
        "exit_code": 0,
        "sandbox": "docker-network-none-cap-drop-all",
        "status": "success",
        "outcome": "",
        "command": null,
        "stdout": "PathToAtomicsFolder = /opt/atomic-red-team/atomics\nExecuting test: T1104\nHTTP/1.1 404 Not Found\ndate: Mon, 27 Apr 2026 10:01:43 GMT\nserver: uvicorn\ncontent-length: 22\ncontent-type: application/json\n",
        "stdout_sha256": "07dfaba6adc3114171c42e5443dd8416b80dc8dc5c9e22fc444a4554dd5f69e1",
        "stderr_sha256": "e3b0c44298fc1c149afbf4c8996fb92427ae41e4649b934ca495991b7852b855",
        "real_execution": true
      },
      {
        "run_id": "38f945bd402e4900_T1104",
        "job_id": "bronze-multipass",
        "job_name": "Bronze Multi-Pass",
        "finished_at": "2026-04-27T10:09:08.364855+00:00",
        "exit_code": 0,
        "sandbox": "docker-network-none-cap-drop-all",
        "status": "success",
        "outcome": "",
        "command": null,
        "stdout": "PathToAtomicsFolder = /opt/atomic-red-team/atomics\nExecuting test: T1104\nHTTP/1.1 404 Not Found\ndate: Mon, 27 Apr 2026 10:09:08 GMT\nserver: uvicorn\ncontent-length: 22\ncontent-type: application/json\n",
        "stdout_sha256": "64aaadd7321fc533e3588bd2cca4e50eee85f54c12804efab4f25c57da0385f4",
        "stderr_sha256": "e3b0c44298fc1c149afbf4c8996fb92427ae41e4649b934ca495991b7852b855",
        "real_execution": true
      },
      {
        "run_id": "401874dcebd243f3_T1104",
        "job_id": "bronze-fixed-sweep",
        "job_name": "Bronze Fixed Sweep",
        "finished_at": "2026-04-27T10:14:57.525084+00:00",
        "exit_code": 0,
        "sandbox": "docker-network-none-cap-drop-all",
        "status": "success",
        "outcome": "",
        "command": null,
        "stdout": "PathToAtomicsFolder = /opt/atomic-red-team/atomics\nExecuting test: T1104\nHTTP/1.1 404 Not Found\ndate: Mon, 27 Apr 2026 10:14:56 GMT\nserver: uvicorn\ncontent-length: 22\ncontent-type: application/json\nHTTP/1.1 405 Method Not Allowed\ndate: Mon, 27 Apr 2026 10:14:56 GMT\nserver: uvicorn\n",
        "stdout_sha256": "e0b07ab572c9dbfc9ec373bbe59ae4e6be32e41fd73c9a49343208f71b067e58",
        "stderr_sha256": "e3b0c44298fc1c149afbf4c8996fb92427ae41e4649b934ca495991b7852b855",
        "real_execution": true
      },
      {
        "run_id": "4d88beb65df94713_T1104",
        "job_id": "bronze-multipass",
        "job_name": "Bronze Multi-Pass",
        "finished_at": "2026-04-27T10:09:06.833487+00:00",
        "exit_code": 0,
        "sandbox": "docker-network-none-cap-drop-all",
        "status": "success",
        "outcome": "",
        "command": null,
        "stdout": "PathToAtomicsFolder = /opt/atomic-red-team/atomics\nExecuting test: T1104\nHTTP/1.1 404 Not Found\ndate: Mon, 27 Apr 2026 10:09:05 GMT\nserver: uvicorn\ncontent-length: 22\ncontent-type: application/json\n",
        "stdout_sha256": "f8565c05ddbe3a05ace5ba95d28067c1f3ca85cd06c82e5065a99e37fe89b751",
        "stderr_sha256": "e3b0c44298fc1c149afbf4c8996fb92427ae41e4649b934ca495991b7852b855",
        "real_execution": true
      },
      {
        "run_id": "530f956d8d754afa_T1104",
        "job_id": "bronze-multipass",
        "job_name": "Bronze Multi-Pass",
        "finished_at": "2026-04-27T10:09:07.853287+00:00",
        "exit_code": 0,
        "sandbox": "docker-network-none-cap-drop-all",
        "status": "success",
        "outcome": "",
        "command": null,
        "stdout": "PathToAtomicsFolder = /opt/atomic-red-team/atomics\nExecuting test: T1104\nHTTP/1.1 404 Not Found\ndate: Mon, 27 Apr 2026 10:09:06 GMT\nserver: uvicorn\ncontent-length: 22\ncontent-type: application/json\n",
        "stdout_sha256": "f2bb6544fa0fd2982893bcbd1b7c1dad92fffaddba4abba1533b38b63c8ce163",
        "stderr_sha256": "e3b0c44298fc1c149afbf4c8996fb92427ae41e4649b934ca495991b7852b855",
        "real_execution": true
      },
      {
        "run_id": "5980b09764c14726_T1104",
        "job_id": "bronze-fixed-sweep",
        "job_name": "Bronze Fixed Sweep",
        "finished_at": "2026-04-27T10:14:53.984351+00:00",
        "exit_code": 0,
        "sandbox": "docker-network-none-cap-drop-all",
        "status": "success",
        "outcome": "",
        "command": null,
        "stdout": "PathToAtomicsFolder = /opt/atomic-red-team/atomics\nExecuting test: T1104\nHTTP/1.1 404 Not Found\ndate: Mon, 27 Apr 2026 10:14:53 GMT\nserver: uvicorn\ncontent-length: 22\ncontent-type: application/json\nHTTP/1.1 405 Method Not Allowed\ndate: Mon, 27 Apr 2026 10:14:53 GMT\nserver: uvicorn\n",
        "stdout_sha256": "9f0615fd399a8dcf598fc5c06be6d781c2418f77d84a117f0a8bbfeff2f48d4c",
        "stderr_sha256": "e3b0c44298fc1c149afbf4c8996fb92427ae41e4649b934ca495991b7852b855",
        "real_execution": true
      },
      {
        "run_id": "59c5891731cd4275_T1104",
        "job_id": "bronze-multipass",
        "job_name": "Bronze Multi-Pass",
        "finished_at": "2026-04-27T10:09:07.343700+00:00",
        "exit_code": 0,
        "sandbox": "docker-network-none-cap-drop-all",
        "status": "success",
        "outcome": "",
        "command": null,
        "stdout": "PathToAtomicsFolder = /opt/atomic-red-team/atomics\nExecuting test: T1104\nHTTP/1.1 404 Not Found\ndate: Mon, 27 Apr 2026 10:09:06 GMT\nserver: uvicorn\ncontent-length: 22\ncontent-type: application/json\n",
        "stdout_sha256": "f2bb6544fa0fd2982893bcbd1b7c1dad92fffaddba4abba1533b38b63c8ce163",
        "stderr_sha256": "e3b0c44298fc1c149afbf4c8996fb92427ae41e4649b934ca495991b7852b855",
        "real_execution": true
      },
      {
        "run_id": "5ab7fea961ee454b_T1104",
        "job_id": "bronze-fixed-sweep",
        "job_name": "Bronze Fixed Sweep",
        "finished_at": "2026-04-27T10:14:55.363364+00:00",
        "exit_code": 0,
        "sandbox": "docker-network-none-cap-drop-all",
        "status": "success",
        "outcome": "",
        "command": null,
        "stdout": "PathToAtomicsFolder = /opt/atomic-red-team/atomics\nExecuting test: T1104\nHTTP/1.1 404 Not Found\ndate: Mon, 27 Apr 2026 10:14:54 GMT\nserver: uvicorn\ncontent-length: 22\ncontent-type: application/json\nHTTP/1.1 405 Method Not Allowed\ndate: Mon, 27 Apr 2026 10:14:54 GMT\nserver: uvicorn\n",
        "stdout_sha256": "fadcc2c3dd2e7dae97c23209615a492d2c3ae4db2afc3d50b373af2e623ec626",
        "stderr_sha256": "e3b0c44298fc1c149afbf4c8996fb92427ae41e4649b934ca495991b7852b855",
        "real_execution": true
      },
      {
        "run_id": "6c85bb43d63347bd_T1104",
        "job_id": "bronze-fixed-sweep",
        "job_name": "Bronze Fixed Sweep",
        "finished_at": "2026-04-27T10:14:55.860553+00:00",
        "exit_code": 0,
        "sandbox": "docker-network-none-cap-drop-all",
        "status": "success",
        "outcome": "",
        "command": null,
        "stdout": "PathToAtomicsFolder = /opt/atomic-red-team/atomics\nExecuting test: T1104\nHTTP/1.1 404 Not Found\ndate: Mon, 27 Apr 2026 10:14:54 GMT\nserver: uvicorn\ncontent-length: 22\ncontent-type: application/json\nHTTP/1.1 405 Method Not Allowed\ndate: Mon, 27 Apr 2026 10:14:54 GMT\nserver: uvicorn\n",
        "stdout_sha256": "fadcc2c3dd2e7dae97c23209615a492d2c3ae4db2afc3d50b373af2e623ec626",
        "stderr_sha256": "e3b0c44298fc1c149afbf4c8996fb92427ae41e4649b934ca495991b7852b855",
        "real_execution": true
      },
      {
        "run_id": "6e825e26e9664fd4_T1104",
        "job_id": "bronze-sweep-pass-extra",
        "job_name": "Bronze Sweep Extra Pass",
        "finished_at": "2026-04-27T10:01:43.636457+00:00",
        "exit_code": 0,
        "sandbox": "docker-network-none-cap-drop-all",
        "status": "success",
        "outcome": "",
        "command": null,
        "stdout": "PathToAtomicsFolder = /opt/atomic-red-team/atomics\nExecuting test: T1104\nHTTP/1.1 404 Not Found\ndate: Mon, 27 Apr 2026 10:01:43 GMT\nserver: uvicorn\ncontent-length: 22\ncontent-type: application/json\n",
        "stdout_sha256": "07dfaba6adc3114171c42e5443dd8416b80dc8dc5c9e22fc444a4554dd5f69e1",
        "stderr_sha256": "e3b0c44298fc1c149afbf4c8996fb92427ae41e4649b934ca495991b7852b855",
        "real_execution": true
      },
      {
        "run_id": "7b18097e84d044e4_T1104",
        "job_id": "bronze-multipass",
        "job_name": "Bronze Multi-Pass",
        "finished_at": "2026-04-27T10:09:07.070628+00:00",
        "exit_code": 0,
        "sandbox": "docker-network-none-cap-drop-all",
        "status": "success",
        "outcome": "",
        "command": null,
        "stdout": "PathToAtomicsFolder = /opt/atomic-red-team/atomics\nExecuting test: T1104\nHTTP/1.1 404 Not Found\ndate: Mon, 27 Apr 2026 10:09:06 GMT\nserver: uvicorn\ncontent-length: 22\ncontent-type: application/json\n",
        "stdout_sha256": "f2bb6544fa0fd2982893bcbd1b7c1dad92fffaddba4abba1533b38b63c8ce163",
        "stderr_sha256": "e3b0c44298fc1c149afbf4c8996fb92427ae41e4649b934ca495991b7852b855",
        "real_execution": true
      },
      {
        "run_id": "81608275e05e4461_T1104",
        "job_id": "bronze-multipass",
        "job_name": "Bronze Multi-Pass",
        "finished_at": "2026-04-27T10:09:07.616296+00:00",
        "exit_code": 0,
        "sandbox": "docker-network-none-cap-drop-all",
        "status": "success",
        "outcome": "",
        "command": null,
        "stdout": "PathToAtomicsFolder = /opt/atomic-red-team/atomics\nExecuting test: T1104\nHTTP/1.1 404 Not Found\ndate: Mon, 27 Apr 2026 10:09:06 GMT\nserver: uvicorn\ncontent-length: 22\ncontent-type: application/json\n",
        "stdout_sha256": "f2bb6544fa0fd2982893bcbd1b7c1dad92fffaddba4abba1533b38b63c8ce163",
        "stderr_sha256": "e3b0c44298fc1c149afbf4c8996fb92427ae41e4649b934ca495991b7852b855",
        "real_execution": true
      },
      {
        "run_id": "9019b42e6ff340ad_T1104",
        "job_id": "bronze-fixed-sweep",
        "job_name": "Bronze Fixed Sweep",
        "finished_at": "2026-04-27T10:14:56.696540+00:00",
        "exit_code": 0,
        "sandbox": "docker-network-none-cap-drop-all",
        "status": "success",
        "outcome": "",
        "command": null,
        "stdout": "PathToAtomicsFolder = /opt/atomic-red-team/atomics\nExecuting test: T1104\nHTTP/1.1 404 Not Found\ndate: Mon, 27 Apr 2026 10:14:55 GMT\nserver: uvicorn\ncontent-length: 22\ncontent-type: application/json\nHTTP/1.1 405 Method Not Allowed\ndate: Mon, 27 Apr 2026 10:14:55 GMT\nserver: uvicorn\n",
        "stdout_sha256": "730194c70b1cad453fd87371a614a0195b23aaf4a13075022ca2453a46e3a0fb",
        "stderr_sha256": "e3b0c44298fc1c149afbf4c8996fb92427ae41e4649b934ca495991b7852b855",
        "real_execution": true
      },
      {
        "run_id": "962c4dee70d2451a_T1104",
        "job_id": "bronze-fixed-sweep",
        "job_name": "Bronze Fixed Sweep",
        "finished_at": "2026-04-27T10:14:57.109648+00:00",
        "exit_code": 0,
        "sandbox": "docker-network-none-cap-drop-all",
        "status": "success",
        "outcome": "",
        "command": null,
        "stdout": "PathToAtomicsFolder = /opt/atomic-red-team/atomics\nExecuting test: T1104\nHTTP/1.1 404 Not Found\ndate: Mon, 27 Apr 2026 10:14:56 GMT\nserver: uvicorn\ncontent-length: 22\ncontent-type: application/json\nHTTP/1.1 405 Method Not Allowed\ndate: Mon, 27 Apr 2026 10:14:56 GMT\nserver: uvicorn\n",
        "stdout_sha256": "e0b07ab572c9dbfc9ec373bbe59ae4e6be32e41fd73c9a49343208f71b067e58",
        "stderr_sha256": "e3b0c44298fc1c149afbf4c8996fb92427ae41e4649b934ca495991b7852b855",
        "real_execution": true
      },
      {
        "run_id": "a0384ce3386540cd_T1104",
        "job_id": "bronze-fixed-sweep",
        "job_name": "Bronze Fixed Sweep",
        "finished_at": "2026-04-27T10:14:57.911149+00:00",
        "exit_code": 0,
        "sandbox": "docker-network-none-cap-drop-all",
        "status": "success",
        "outcome": "",
        "command": null,
        "stdout": "PathToAtomicsFolder = /opt/atomic-red-team/atomics\nExecuting test: T1104\nHTTP/1.1 404 Not Found\ndate: Mon, 27 Apr 2026 10:14:56 GMT\nserver: uvicorn\ncontent-length: 22\ncontent-type: application/json\nHTTP/1.1 405 Method Not Allowed\ndate: Mon, 27 Apr 2026 10:14:56 GMT\nserver: uvicorn\n",
        "stdout_sha256": "e0b07ab572c9dbfc9ec373bbe59ae4e6be32e41fd73c9a49343208f71b067e58",
        "stderr_sha256": "e3b0c44298fc1c149afbf4c8996fb92427ae41e4649b934ca495991b7852b855",
        "real_execution": true
      },
      {
        "run_id": "aceff3707fb94858_T1104",
        "job_id": "bronze-fixed-sweep",
        "job_name": "Bronze Fixed Sweep",
        "finished_at": "2026-04-27T10:14:56.298846+00:00",
        "exit_code": 0,
        "sandbox": "docker-network-none-cap-drop-all",
        "status": "success",
        "outcome": "",
        "command": null,
        "stdout": "PathToAtomicsFolder = /opt/atomic-red-team/atomics\nExecuting test: T1104\nHTTP/1.1 404 Not Found\ndate: Mon, 27 Apr 2026 10:14:55 GMT\nserver: uvicorn\ncontent-length: 22\ncontent-type: application/json\nHTTP/1.1 405 Method Not Allowed\ndate: Mon, 27 Apr 2026 10:14:55 GMT\nserver: uvicorn\n",
        "stdout_sha256": "730194c70b1cad453fd87371a614a0195b23aaf4a13075022ca2453a46e3a0fb",
        "stderr_sha256": "e3b0c44298fc1c149afbf4c8996fb92427ae41e4649b934ca495991b7852b855",
        "real_execution": true
      },
      {
        "run_id": "c7611e0b74854458_T1104",
        "job_id": "bronze-sweep-pass-extra",
        "job_name": "Bronze Sweep Extra Pass",
        "finished_at": "2026-04-27T10:01:44.196852+00:00",
        "exit_code": 0,
        "sandbox": "docker-network-none-cap-drop-all",
        "status": "success",
        "outcome": "",
        "command": null,
        "stdout": "PathToAtomicsFolder = /opt/atomic-red-team/atomics\nExecuting test: T1104\nHTTP/1.1 404 Not Found\ndate: Mon, 27 Apr 2026 10:01:43 GMT\nserver: uvicorn\ncontent-length: 22\ncontent-type: application/json\n",
        "stdout_sha256": "07dfaba6adc3114171c42e5443dd8416b80dc8dc5c9e22fc444a4554dd5f69e1",
        "stderr_sha256": "e3b0c44298fc1c149afbf4c8996fb92427ae41e4649b934ca495991b7852b855",
        "real_execution": true
      },
      {
        "run_id": "ead45bc241494f5e_T1104",
        "job_id": "bronze-fixed-sweep",
        "job_name": "Bronze Fixed Sweep",
        "finished_at": "2026-04-27T10:14:54.450151+00:00",
        "exit_code": 0,
        "sandbox": "docker-network-none-cap-drop-all",
        "status": "success",
        "outcome": "",
        "command": null,
        "stdout": "PathToAtomicsFolder = /opt/atomic-red-team/atomics\nExecuting test: T1104\nHTTP/1.1 404 Not Found\ndate: Mon, 27 Apr 2026 10:14:53 GMT\nserver: uvicorn\ncontent-length: 22\ncontent-type: application/json\nHTTP/1.1 405 Method Not Allowed\ndate: Mon, 27 Apr 2026 10:14:53 GMT\nserver: uvicorn\n",
        "stdout_sha256": "9f0615fd399a8dcf598fc5c06be6d781c2418f77d84a117f0a8bbfeff2f48d4c",
        "stderr_sha256": "e3b0c44298fc1c149afbf4c8996fb92427ae41e4649b934ca495991b7852b855",
        "real_execution": true
      },
      {
        "run_id": "f93081127833474c_T1104",
        "job_id": "bronze-sweep-20260427",
        "job_name": "Bronze Technique Promotion Sweep",
        "finished_at": "2026-04-27T10:00:50.922780+00:00",
        "exit_code": 0,
        "sandbox": "docker-network-none-cap-drop-all",
        "status": "success",
        "outcome": "",
        "command": null,
        "stdout": "PathToAtomicsFolder = /opt/atomic-red-team/atomics\nExecuting test: T1104\nHTTP/1.1 404 Not Found\ndate: Mon, 27 Apr 2026 10:00:50 GMT\nserver: uvicorn\n",
        "stdout_sha256": "590867cce484e05be469b56f0845e076f85f3a4d3851288a805dce48d185478d",
        "stderr_sha256": "e3b0c44298fc1c149afbf4c8996fb92427ae41e4649b934ca495991b7852b855",
        "real_execution": true
      },
      {
        "run_id": "ff0f5d61c67a4495_T1104",
        "job_id": "bronze-multipass",
        "job_name": "Bronze Multi-Pass",
        "finished_at": "2026-04-27T10:09:08.128287+00:00",
        "exit_code": 0,
        "sandbox": "docker-network-none-cap-drop-all",
        "status": "success",
        "outcome": "",
        "command": null,
        "stdout": "PathToAtomicsFolder = /opt/atomic-red-team/atomics\nExecuting test: T1104\nHTTP/1.1 404 Not Found\ndate: Mon, 27 Apr 2026 10:09:08 GMT\nserver: uvicorn\ncontent-length: 22\ncontent-type: application/json\n",
        "stdout_sha256": "64aaadd7321fc533e3588bd2cca4e50eee85f54c12804efab4f25c57da0385f4",
        "stderr_sha256": "e3b0c44298fc1c149afbf4c8996fb92427ae41e4649b934ca495991b7852b855",
        "real_execution": true
      }
    ]
  },
  "telemetry_evidence": {
    "sources": [
      {
        "source_name": "atomic_execution",
        "file": "telemetry/atomic_stdout.ndjson",
        "sha256": "64aaadd7321fc533e3588bd2cca4e50eee85f54c12804efab4f25c57da0385f4"
      },
      {
        "source_name": "run_artifacts",
        "file": "run_*.json",
        "sha256": "f40dca7251efe41c3b71d4f6bb43e5e726df6d0257868ea2e04f60f78b39405d"
      }
    ],
    "key_events": []
  },
  "execution_evidence": {
    "observed": true,
    "command_line": "",
    "exit_code": 0,
    "run_ids": [
      "0ee121e7b010417a_T1104",
      "19c8f027d99e4dbe_T1104",
      "1fe7b0052aab4d32_T1104",
      "38f945bd402e4900_T1104",
      "401874dcebd243f3_T1104",
      "4d88beb65df94713_T1104",
      "530f956d8d754afa_T1104",
      "5980b09764c14726_T1104",
      "59c5891731cd4275_T1104",
      "5ab7fea961ee454b_T1104",
      "6c85bb43d63347bd_T1104",
      "6e825e26e9664fd4_T1104",
      "7b18097e84d044e4_T1104",
      "81608275e05e4461_T1104",
      "9019b42e6ff340ad_T1104",
      "962c4dee70d2451a_T1104",
      "a0384ce3386540cd_T1104",
      "aceff3707fb94858_T1104",
      "c7611e0b74854458_T1104",
      "ead45bc241494f5e_T1104",
      "f93081127833474c_T1104",
      "ff0f5d61c67a4495_T1104"
    ],
    "process_ids": [
      0
    ],
    "timestamps": [
      "2026-04-27T10:09:06.585147+00:00",
      "2026-04-27T10:14:54.898131+00:00",
      "2026-04-27T10:01:43.926359+00:00",
      "2026-04-27T10:09:08.364855+00:00",
      "2026-04-27T10:14:57.525084+00:00",
      "2026-04-27T10:09:06.833487+00:00",
      "2026-04-27T10:09:07.853287+00:00",
      "2026-04-27T10:14:53.984351+00:00"
    ]
  },
  "host_telemetry_evidence": {
    "observed": false,
    "sources": [
      {
        "source_name": "atomic_execution",
        "file": "telemetry/atomic_stdout.ndjson",
        "sha256": "64aaadd7321fc533e3588bd2cca4e50eee85f54c12804efab4f25c57da0385f4"
      },
      {
        "source_name": "run_artifacts",
        "file": "run_*.json",
        "sha256": "f40dca7251efe41c3b71d4f6bb43e5e726df6d0257868ea2e04f60f78b39405d"
      }
    ],
    "events": []
  },
  "network_telemetry_evidence": {
    "sources": [
      {
        "source_name": "zeek_conn",
        "file": "conn.log",
        "match_methods": [
          "ip_match"
        ]
      }
    ],
    "key_events": [
      {
        "source": "zeek_conn",
        "match_method": "ip_match",
        "timestamp": "1777117748.173587",
        "src_ip": "192.168.101.183",
        "src_port": "34820",
        "dest_ip": "192.168.101.1",
        "dest_port": "53",
        "proto": "udp",
        "service": "-",
        "connection_uid": "C6kAey1Xwhov3qtrq7"
      },
      {
        "source": "zeek_conn",
        "match_method": "ip_match",
        "timestamp": "1777117748.166485",
        "src_ip": "192.168.101.183",
        "src_port": "44587",
        "dest_ip": "192.168.101.1",
        "dest_port": "53",
        "proto": "udp",
        "service": "-",
        "connection_uid": "C4EWG11CY3dcG4SO2k"
      },
      {
        "source": "zeek_conn",
        "match_method": "ip_match",
        "timestamp": "1777117748.175578",
        "src_ip": "192.168.101.183",
        "src_port": "44736",
        "dest_ip": "192.168.101.1",
        "dest_port": "53",
        "proto": "udp",
        "service": "-",
        "connection_uid": "CYnQA64Ym1fVz61psf"
      },
      {
        "source": "zeek_conn",
        "match_method": "ip_match",
        "timestamp": "1777117748.171940",
        "src_ip": "192.168.101.183",
        "src_port": "33002",
        "dest_ip": "192.168.101.1",
        "dest_port": "53",
        "proto": "udp",
        "service": "-",
        "connection_uid": "C1lRqy4bvul27cdp89"
      },
      {
        "source": "zeek_conn",
        "match_method": "ip_match",
        "timestamp": "1777117748.172079",
        "src_ip": "192.168.101.183",
        "src_port": "44857",
        "dest_ip": "192.168.101.1",
        "dest_port": "53",
        "proto": "udp",
        "service": "-",
        "connection_uid": "CG1EP33lnYCNdl0qEc"
      },
      {
        "source": "zeek_conn",
        "match_method": "ip_match",
        "timestamp": "1777117750.187661",
        "src_ip": "192.168.101.183",
        "src_port": "56803",
        "dest_ip": "192.168.101.1",
        "dest_port": "53",
        "proto": "udp",
        "service": "-",
        "connection_uid": "CXt6WU1G6duvc1nZo6"
      },
      {
        "source": "zeek_conn",
        "match_method": "ip_match",
        "timestamp": "1777117750.187631",
        "src_ip": "192.168.101.183",
        "src_port": "49206",
        "dest_ip": "192.168.101.1",
        "dest_port": "53",
        "proto": "udp",
        "service": "-",
        "connection_uid": "C0hFj01W1mlSxg7JZe"
      },
      {
        "source": "zeek_conn",
        "match_method": "ip_match",
        "timestamp": "1777117750.300124",
        "src_ip": "192.168.101.183",
        "src_port": "44681",
        "dest_ip": "192.168.101.1",
        "dest_port": "53",
        "proto": "udp",
        "service": "-",
        "connection_uid": "CpLl6B2klInBLm3Zdl"
      },
      {
        "source": "zeek_conn",
        "match_method": "ip_match",
        "timestamp": "1777117750.296382",
        "src_ip": "192.168.101.183",
        "src_port": "50982",
        "dest_ip": "192.168.101.1",
        "dest_port": "53",
        "proto": "udp",
        "service": "-",
        "connection_uid": "Ccnydf3OTNEhfeL3Bh"
      },
      {
        "source": "zeek_conn",
        "match_method": "ip_match",
        "timestamp": "1777117750.197436",
        "src_ip": "192.168.101.183",
        "src_port": "42895",
        "dest_ip": "142.251.47.99",
        "dest_port": "443",
        "proto": "udp",
        "service": "-",
        "connection_uid": "Cmx5ls1cKjrGpGCCW4"
      },
      {
        "source": "zeek_conn",
        "match_method": "ip_match",
        "timestamp": "1777117750.774093",
        "src_ip": "192.168.101.183",
        "src_port": "53317",
        "dest_ip": "192.168.101.1",
        "dest_port": "53",
        "proto": "udp",
        "service": "-",
        "connection_uid": "CfSWOS1Ove40RnOqXa"
      },
      {
        "source": "zeek_conn",
        "match_method": "ip_match",
        "timestamp": "1777117750.774221",
        "src_ip": "192.168.101.183",
        "src_port": "47109",
        "dest_ip": "192.168.101.1",
        "dest_port": "53",
        "proto": "udp",
        "service": "-",
        "connection_uid": "C06q4e4Kn1owG9Rua6"
      }
    ],
    "observed": true
  },
  "analytic_evidence": {
    "sigma": [],
    "osquery": [
      {
        "query_id": "OSQ-T1104_C2_SOCKETS",
        "name": "t1104_c2_sockets",
        "query_text": "SELECT p.pid, p.name, p.path, p.cmdline, s.remote_address, s.remote_port, s.state FROM process_open_sockets s JOIN processes p ON s.pid = p.pid WHERE s.remote_address != '' AND s.remote_address != '127.0.0.1' AND s.remote_address != '::1' AND s.state = 'ESTABLISHED' LIMIT 100;",
        "matched": false,
        "result_count": 0,
        "supporting_event_ids": []
      },
      {
        "query_id": "OSQ-T1104_DNS_CACHE",
        "name": "t1104_dns_cache",
        "query_text": "SELECT pid, fd, socket, remote_address, remote_port FROM process_open_sockets WHERE remote_port = 53 LIMIT 50;",
        "matched": false,
        "result_count": 0,
        "supporting_event_ids": []
      }
    ],
    "custom": []
  },
  "detection_evidence": {
    "observed": false,
    "sigma_matches": [],
    "osquery_matches": []
  },
  "artifact_evidence": {
    "files": [
      {
        "path": "/opt/atomic-red-team/atomics",
        "hashes": [
          "f8565c05ddbe3a05ace5ba95d28067c1f3ca85cd06c82e5065a99e37fe89b751",
          "e3b0c44298fc1c149afbf4c8996fb92427ae41e4649b934ca495991b7852b855",
          "4ee986c89c1179692bb5f123f3fdd33247c190303bd956874f60ff1a536b7148",
          "07dfaba6adc3114171c42e5443dd8416b80dc8dc5c9e22fc444a4554dd5f69e1",
          "64aaadd7321fc533e3588bd2cca4e50eee85f54c12804efab4f25c57da0385f4",
          "e0b07ab572c9dbfc9ec373bbe59ae4e6be32e41fd73c9a49343208f71b067e58"
        ]
      },
      {
        "path": "/1.1",
        "hashes": [
          "f8565c05ddbe3a05ace5ba95d28067c1f3ca85cd06c82e5065a99e37fe89b751",
          "e3b0c44298fc1c149afbf4c8996fb92427ae41e4649b934ca495991b7852b855",
          "4ee986c89c1179692bb5f123f3fdd33247c190303bd956874f60ff1a536b7148",
          "07dfaba6adc3114171c42e5443dd8416b80dc8dc5c9e22fc444a4554dd5f69e1",
          "64aaadd7321fc533e3588bd2cca4e50eee85f54c12804efab4f25c57da0385f4",
          "e0b07ab572c9dbfc9ec373bbe59ae4e6be32e41fd73c9a49343208f71b067e58"
        ]
      },
      {
        "path": "/json",
        "hashes": [
          "f8565c05ddbe3a05ace5ba95d28067c1f3ca85cd06c82e5065a99e37fe89b751",
          "e3b0c44298fc1c149afbf4c8996fb92427ae41e4649b934ca495991b7852b855",
          "4ee986c89c1179692bb5f123f3fdd33247c190303bd956874f60ff1a536b7148",
          "07dfaba6adc3114171c42e5443dd8416b80dc8dc5c9e22fc444a4554dd5f69e1",
          "64aaadd7321fc533e3588bd2cca4e50eee85f54c12804efab4f25c57da0385f4",
          "e0b07ab572c9dbfc9ec373bbe59ae4e6be32e41fd73c9a49343208f71b067e58"
        ]
      },
      {
        "path": "/var/lib/seraph-ai/artifacts/soar_executions_archive.json",
        "hashes": [
          "f8565c05ddbe3a05ace5ba95d28067c1f3ca85cd06c82e5065a99e37fe89b751",
          "e3b0c44298fc1c149afbf4c8996fb92427ae41e4649b934ca495991b7852b855",
          "4ee986c89c1179692bb5f123f3fdd33247c190303bd956874f60ff1a536b7148",
          "07dfaba6adc3114171c42e5443dd8416b80dc8dc5c9e22fc444a4554dd5f69e1",
          "64aaadd7321fc533e3588bd2cca4e50eee85f54c12804efab4f25c57da0385f4",
          "e0b07ab572c9dbfc9ec373bbe59ae4e6be32e41fd73c9a49343208f71b067e58"
        ]
      }
    ],
    "hashes": [
      "f8565c05ddbe3a05ace5ba95d28067c1f3ca85cd06c82e5065a99e37fe89b751",
      "e3b0c44298fc1c149afbf4c8996fb92427ae41e4649b934ca495991b7852b855",
      "4ee986c89c1179692bb5f123f3fdd33247c190303bd956874f60ff1a536b7148",
      "07dfaba6adc3114171c42e5443dd8416b80dc8dc5c9e22fc444a4554dd5f69e1",
      "64aaadd7321fc533e3588bd2cca4e50eee85f54c12804efab4f25c57da0385f4",
      "e0b07ab572c9dbfc9ec373bbe59ae4e6be32e41fd73c9a49343208f71b067e58",
      "f2bb6544fa0fd2982893bcbd1b7c1dad92fffaddba4abba1533b38b63c8ce163",
      "9f0615fd399a8dcf598fc5c06be6d781c2418f77d84a117f0a8bbfeff2f48d4c",
      "fadcc2c3dd2e7dae97c23209615a492d2c3ae4db2afc3d50b373af2e623ec626",
      "730194c70b1cad453fd87371a614a0195b23aaf4a13075022ca2453a46e3a0fb",
      "590867cce484e05be469b56f0845e076f85f3a4d3851288a805dce48d185478d"
    ],
    "observed": true
  },
  "response_evidence": {
    "executions": [
      {
        "execution_id": "exec_integ_5eab4235c07b",
        "playbook_id": "pb_generic_response",
        "playbook_name": "Generic Threat Response",
        "status": "completed",
        "started_at": "2026-04-27T02:14:51.454165+00:00",
        "completed_at": "2026-04-27T02:14:51.454165+00:00",
        "host_id": "metatron-lab-a",
        "source_ip": "192.168.101.183",
        "session_id": "sess_t1104",
        "pid": 0,
        "file_path": "",
        "reason": "Seraph SOAR automated response to detected T1104 activity",
        "step_results": [
          {
            "step_id": "step_1",
            "action": "alert_soc_analyst",
            "status": "completed",
            "completed_at": "2026-04-27T02:14:51.454165+00:00",
            "result": {
              "action": "alert_soc_analyst",
              "status": "completed",
              "timestamp": "2026-04-27T02:14:51.454165+00:00",
              "host_id": "metatron-lab-a",
              "session_id": "sess_t1104"
            }
          },
          {
            "step_id": "step_2",
            "action": "increase_logging_verbosity",
            "status": "completed",
            "completed_at": "2026-04-27T02:14:51.454165+00:00",
            "result": {
              "action": "increase_logging_verbosity",
              "status": "completed",
              "timestamp": "2026-04-27T02:14:51.454165+00:00",
              "host_id": "metatron-lab-a",
              "session_id": "sess_t1104"
            }
          },
          {
            "step_id": "step_3",
            "action": "create_threat_hunt_task",
            "status": "completed",
            "completed_at": "2026-04-27T02:14:51.454165+00:00",
            "result": {
              "action": "create_threat_hunt_task",
              "status": "completed",
              "timestamp": "2026-04-27T02:14:51.454165+00:00",
              "host_id": "metatron-lab-a",
              "session_id": "sess_t1104"
            }
          }
        ],
        "source_file": "/var/lib/seraph-ai/artifacts/soar_executions_archive.json"
      },
      {
        "execution_id": "exec_integ_5eab4235c07b",
        "playbook_id": "pb_generic_response",
        "playbook_name": "Generic Threat Response",
        "status": "completed",
        "started_at": "2026-04-27T02:14:51.454165+00:00",
        "completed_at": "2026-04-27T02:14:51.454165+00:00",
        "host_id": "metatron-lab-a",
        "source_ip": "192.168.101.183",
        "session_id": "sess_t1104",
        "pid": 0,
        "file_path": "",
        "reason": "Seraph SOAR automated response to detected T1104 activity",
        "step_results": [
          {
            "step_id": "step_1",
            "action": "alert_soc_analyst",
            "status": "completed",
            "completed_at": "2026-04-27T02:14:51.454165+00:00",
            "result": {
              "action": "alert_soc_analyst",
              "status": "completed",
              "timestamp": "2026-04-27T02:14:51.454165+00:00",
              "host_id": "metatron-lab-a",
              "session_id": "sess_t1104"
            }
          },
          {
            "step_id": "step_2",
            "action": "increase_logging_verbosity",
            "status": "completed",
            "completed_at": "2026-04-27T02:14:51.454165+00:00",
            "result": {
              "action": "increase_logging_verbosity",
              "status": "completed",
              "timestamp": "2026-04-27T02:14:51.454165+00:00",
              "host_id": "metatron-lab-a",
              "session_id": "sess_t1104"
            }
          },
          {
            "step_id": "step_3",
            "action": "create_threat_hunt_task",
            "status": "completed",
            "completed_at": "2026-04-27T02:14:51.454165+00:00",
            "result": {
              "action": "create_threat_hunt_task",
              "status": "completed",
              "timestamp": "2026-04-27T02:14:51.454165+00:00",
              "host_id": "metatron-lab-a",
              "session_id": "sess_t1104"
            }
          }
        ],
        "source_file": "/var/lib/seraph-ai/artifacts/soar_executions_archive.json"
      },
      {
        "execution_id": "exec_integ_5eab4235c07b",
        "playbook_id": "pb_generic_response",
        "playbook_name": "Generic Threat Response",
        "status": "completed",
        "started_at": "2026-04-27T02:14:51.454165+00:00",
        "completed_at": "2026-04-27T02:14:51.454165+00:00",
        "host_id": "metatron-lab-a",
        "source_ip": "192.168.101.183",
        "session_id": "sess_t1104",
        "pid": 0,
        "file_path": "",
        "reason": "Seraph SOAR automated response to detected T1104 activity",
        "step_results": [
          {
            "step_id": "step_1",
            "action": "alert_soc_analyst",
            "status": "completed",
            "completed_at": "2026-04-27T02:14:51.454165+00:00",
            "result": {
              "action": "alert_soc_analyst",
              "status": "completed",
              "timestamp": "2026-04-27T02:14:51.454165+00:00",
              "host_id": "metatron-lab-a",
              "session_id": "sess_t1104"
            }
          },
          {
            "step_id": "step_2",
            "action": "increase_logging_verbosity",
            "status": "completed",
            "completed_at": "2026-04-27T02:14:51.454165+00:00",
            "result": {
              "action": "increase_logging_verbosity",
              "status": "completed",
              "timestamp": "2026-04-27T02:14:51.454165+00:00",
              "host_id": "metatron-lab-a",
              "session_id": "sess_t1104"
            }
          },
          {
            "step_id": "step_3",
            "action": "create_threat_hunt_task",
            "status": "completed",
            "completed_at": "2026-04-27T02:14:51.454165+00:00",
            "result": {
              "action": "create_threat_hunt_task",
              "status": "completed",
              "timestamp": "2026-04-27T02:14:51.454165+00:00",
              "host_id": "metatron-lab-a",
              "session_id": "sess_t1104"
            }
          }
        ],
        "source_file": "/var/lib/seraph-ai/artifacts/soar_executions_archive.json"
      }
    ],
    "actions": [
      {
        "execution_id": "exec_integ_5eab4235c07b",
        "playbook_id": "pb_generic_response",
        "playbook_name": "Generic Threat Response",
        "action": "alert_soc_analyst",
        "status": "completed",
        "timestamp": "2026-04-27T02:14:51.454165+00:00",
        "host_id": "metatron-lab-a",
        "session_id": "sess_t1104"
      },
      {
        "execution_id": "exec_integ_5eab4235c07b",
        "playbook_id": "pb_generic_response",
        "playbook_name": "Generic Threat Response",
        "action": "increase_logging_verbosity",
        "status": "completed",
        "timestamp": "2026-04-27T02:14:51.454165+00:00",
        "host_id": "metatron-lab-a",
        "session_id": "sess_t1104"
      },
      {
        "execution_id": "exec_integ_5eab4235c07b",
        "playbook_id": "pb_generic_response",
        "playbook_name": "Generic Threat Response",
        "action": "create_threat_hunt_task",
        "status": "completed",
        "timestamp": "2026-04-27T02:14:51.454165+00:00",
        "host_id": "metatron-lab-a",
        "session_id": "sess_t1104"
      },
      {
        "execution_id": "exec_integ_5eab4235c07b",
        "playbook_id": "pb_generic_response",
        "playbook_name": "Generic Threat Response",
        "action": "alert_soc_analyst",
        "status": "completed",
        "timestamp": "2026-04-27T02:14:51.454165+00:00",
        "host_id": "metatron-lab-a",
        "session_id": "sess_t1104"
      },
      {
        "execution_id": "exec_integ_5eab4235c07b",
        "playbook_id": "pb_generic_response",
        "playbook_name": "Generic Threat Response",
        "action": "increase_logging_verbosity",
        "status": "completed",
        "timestamp": "2026-04-27T02:14:51.454165+00:00",
        "host_id": "metatron-lab-a",
        "session_id": "sess_t1104"
      },
      {
        "execution_id": "exec_integ_5eab4235c07b",
        "playbook_id": "pb_generic_response",
        "playbook_name": "Generic Threat Response",
        "action": "create_threat_hunt_task",
        "status": "completed",
        "timestamp": "2026-04-27T02:14:51.454165+00:00",
        "host_id": "metatron-lab-a",
        "session_id": "sess_t1104"
      },
      {
        "execution_id": "exec_integ_5eab4235c07b",
        "playbook_id": "pb_generic_response",
        "playbook_name": "Generic Threat Response",
        "action": "alert_soc_analyst",
        "status": "completed",
        "timestamp": "2026-04-27T02:14:51.454165+00:00",
        "host_id": "metatron-lab-a",
        "session_id": "sess_t1104"
      },
      {
        "execution_id": "exec_integ_5eab4235c07b",
        "playbook_id": "pb_generic_response",
        "playbook_name": "Generic Threat Response",
        "action": "increase_logging_verbosity",
        "status": "completed",
        "timestamp": "2026-04-27T02:14:51.454165+00:00",
        "host_id": "metatron-lab-a",
        "session_id": "sess_t1104"
      },
      {
        "execution_id": "exec_integ_5eab4235c07b",
        "playbook_id": "pb_generic_response",
        "playbook_name": "Generic Threat Response",
        "action": "create_threat_hunt_task",
        "status": "completed",
        "timestamp": "2026-04-27T02:14:51.454165+00:00",
        "host_id": "metatron-lab-a",
        "session_id": "sess_t1104"
      }
    ],
    "observed": true
  },
  "correlation": {
    "direct_detection": false,
    "correlated_detection": true,
    "evidence_chain": [
      "execution.command_line",
      "network_telemetry_evidence.key_events[0]",
      "artifact_evidence.files[0]",
      "response_evidence.actions[0]"
    ],
    "anchors": {
      "timestamp_window": {
        "first_seen": "2026-04-27T10:09:06.585147+00:00",
        "last_seen": "1777117750.774221",
        "samples": [
          "2026-04-27T10:09:06.585147+00:00",
          "2026-04-27T10:14:54.898131+00:00",
          "2026-04-27T10:01:43.926359+00:00",
          "2026-04-27T10:09:08.364855+00:00",
          "2026-04-27T10:14:57.525084+00:00",
          "2026-04-27T10:09:06.833487+00:00",
          "2026-04-27T10:09:07.853287+00:00",
          "2026-04-27T10:14:53.984351+00:00"
        ]
      },
      "host_ids": [
        "metatron-lab-a"
      ],
      "process_ids": [
        0
      ],
      "ip_addresses": [
        "192.168.101.183",
        "192.168.101.1",
        "142.251.47.99"
      ],
      "file_paths": [
        "/opt/atomic-red-team/atomics",
        "/1.1",
        "/json",
        "/var/lib/seraph-ai/artifacts/soar_executions_archive.json"
      ],
      "hashes": [
        "f8565c05ddbe3a05ace5ba95d28067c1f3ca85cd06c82e5065a99e37fe89b751",
        "e3b0c44298fc1c149afbf4c8996fb92427ae41e4649b934ca495991b7852b855",
        "4ee986c89c1179692bb5f123f3fdd33247c190303bd956874f60ff1a536b7148",
        "07dfaba6adc3114171c42e5443dd8416b80dc8dc5c9e22fc444a4554dd5f69e1",
        "64aaadd7321fc533e3588bd2cca4e50eee85f54c12804efab4f25c57da0385f4",
        "e0b07ab572c9dbfc9ec373bbe59ae4e6be32e41fd73c9a49343208f71b067e58",
        "f2bb6544fa0fd2982893bcbd1b7c1dad92fffaddba4abba1533b38b63c8ce163",
        "9f0615fd399a8dcf598fc5c06be6d781c2418f77d84a117f0a8bbfeff2f48d4c",
        "fadcc2c3dd2e7dae97c23209615a492d2c3ae4db2afc3d50b373af2e623ec626",
        "730194c70b1cad453fd87371a614a0195b23aaf4a13075022ca2453a46e3a0fb",
        "590867cce484e05be469b56f0845e076f85f3a4d3851288a805dce48d185478d"
      ],
      "event_ids": []
    },
    "story_assessment": {
      "present_layers": [
        "execution",
        "host_telemetry",
        "network_telemetry",
        "artifact",
        "response"
      ],
      "missing_layers": [
        "detection"
      ],
      "layer_count": 5,
      "anchor_counts": {
        "host_ids": 1,
        "process_ids": 1,
        "ip_addresses": 3,
        "file_paths": 4,
        "hashes": 11,
        "event_ids": 0
      },
      "has_anchor_overlap": true,
      "perfect_story": false
    }
  },
  "quality": {
    "repeated_runs": 22,
    "successful_detections": 22,
    "effective_runs": 22,
    "unique_successful_direct_run_ids": [
      "0ee121e7b010417a_T1104",
      "19c8f027d99e4dbe_T1104",
      "1fe7b0052aab4d32_T1104",
      "38f945bd402e4900_T1104",
      "401874dcebd243f3_T1104",
      "4d88beb65df94713_T1104",
      "530f956d8d754afa_T1104",
      "5980b09764c14726_T1104",
      "59c5891731cd4275_T1104",
      "5ab7fea961ee454b_T1104",
      "6c85bb43d63347bd_T1104",
      "6e825e26e9664fd4_T1104",
      "7b18097e84d044e4_T1104",
      "81608275e05e4461_T1104",
      "9019b42e6ff340ad_T1104",
      "962c4dee70d2451a_T1104",
      "a0384ce3386540cd_T1104",
      "aceff3707fb94858_T1104",
      "c7611e0b74854458_T1104",
      "ead45bc241494f5e_T1104",
      "f93081127833474c_T1104",
      "ff0f5d61c67a4495_T1104"
    ],
    "clean_run_count": 22,
    "quality_run_count": 22,
    "run_validity_summary": {
      "success_clean": 22
    },
    "has_fatal_stdout_markers": false,
    "has_vns_or_simulation_only": false,
    "evidence_inheritance": "direct",
    "execution_source": "docker_sandbox",
    "osquery_status": "mapped_only",
    "baseline_window_minutes": 60,
    "baseline_false_positives": 0,
    "analyst_reviewed": true,
    "reviewer": "Byron Bunt",
    "review_class": "internal_author_reviewed",
    "reviewed_at": "2026-04-27T10:15:45.242216+00:00"
  },
  "story": {
    "goal": "one_event_many_witnesses_one_story",
    "layered_presence": {
      "execution": true,
      "host_telemetry": true,
      "network_telemetry": true,
      "detection": false,
      "artifact": true,
      "response": true
    },
    "assessment": {
      "present_layers": [
        "execution",
        "host_telemetry",
        "network_telemetry",
        "artifact",
        "response"
      ],
      "missing_layers": [
        "detection"
      ],
      "layer_count": 5,
      "anchor_counts": {
        "host_ids": 1,
        "process_ids": 1,
        "ip_addresses": 3,
        "file_paths": 4,
        "hashes": 11,
        "event_ids": 0
      },
      "has_anchor_overlap": true,
      "perfect_story": false
    },
    "narrative": "Execution, telemetry, detections, artifacts, network observations, and SOAR response are tracked as separate witnesses and tied together through shared anchors."
  },
  "promotion": {
    "score": 2,
    "tier": "S2",
    "tier_name": "bronze",
    "certification_tier": "S3",
    "certification_label": "silver",
    "status": "partial",
    "reason": "S2 Bronze \u2014 mapping only: 0 Sigma rules + 2 osquery queries exist for this technique; no successful execution evidence."
  },
  "integrity": {
    "record_sha256": "6c3dd271a4de00acd72fa215408026d1fa27fd7f2d3241aa79306ffc09cdb0bd",
    "hash_method": "SHA-256 of canonical JSON (sort_keys=True, default=str) excluding the integrity block itself",
    "created_at": "2026-04-27T10:15:45.242216+00:00"
  }
}