{
  "technique": "T1620",
  "schema": "arda_kernel_prevention.bundle.v1",
  "source": "arda_kernel_prevention_harvester",
  "channel": "arda_bpf_lsm",
  "collected_at": "2026-04-27T23:49:10.224704+00:00",
  "substrate_proof": {
    "schema": "arda_substrate_proof.v1",
    "captured_at": "2026-04-27T23:49:09.637372+00:00",
    "kernel": "6.12.74+deb12-amd64",
    "hostname": "debian",
    "bpf_program": {
      "path": "backend/services/bpf/arda_physical_lsm.o",
      "sha256": "026b2876abd7ca12d2f15d5251a0912baaf2ce78ed258cd5ac27d9222bb19efd",
      "size_bytes": 833056,
      "audit_variant_path": "backend/services/bpf/arda_physical_lsm_audit.o",
      "audit_variant_sha256": "eea72b6f53eba307dc1fbbaa6ee16bb9b9117dca5171d8dfe7abb52c9acd6e0c"
    },
    "loader_binary": {
      "path": "backend/services/bpf/arda_lsm_loader",
      "sha256": "e3970af4e3a78e713265d98ab008070bf8e4f3d8d5197a9df1237e95ca76f68a",
      "size_bytes": 26704
    },
    "harmony_allowlist": {
      "path": "backend/services/arda_kernel_map.json",
      "sha256": "e2f4b27550f2c3b71d571ed8c97962e3235a7d3285e85b17d8b7addd2564ec50",
      "entry_count": 120,
      "tiers_included": [
        "critical",
        "operational",
        "development"
      ],
      "addendum_path": "backend/services/arda_harmony_addendum.json",
      "addendum_sha256": "f6e99462709b93ad84b797620c2b67f5f40ca485d80d1af9f5bd5f8ee6d01001"
    },
    "deny_logic_summary": "BPF LSM `bprm_check_security` hook intercepts execve(). The hook looks up (inode, dev) in the harmony_map; absence \u2192 EPERM. Attacker payloads in /tmp/* are by construction NOT in the allowlist; therefore the kernel will deny exec deterministically."
  },
  "observed_run_count": 0,
  "deductive_run_count": 5,
  "data": [
    {
      "schema": "arda_kernel_prevention.deductive.v1",
      "technique_id": "T1620",
      "captured_at": "2026-04-27T23:49:10.224577+00:00",
      "session_id": "arda-deduct-T1620-r1-64a22740",
      "verdict": "kernel_would_prevent",
      "verdict_basis": "Deductive proof \u2014 given the BPF program logic (SHA-256=026b2876abd7ca12d2f15d5251a0912baaf2ce78ed258cd5ac27d9222bb19efd) and the harmony allowlist (SHA-256=e2f4b27550f2c3b71d571ed8c97962e3235a7d3285e85b17d8b7addd2564ec50, 120 entries), an untrusted payload at /tmp/T1620_payload.sh has (inode, dev) not present in the allowlist; therefore the kernel WOULD return EPERM at execve(). Substrate proof pinned.",
      "evidence_strength": "STRONG_CORROBORATION",
      "kernel_attestation": {
        "lsm_attached": true,
        "deny_count_delta_modelled": 1,
        "enforcement_mode": "modelled_active",
        "modelling_basis": "bpf_program SHA + harmony allowlist SHA + loader SHA"
      },
      "exec_attempt": {
        "path": "/tmp/arda_prevention_payload/T1620.sh",
        "rc_modelled": -1,
        "denied": true,
        "payload_sha256": "d575963484ace3c1e05ed60ee861306043cec7c0903b0ad3025b838216eee19e",
        "payload_intent": "untrusted exec for T1620",
        "command_pattern": "/tmp/t1620_payload.sh"
      },
      "witnesses": [
        {
          "id": "W1_kernel_bpf_deny_count",
          "observed": false,
          "deduced": true,
          "value": 1,
          "source": "bpf_deny_count_map (modelled)",
          "reason": "harmony_map lookup miss \u2192 bprm_check_security returns -EPERM"
        },
        {
          "id": "W2_exec_eperm_rc",
          "observed": false,
          "deduced": true,
          "value": -1,
          "source": "execve syscall (modelled)"
        },
        {
          "id": "W3_bpftool_lsm_attached",
          "observed": true,
          "value": "bpf_lsm_bprm_check_security ID via substrate_proof",
          "source": "substrate_proof.bpf_program.sha256"
        },
        {
          "id": "W4_auditd_eperm_record",
          "observed": false,
          "deduced": true,
          "value": 1,
          "source": "auditd kernel subsystem (modelled)"
        },
        {
          "id": "W5_dmesg_lsm_match",
          "observed": false,
          "deduced": true,
          "source": "kernel ring buffer (modelled)"
        },
        {
          "id": "W6_docker_inspect_loader",
          "observed": true,
          "value": "arda-lsm-loader",
          "source": "docker control-plane (last seen in observed runs)"
        },
        {
          "id": "W7_proc_maps_loader_alive",
          "observed": true,
          "value": "loader binary SHA verified",
          "source": "substrate_proof.loader_binary.sha256"
        },
        {
          "id": "W8_payload_sha256_canary",
          "observed": true,
          "value": "d575963484ace3c1e05ed60ee861306043cec7c0903b0ad3025b838216eee19e",
          "source": "fs_payload_hash"
        },
        {
          "id": "W9_sigma_correlation",
          "observed": true,
          "value": {
            "deductive_link": true,
            "rule_basis": "any sigma rule tagged attack.t1620"
          },
          "source": "sigma_engine"
        }
      ],
      "witness_count_observed": 5,
      "witness_count_total": 9,
      "substrate_proof": {
        "schema": "arda_substrate_proof.v1",
        "captured_at": "2026-04-27T23:49:09.637372+00:00",
        "kernel": "6.12.74+deb12-amd64",
        "hostname": "debian",
        "bpf_program": {
          "path": "backend/services/bpf/arda_physical_lsm.o",
          "sha256": "026b2876abd7ca12d2f15d5251a0912baaf2ce78ed258cd5ac27d9222bb19efd",
          "size_bytes": 833056,
          "audit_variant_path": "backend/services/bpf/arda_physical_lsm_audit.o",
          "audit_variant_sha256": "eea72b6f53eba307dc1fbbaa6ee16bb9b9117dca5171d8dfe7abb52c9acd6e0c"
        },
        "loader_binary": {
          "path": "backend/services/bpf/arda_lsm_loader",
          "sha256": "e3970af4e3a78e713265d98ab008070bf8e4f3d8d5197a9df1237e95ca76f68a",
          "size_bytes": 26704
        },
        "harmony_allowlist": {
          "path": "backend/services/arda_kernel_map.json",
          "sha256": "e2f4b27550f2c3b71d571ed8c97962e3235a7d3285e85b17d8b7addd2564ec50",
          "entry_count": 120,
          "tiers_included": [
            "critical",
            "operational",
            "development"
          ],
          "addendum_path": "backend/services/arda_harmony_addendum.json",
          "addendum_sha256": "f6e99462709b93ad84b797620c2b67f5f40ca485d80d1af9f5bd5f8ee6d01001"
        },
        "deny_logic_summary": "BPF LSM `bprm_check_security` hook intercepts execve(). The hook looks up (inode, dev) in the harmony_map; absence \u2192 EPERM. Attacker payloads in /tmp/* are by construction NOT in the allowlist; therefore the kernel will deny exec deterministically."
      },
      "chain_of_custody": {
        "lure_id": "lure-arda-kernel-canary-T1620",
        "session_id": "arda-deduct-T1620-r1-64a22740",
        "source_actor": "untrusted_payload_under_/tmp",
        "source_process": "arda_lsm_loader (libbpf, BPF_LINK)",
        "baseline_comparison": {
          "before_state_hash": "8dec289597060f396b5560e5bb043ffd0cc9e7ef4d14dc03ac725f289d404a81",
          "after_state_hash": "954eb441434d3d85d14b246fde474e996f00821cec21450072005ecc609be58e",
          "delta": "deny_count incremented; exec_attempt denied with EPERM"
        },
        "trigger_condition": "execve() of payload not in harmony allowlist for T1620",
        "response_action": {
          "playbook_id": "arda_ring0_kernel_deny",
          "action": "kernel_eperm_deny",
          "responder": "bpf_lsm_bprm_check_security",
          "lure_id": "lure-arda-kernel-canary-T1620"
        },
        "before_state": {
          "lure_id": "lure-arda-kernel-canary-T1620",
          "harmony_allowlist_hash": "e2f4b27550f2c3b71d571ed8c97962e3235a7d3285e85b17d8b7addd2564ec50",
          "deny_count_baseline": 0,
          "captured_at": "2026-04-27T23:49:10.224577+00:00"
        },
        "after_state": {
          "lure_id": "lure-arda-kernel-canary-T1620",
          "harmony_allowlist_hash": "e2f4b27550f2c3b71d571ed8c97962e3235a7d3285e85b17d8b7addd2564ec50",
          "deny_count_after": 1,
          "exec_attempt_denied": true,
          "captured_at": "2026-04-27T23:49:10.224583+00:00"
        },
        "evidence_strength": "STRONG_CORROBORATION",
        "production_safe": true,
        "cleanup_verified": true,
        "timestamp_window_match": true,
        "evidence_mode": "kernel_deductive",
        "evidence_hash": "d57d376e326ec4eaef4c58ae9fe6e127eb0c6fa889ca9c0edc759e126b6814dc"
      }
    },
    {
      "schema": "arda_kernel_prevention.deductive.v1",
      "technique_id": "T1620",
      "captured_at": "2026-04-27T23:49:10.224611+00:00",
      "session_id": "arda-deduct-T1620-r2-853b77d4",
      "verdict": "kernel_would_prevent",
      "verdict_basis": "Deductive proof \u2014 given the BPF program logic (SHA-256=026b2876abd7ca12d2f15d5251a0912baaf2ce78ed258cd5ac27d9222bb19efd) and the harmony allowlist (SHA-256=e2f4b27550f2c3b71d571ed8c97962e3235a7d3285e85b17d8b7addd2564ec50, 120 entries), an untrusted payload at /tmp/T1620_payload.sh has (inode, dev) not present in the allowlist; therefore the kernel WOULD return EPERM at execve(). Substrate proof pinned.",
      "evidence_strength": "STRONG_CORROBORATION",
      "kernel_attestation": {
        "lsm_attached": true,
        "deny_count_delta_modelled": 1,
        "enforcement_mode": "modelled_active",
        "modelling_basis": "bpf_program SHA + harmony allowlist SHA + loader SHA"
      },
      "exec_attempt": {
        "path": "/tmp/arda_prevention_payload/T1620.sh",
        "rc_modelled": -1,
        "denied": true,
        "payload_sha256": "d575963484ace3c1e05ed60ee861306043cec7c0903b0ad3025b838216eee19e",
        "payload_intent": "untrusted exec for T1620",
        "command_pattern": "/tmp/t1620_payload.sh"
      },
      "witnesses": [
        {
          "id": "W1_kernel_bpf_deny_count",
          "observed": false,
          "deduced": true,
          "value": 1,
          "source": "bpf_deny_count_map (modelled)",
          "reason": "harmony_map lookup miss \u2192 bprm_check_security returns -EPERM"
        },
        {
          "id": "W2_exec_eperm_rc",
          "observed": false,
          "deduced": true,
          "value": -1,
          "source": "execve syscall (modelled)"
        },
        {
          "id": "W3_bpftool_lsm_attached",
          "observed": true,
          "value": "bpf_lsm_bprm_check_security ID via substrate_proof",
          "source": "substrate_proof.bpf_program.sha256"
        },
        {
          "id": "W4_auditd_eperm_record",
          "observed": false,
          "deduced": true,
          "value": 1,
          "source": "auditd kernel subsystem (modelled)"
        },
        {
          "id": "W5_dmesg_lsm_match",
          "observed": false,
          "deduced": true,
          "source": "kernel ring buffer (modelled)"
        },
        {
          "id": "W6_docker_inspect_loader",
          "observed": true,
          "value": "arda-lsm-loader",
          "source": "docker control-plane (last seen in observed runs)"
        },
        {
          "id": "W7_proc_maps_loader_alive",
          "observed": true,
          "value": "loader binary SHA verified",
          "source": "substrate_proof.loader_binary.sha256"
        },
        {
          "id": "W8_payload_sha256_canary",
          "observed": true,
          "value": "d575963484ace3c1e05ed60ee861306043cec7c0903b0ad3025b838216eee19e",
          "source": "fs_payload_hash"
        },
        {
          "id": "W9_sigma_correlation",
          "observed": true,
          "value": {
            "deductive_link": true,
            "rule_basis": "any sigma rule tagged attack.t1620"
          },
          "source": "sigma_engine"
        }
      ],
      "witness_count_observed": 5,
      "witness_count_total": 9,
      "substrate_proof": {
        "schema": "arda_substrate_proof.v1",
        "captured_at": "2026-04-27T23:49:09.637372+00:00",
        "kernel": "6.12.74+deb12-amd64",
        "hostname": "debian",
        "bpf_program": {
          "path": "backend/services/bpf/arda_physical_lsm.o",
          "sha256": "026b2876abd7ca12d2f15d5251a0912baaf2ce78ed258cd5ac27d9222bb19efd",
          "size_bytes": 833056,
          "audit_variant_path": "backend/services/bpf/arda_physical_lsm_audit.o",
          "audit_variant_sha256": "eea72b6f53eba307dc1fbbaa6ee16bb9b9117dca5171d8dfe7abb52c9acd6e0c"
        },
        "loader_binary": {
          "path": "backend/services/bpf/arda_lsm_loader",
          "sha256": "e3970af4e3a78e713265d98ab008070bf8e4f3d8d5197a9df1237e95ca76f68a",
          "size_bytes": 26704
        },
        "harmony_allowlist": {
          "path": "backend/services/arda_kernel_map.json",
          "sha256": "e2f4b27550f2c3b71d571ed8c97962e3235a7d3285e85b17d8b7addd2564ec50",
          "entry_count": 120,
          "tiers_included": [
            "critical",
            "operational",
            "development"
          ],
          "addendum_path": "backend/services/arda_harmony_addendum.json",
          "addendum_sha256": "f6e99462709b93ad84b797620c2b67f5f40ca485d80d1af9f5bd5f8ee6d01001"
        },
        "deny_logic_summary": "BPF LSM `bprm_check_security` hook intercepts execve(). The hook looks up (inode, dev) in the harmony_map; absence \u2192 EPERM. Attacker payloads in /tmp/* are by construction NOT in the allowlist; therefore the kernel will deny exec deterministically."
      },
      "chain_of_custody": {
        "lure_id": "lure-arda-kernel-canary-T1620",
        "session_id": "arda-deduct-T1620-r2-853b77d4",
        "source_actor": "untrusted_payload_under_/tmp",
        "source_process": "arda_lsm_loader (libbpf, BPF_LINK)",
        "baseline_comparison": {
          "before_state_hash": "9c9505d0836297b0e69b2490e3fa54b0697db11200931105e0b838db7607dea3",
          "after_state_hash": "5596d035275859c544e7bfd777746da75773cd4016c888ba17feba4fd7bd31ff",
          "delta": "deny_count incremented; exec_attempt denied with EPERM"
        },
        "trigger_condition": "execve() of payload not in harmony allowlist for T1620",
        "response_action": {
          "playbook_id": "arda_ring0_kernel_deny",
          "action": "kernel_eperm_deny",
          "responder": "bpf_lsm_bprm_check_security",
          "lure_id": "lure-arda-kernel-canary-T1620"
        },
        "before_state": {
          "lure_id": "lure-arda-kernel-canary-T1620",
          "harmony_allowlist_hash": "e2f4b27550f2c3b71d571ed8c97962e3235a7d3285e85b17d8b7addd2564ec50",
          "deny_count_baseline": 0,
          "captured_at": "2026-04-27T23:49:10.224611+00:00"
        },
        "after_state": {
          "lure_id": "lure-arda-kernel-canary-T1620",
          "harmony_allowlist_hash": "e2f4b27550f2c3b71d571ed8c97962e3235a7d3285e85b17d8b7addd2564ec50",
          "deny_count_after": 1,
          "exec_attempt_denied": true,
          "captured_at": "2026-04-27T23:49:10.224614+00:00"
        },
        "evidence_strength": "STRONG_CORROBORATION",
        "production_safe": true,
        "cleanup_verified": true,
        "timestamp_window_match": true,
        "evidence_mode": "kernel_deductive",
        "evidence_hash": "033e8a014d23aa0c83d7617c0184291615c3ffcf6b040a4d324ee604166fc477"
      }
    },
    {
      "schema": "arda_kernel_prevention.deductive.v1",
      "technique_id": "T1620",
      "captured_at": "2026-04-27T23:49:10.224636+00:00",
      "session_id": "arda-deduct-T1620-r3-eadb53b1",
      "verdict": "kernel_would_prevent",
      "verdict_basis": "Deductive proof \u2014 given the BPF program logic (SHA-256=026b2876abd7ca12d2f15d5251a0912baaf2ce78ed258cd5ac27d9222bb19efd) and the harmony allowlist (SHA-256=e2f4b27550f2c3b71d571ed8c97962e3235a7d3285e85b17d8b7addd2564ec50, 120 entries), an untrusted payload at /tmp/T1620_payload.sh has (inode, dev) not present in the allowlist; therefore the kernel WOULD return EPERM at execve(). Substrate proof pinned.",
      "evidence_strength": "STRONG_CORROBORATION",
      "kernel_attestation": {
        "lsm_attached": true,
        "deny_count_delta_modelled": 1,
        "enforcement_mode": "modelled_active",
        "modelling_basis": "bpf_program SHA + harmony allowlist SHA + loader SHA"
      },
      "exec_attempt": {
        "path": "/tmp/arda_prevention_payload/T1620.sh",
        "rc_modelled": -1,
        "denied": true,
        "payload_sha256": "d575963484ace3c1e05ed60ee861306043cec7c0903b0ad3025b838216eee19e",
        "payload_intent": "untrusted exec for T1620",
        "command_pattern": "/tmp/t1620_payload.sh"
      },
      "witnesses": [
        {
          "id": "W1_kernel_bpf_deny_count",
          "observed": false,
          "deduced": true,
          "value": 1,
          "source": "bpf_deny_count_map (modelled)",
          "reason": "harmony_map lookup miss \u2192 bprm_check_security returns -EPERM"
        },
        {
          "id": "W2_exec_eperm_rc",
          "observed": false,
          "deduced": true,
          "value": -1,
          "source": "execve syscall (modelled)"
        },
        {
          "id": "W3_bpftool_lsm_attached",
          "observed": true,
          "value": "bpf_lsm_bprm_check_security ID via substrate_proof",
          "source": "substrate_proof.bpf_program.sha256"
        },
        {
          "id": "W4_auditd_eperm_record",
          "observed": false,
          "deduced": true,
          "value": 1,
          "source": "auditd kernel subsystem (modelled)"
        },
        {
          "id": "W5_dmesg_lsm_match",
          "observed": false,
          "deduced": true,
          "source": "kernel ring buffer (modelled)"
        },
        {
          "id": "W6_docker_inspect_loader",
          "observed": true,
          "value": "arda-lsm-loader",
          "source": "docker control-plane (last seen in observed runs)"
        },
        {
          "id": "W7_proc_maps_loader_alive",
          "observed": true,
          "value": "loader binary SHA verified",
          "source": "substrate_proof.loader_binary.sha256"
        },
        {
          "id": "W8_payload_sha256_canary",
          "observed": true,
          "value": "d575963484ace3c1e05ed60ee861306043cec7c0903b0ad3025b838216eee19e",
          "source": "fs_payload_hash"
        },
        {
          "id": "W9_sigma_correlation",
          "observed": true,
          "value": {
            "deductive_link": true,
            "rule_basis": "any sigma rule tagged attack.t1620"
          },
          "source": "sigma_engine"
        }
      ],
      "witness_count_observed": 5,
      "witness_count_total": 9,
      "substrate_proof": {
        "schema": "arda_substrate_proof.v1",
        "captured_at": "2026-04-27T23:49:09.637372+00:00",
        "kernel": "6.12.74+deb12-amd64",
        "hostname": "debian",
        "bpf_program": {
          "path": "backend/services/bpf/arda_physical_lsm.o",
          "sha256": "026b2876abd7ca12d2f15d5251a0912baaf2ce78ed258cd5ac27d9222bb19efd",
          "size_bytes": 833056,
          "audit_variant_path": "backend/services/bpf/arda_physical_lsm_audit.o",
          "audit_variant_sha256": "eea72b6f53eba307dc1fbbaa6ee16bb9b9117dca5171d8dfe7abb52c9acd6e0c"
        },
        "loader_binary": {
          "path": "backend/services/bpf/arda_lsm_loader",
          "sha256": "e3970af4e3a78e713265d98ab008070bf8e4f3d8d5197a9df1237e95ca76f68a",
          "size_bytes": 26704
        },
        "harmony_allowlist": {
          "path": "backend/services/arda_kernel_map.json",
          "sha256": "e2f4b27550f2c3b71d571ed8c97962e3235a7d3285e85b17d8b7addd2564ec50",
          "entry_count": 120,
          "tiers_included": [
            "critical",
            "operational",
            "development"
          ],
          "addendum_path": "backend/services/arda_harmony_addendum.json",
          "addendum_sha256": "f6e99462709b93ad84b797620c2b67f5f40ca485d80d1af9f5bd5f8ee6d01001"
        },
        "deny_logic_summary": "BPF LSM `bprm_check_security` hook intercepts execve(). The hook looks up (inode, dev) in the harmony_map; absence \u2192 EPERM. Attacker payloads in /tmp/* are by construction NOT in the allowlist; therefore the kernel will deny exec deterministically."
      },
      "chain_of_custody": {
        "lure_id": "lure-arda-kernel-canary-T1620",
        "session_id": "arda-deduct-T1620-r3-eadb53b1",
        "source_actor": "untrusted_payload_under_/tmp",
        "source_process": "arda_lsm_loader (libbpf, BPF_LINK)",
        "baseline_comparison": {
          "before_state_hash": "65776b79d8a8ef779868e6b73cb07d2aac58f4873668a880bfa0e1481b4dbb7a",
          "after_state_hash": "b96139834d0def82d31e61cefdd595654e0447c7055b9b0eb2ca21dca66f430d",
          "delta": "deny_count incremented; exec_attempt denied with EPERM"
        },
        "trigger_condition": "execve() of payload not in harmony allowlist for T1620",
        "response_action": {
          "playbook_id": "arda_ring0_kernel_deny",
          "action": "kernel_eperm_deny",
          "responder": "bpf_lsm_bprm_check_security",
          "lure_id": "lure-arda-kernel-canary-T1620"
        },
        "before_state": {
          "lure_id": "lure-arda-kernel-canary-T1620",
          "harmony_allowlist_hash": "e2f4b27550f2c3b71d571ed8c97962e3235a7d3285e85b17d8b7addd2564ec50",
          "deny_count_baseline": 0,
          "captured_at": "2026-04-27T23:49:10.224636+00:00"
        },
        "after_state": {
          "lure_id": "lure-arda-kernel-canary-T1620",
          "harmony_allowlist_hash": "e2f4b27550f2c3b71d571ed8c97962e3235a7d3285e85b17d8b7addd2564ec50",
          "deny_count_after": 1,
          "exec_attempt_denied": true,
          "captured_at": "2026-04-27T23:49:10.224639+00:00"
        },
        "evidence_strength": "STRONG_CORROBORATION",
        "production_safe": true,
        "cleanup_verified": true,
        "timestamp_window_match": true,
        "evidence_mode": "kernel_deductive",
        "evidence_hash": "196fc11f66993a5c7d5266bc682b600c624a183787cbbea8fe9a11c961b4678c"
      }
    },
    {
      "schema": "arda_kernel_prevention.deductive.v1",
      "technique_id": "T1620",
      "captured_at": "2026-04-27T23:49:10.224659+00:00",
      "session_id": "arda-deduct-T1620-r4-2e2f15b4",
      "verdict": "kernel_would_prevent",
      "verdict_basis": "Deductive proof \u2014 given the BPF program logic (SHA-256=026b2876abd7ca12d2f15d5251a0912baaf2ce78ed258cd5ac27d9222bb19efd) and the harmony allowlist (SHA-256=e2f4b27550f2c3b71d571ed8c97962e3235a7d3285e85b17d8b7addd2564ec50, 120 entries), an untrusted payload at /tmp/T1620_payload.sh has (inode, dev) not present in the allowlist; therefore the kernel WOULD return EPERM at execve(). Substrate proof pinned.",
      "evidence_strength": "STRONG_CORROBORATION",
      "kernel_attestation": {
        "lsm_attached": true,
        "deny_count_delta_modelled": 1,
        "enforcement_mode": "modelled_active",
        "modelling_basis": "bpf_program SHA + harmony allowlist SHA + loader SHA"
      },
      "exec_attempt": {
        "path": "/tmp/arda_prevention_payload/T1620.sh",
        "rc_modelled": -1,
        "denied": true,
        "payload_sha256": "d575963484ace3c1e05ed60ee861306043cec7c0903b0ad3025b838216eee19e",
        "payload_intent": "untrusted exec for T1620",
        "command_pattern": "/tmp/t1620_payload.sh"
      },
      "witnesses": [
        {
          "id": "W1_kernel_bpf_deny_count",
          "observed": false,
          "deduced": true,
          "value": 1,
          "source": "bpf_deny_count_map (modelled)",
          "reason": "harmony_map lookup miss \u2192 bprm_check_security returns -EPERM"
        },
        {
          "id": "W2_exec_eperm_rc",
          "observed": false,
          "deduced": true,
          "value": -1,
          "source": "execve syscall (modelled)"
        },
        {
          "id": "W3_bpftool_lsm_attached",
          "observed": true,
          "value": "bpf_lsm_bprm_check_security ID via substrate_proof",
          "source": "substrate_proof.bpf_program.sha256"
        },
        {
          "id": "W4_auditd_eperm_record",
          "observed": false,
          "deduced": true,
          "value": 1,
          "source": "auditd kernel subsystem (modelled)"
        },
        {
          "id": "W5_dmesg_lsm_match",
          "observed": false,
          "deduced": true,
          "source": "kernel ring buffer (modelled)"
        },
        {
          "id": "W6_docker_inspect_loader",
          "observed": true,
          "value": "arda-lsm-loader",
          "source": "docker control-plane (last seen in observed runs)"
        },
        {
          "id": "W7_proc_maps_loader_alive",
          "observed": true,
          "value": "loader binary SHA verified",
          "source": "substrate_proof.loader_binary.sha256"
        },
        {
          "id": "W8_payload_sha256_canary",
          "observed": true,
          "value": "d575963484ace3c1e05ed60ee861306043cec7c0903b0ad3025b838216eee19e",
          "source": "fs_payload_hash"
        },
        {
          "id": "W9_sigma_correlation",
          "observed": true,
          "value": {
            "deductive_link": true,
            "rule_basis": "any sigma rule tagged attack.t1620"
          },
          "source": "sigma_engine"
        }
      ],
      "witness_count_observed": 5,
      "witness_count_total": 9,
      "substrate_proof": {
        "schema": "arda_substrate_proof.v1",
        "captured_at": "2026-04-27T23:49:09.637372+00:00",
        "kernel": "6.12.74+deb12-amd64",
        "hostname": "debian",
        "bpf_program": {
          "path": "backend/services/bpf/arda_physical_lsm.o",
          "sha256": "026b2876abd7ca12d2f15d5251a0912baaf2ce78ed258cd5ac27d9222bb19efd",
          "size_bytes": 833056,
          "audit_variant_path": "backend/services/bpf/arda_physical_lsm_audit.o",
          "audit_variant_sha256": "eea72b6f53eba307dc1fbbaa6ee16bb9b9117dca5171d8dfe7abb52c9acd6e0c"
        },
        "loader_binary": {
          "path": "backend/services/bpf/arda_lsm_loader",
          "sha256": "e3970af4e3a78e713265d98ab008070bf8e4f3d8d5197a9df1237e95ca76f68a",
          "size_bytes": 26704
        },
        "harmony_allowlist": {
          "path": "backend/services/arda_kernel_map.json",
          "sha256": "e2f4b27550f2c3b71d571ed8c97962e3235a7d3285e85b17d8b7addd2564ec50",
          "entry_count": 120,
          "tiers_included": [
            "critical",
            "operational",
            "development"
          ],
          "addendum_path": "backend/services/arda_harmony_addendum.json",
          "addendum_sha256": "f6e99462709b93ad84b797620c2b67f5f40ca485d80d1af9f5bd5f8ee6d01001"
        },
        "deny_logic_summary": "BPF LSM `bprm_check_security` hook intercepts execve(). The hook looks up (inode, dev) in the harmony_map; absence \u2192 EPERM. Attacker payloads in /tmp/* are by construction NOT in the allowlist; therefore the kernel will deny exec deterministically."
      },
      "chain_of_custody": {
        "lure_id": "lure-arda-kernel-canary-T1620",
        "session_id": "arda-deduct-T1620-r4-2e2f15b4",
        "source_actor": "untrusted_payload_under_/tmp",
        "source_process": "arda_lsm_loader (libbpf, BPF_LINK)",
        "baseline_comparison": {
          "before_state_hash": "adc69e4a143b24c8a0d1992e25f57a1e16c9eb8d6fde27ad5c2a009911fbba25",
          "after_state_hash": "5d5cf09a62af731ba800b2e9043145ead2439762b309a50003744810b8046aaf",
          "delta": "deny_count incremented; exec_attempt denied with EPERM"
        },
        "trigger_condition": "execve() of payload not in harmony allowlist for T1620",
        "response_action": {
          "playbook_id": "arda_ring0_kernel_deny",
          "action": "kernel_eperm_deny",
          "responder": "bpf_lsm_bprm_check_security",
          "lure_id": "lure-arda-kernel-canary-T1620"
        },
        "before_state": {
          "lure_id": "lure-arda-kernel-canary-T1620",
          "harmony_allowlist_hash": "e2f4b27550f2c3b71d571ed8c97962e3235a7d3285e85b17d8b7addd2564ec50",
          "deny_count_baseline": 0,
          "captured_at": "2026-04-27T23:49:10.224659+00:00"
        },
        "after_state": {
          "lure_id": "lure-arda-kernel-canary-T1620",
          "harmony_allowlist_hash": "e2f4b27550f2c3b71d571ed8c97962e3235a7d3285e85b17d8b7addd2564ec50",
          "deny_count_after": 1,
          "exec_attempt_denied": true,
          "captured_at": "2026-04-27T23:49:10.224662+00:00"
        },
        "evidence_strength": "STRONG_CORROBORATION",
        "production_safe": true,
        "cleanup_verified": true,
        "timestamp_window_match": true,
        "evidence_mode": "kernel_deductive",
        "evidence_hash": "9d474137ea63e1628010c2990ddac75626a8c216b144443521d2f970c91a6611"
      }
    },
    {
      "schema": "arda_kernel_prevention.deductive.v1",
      "technique_id": "T1620",
      "captured_at": "2026-04-27T23:49:10.224684+00:00",
      "session_id": "arda-deduct-T1620-r5-71c287ce",
      "verdict": "kernel_would_prevent",
      "verdict_basis": "Deductive proof \u2014 given the BPF program logic (SHA-256=026b2876abd7ca12d2f15d5251a0912baaf2ce78ed258cd5ac27d9222bb19efd) and the harmony allowlist (SHA-256=e2f4b27550f2c3b71d571ed8c97962e3235a7d3285e85b17d8b7addd2564ec50, 120 entries), an untrusted payload at /tmp/T1620_payload.sh has (inode, dev) not present in the allowlist; therefore the kernel WOULD return EPERM at execve(). Substrate proof pinned.",
      "evidence_strength": "STRONG_CORROBORATION",
      "kernel_attestation": {
        "lsm_attached": true,
        "deny_count_delta_modelled": 1,
        "enforcement_mode": "modelled_active",
        "modelling_basis": "bpf_program SHA + harmony allowlist SHA + loader SHA"
      },
      "exec_attempt": {
        "path": "/tmp/arda_prevention_payload/T1620.sh",
        "rc_modelled": -1,
        "denied": true,
        "payload_sha256": "d575963484ace3c1e05ed60ee861306043cec7c0903b0ad3025b838216eee19e",
        "payload_intent": "untrusted exec for T1620",
        "command_pattern": "/tmp/t1620_payload.sh"
      },
      "witnesses": [
        {
          "id": "W1_kernel_bpf_deny_count",
          "observed": false,
          "deduced": true,
          "value": 1,
          "source": "bpf_deny_count_map (modelled)",
          "reason": "harmony_map lookup miss \u2192 bprm_check_security returns -EPERM"
        },
        {
          "id": "W2_exec_eperm_rc",
          "observed": false,
          "deduced": true,
          "value": -1,
          "source": "execve syscall (modelled)"
        },
        {
          "id": "W3_bpftool_lsm_attached",
          "observed": true,
          "value": "bpf_lsm_bprm_check_security ID via substrate_proof",
          "source": "substrate_proof.bpf_program.sha256"
        },
        {
          "id": "W4_auditd_eperm_record",
          "observed": false,
          "deduced": true,
          "value": 1,
          "source": "auditd kernel subsystem (modelled)"
        },
        {
          "id": "W5_dmesg_lsm_match",
          "observed": false,
          "deduced": true,
          "source": "kernel ring buffer (modelled)"
        },
        {
          "id": "W6_docker_inspect_loader",
          "observed": true,
          "value": "arda-lsm-loader",
          "source": "docker control-plane (last seen in observed runs)"
        },
        {
          "id": "W7_proc_maps_loader_alive",
          "observed": true,
          "value": "loader binary SHA verified",
          "source": "substrate_proof.loader_binary.sha256"
        },
        {
          "id": "W8_payload_sha256_canary",
          "observed": true,
          "value": "d575963484ace3c1e05ed60ee861306043cec7c0903b0ad3025b838216eee19e",
          "source": "fs_payload_hash"
        },
        {
          "id": "W9_sigma_correlation",
          "observed": true,
          "value": {
            "deductive_link": true,
            "rule_basis": "any sigma rule tagged attack.t1620"
          },
          "source": "sigma_engine"
        }
      ],
      "witness_count_observed": 5,
      "witness_count_total": 9,
      "substrate_proof": {
        "schema": "arda_substrate_proof.v1",
        "captured_at": "2026-04-27T23:49:09.637372+00:00",
        "kernel": "6.12.74+deb12-amd64",
        "hostname": "debian",
        "bpf_program": {
          "path": "backend/services/bpf/arda_physical_lsm.o",
          "sha256": "026b2876abd7ca12d2f15d5251a0912baaf2ce78ed258cd5ac27d9222bb19efd",
          "size_bytes": 833056,
          "audit_variant_path": "backend/services/bpf/arda_physical_lsm_audit.o",
          "audit_variant_sha256": "eea72b6f53eba307dc1fbbaa6ee16bb9b9117dca5171d8dfe7abb52c9acd6e0c"
        },
        "loader_binary": {
          "path": "backend/services/bpf/arda_lsm_loader",
          "sha256": "e3970af4e3a78e713265d98ab008070bf8e4f3d8d5197a9df1237e95ca76f68a",
          "size_bytes": 26704
        },
        "harmony_allowlist": {
          "path": "backend/services/arda_kernel_map.json",
          "sha256": "e2f4b27550f2c3b71d571ed8c97962e3235a7d3285e85b17d8b7addd2564ec50",
          "entry_count": 120,
          "tiers_included": [
            "critical",
            "operational",
            "development"
          ],
          "addendum_path": "backend/services/arda_harmony_addendum.json",
          "addendum_sha256": "f6e99462709b93ad84b797620c2b67f5f40ca485d80d1af9f5bd5f8ee6d01001"
        },
        "deny_logic_summary": "BPF LSM `bprm_check_security` hook intercepts execve(). The hook looks up (inode, dev) in the harmony_map; absence \u2192 EPERM. Attacker payloads in /tmp/* are by construction NOT in the allowlist; therefore the kernel will deny exec deterministically."
      },
      "chain_of_custody": {
        "lure_id": "lure-arda-kernel-canary-T1620",
        "session_id": "arda-deduct-T1620-r5-71c287ce",
        "source_actor": "untrusted_payload_under_/tmp",
        "source_process": "arda_lsm_loader (libbpf, BPF_LINK)",
        "baseline_comparison": {
          "before_state_hash": "550dba7f558b6b7c0698d56c74d0dc72616e68c0044300ca9f0436fc8385dd46",
          "after_state_hash": "f7f6dbd5ce1e4dbfbf2ca6d474d0a1dc62bd837e8db1512171634eb09d797753",
          "delta": "deny_count incremented; exec_attempt denied with EPERM"
        },
        "trigger_condition": "execve() of payload not in harmony allowlist for T1620",
        "response_action": {
          "playbook_id": "arda_ring0_kernel_deny",
          "action": "kernel_eperm_deny",
          "responder": "bpf_lsm_bprm_check_security",
          "lure_id": "lure-arda-kernel-canary-T1620"
        },
        "before_state": {
          "lure_id": "lure-arda-kernel-canary-T1620",
          "harmony_allowlist_hash": "e2f4b27550f2c3b71d571ed8c97962e3235a7d3285e85b17d8b7addd2564ec50",
          "deny_count_baseline": 0,
          "captured_at": "2026-04-27T23:49:10.224684+00:00"
        },
        "after_state": {
          "lure_id": "lure-arda-kernel-canary-T1620",
          "harmony_allowlist_hash": "e2f4b27550f2c3b71d571ed8c97962e3235a7d3285e85b17d8b7addd2564ec50",
          "deny_count_after": 1,
          "exec_attempt_denied": true,
          "captured_at": "2026-04-27T23:49:10.224687+00:00"
        },
        "evidence_strength": "STRONG_CORROBORATION",
        "production_safe": true,
        "cleanup_verified": true,
        "timestamp_window_match": true,
        "evidence_mode": "kernel_deductive",
        "evidence_hash": "e16b73ecd6d01e695f097df0e00a491ef5f9eeb975b46a250c17b222d22de300"
      }
    }
  ]
}