[
  {
    "execution_id": "exec_dc5414e910ae",
    "playbook_id": "ai_pivot_contain_01",
    "playbook_name": "AI Lateral Movement - Contain Fast",
    "action": "tag_session",
    "status": "completed",
    "timestamp": "2026-04-18T09:09:17.316308+00:00",
    "host_id": "coverage-host-01",
    "session_id": "coverage-ai_pivot_contain_01"
  },
  {
    "execution_id": "exec_dc5414e910ae",
    "playbook_id": "ai_pivot_contain_01",
    "playbook_name": "AI Lateral Movement - Contain Fast",
    "action": "snapshot_network_state",
    "status": "completed",
    "timestamp": "2026-04-18T09:09:17.316316+00:00",
    "host_id": "coverage-host-01",
    "session_id": "coverage-ai_pivot_contain_01"
  },
  {
    "execution_id": "exec_dc5414e910ae",
    "playbook_id": "ai_pivot_contain_01",
    "playbook_name": "AI Lateral Movement - Contain Fast",
    "action": "update_firewall",
    "status": "completed",
    "timestamp": "2026-04-18T09:09:17.316321+00:00",
    "host_id": "coverage-host-01",
    "session_id": "coverage-ai_pivot_contain_01"
  },
  {
    "execution_id": "exec_dc5414e910ae",
    "playbook_id": "ai_pivot_contain_01",
    "playbook_name": "AI Lateral Movement - Contain Fast",
    "action": "lock_sensitive_resources",
    "status": "completed",
    "timestamp": "2026-04-18T09:09:17.316327+00:00",
    "host_id": "coverage-host-01",
    "session_id": "coverage-ai_pivot_contain_01"
  },
  {
    "execution_id": "exec_dc5414e910ae",
    "playbook_id": "ai_pivot_contain_01",
    "playbook_name": "AI Lateral Movement - Contain Fast",
    "action": "disable_user",
    "status": "completed",
    "timestamp": "2026-04-18T09:09:17.316333+00:00",
    "host_id": "coverage-host-01",
    "session_id": "coverage-ai_pivot_contain_01"
  },
  {
    "execution_id": "exec_dc5414e910ae",
    "playbook_id": "ai_pivot_contain_01",
    "playbook_name": "AI Lateral Movement - Contain Fast",
    "action": "capture_triage_bundle",
    "status": "completed",
    "timestamp": "2026-04-18T09:09:17.316343+00:00",
    "host_id": "coverage-host-01",
    "session_id": "coverage-ai_pivot_contain_01"
  },
  {
    "execution_id": "exec_dc5414e910ae",
    "playbook_id": "ai_pivot_contain_01",
    "playbook_name": "AI Lateral Movement - Contain Fast",
    "action": "sync_threat_intel",
    "status": "completed",
    "timestamp": "2026-04-18T09:09:17.316350+00:00",
    "host_id": "coverage-host-01",
    "session_id": "coverage-ai_pivot_contain_01"
  },
  {
    "execution_id": "exec_dc5414e910ae",
    "playbook_id": "ai_pivot_contain_01",
    "playbook_name": "AI Lateral Movement - Contain Fast",
    "action": "send_alert",
    "status": "completed",
    "timestamp": "2026-04-18T09:09:17.316355+00:00",
    "host_id": "coverage-host-01",
    "session_id": "coverage-ai_pivot_contain_01"
  },
  {
    "execution_id": "exec_dc5414e910ae",
    "playbook_id": "ai_pivot_contain_01",
    "playbook_name": "AI Lateral Movement - Contain Fast",
    "action": "create_ticket",
    "status": "completed",
    "timestamp": "2026-04-18T09:09:17.316362+00:00",
    "host_id": "coverage-host-01",
    "session_id": "coverage-ai_pivot_contain_01"
  },
  {
    "execution_id": "exec_dc5414e910ae",
    "playbook_id": "ai_pivot_contain_01",
    "playbook_name": "AI Lateral Movement - Contain Fast",
    "action": "tag_session",
    "status": "completed",
    "timestamp": "2026-04-18T09:09:17.316308+00:00",
    "host_id": "coverage-host-01",
    "session_id": "coverage-ai_pivot_contain_01"
  },
  {
    "execution_id": "exec_dc5414e910ae",
    "playbook_id": "ai_pivot_contain_01",
    "playbook_name": "AI Lateral Movement - Contain Fast",
    "action": "snapshot_network_state",
    "status": "completed",
    "timestamp": "2026-04-18T09:09:17.316316+00:00",
    "host_id": "coverage-host-01",
    "session_id": "coverage-ai_pivot_contain_01"
  },
  {
    "execution_id": "exec_dc5414e910ae",
    "playbook_id": "ai_pivot_contain_01",
    "playbook_name": "AI Lateral Movement - Contain Fast",
    "action": "update_firewall",
    "status": "completed",
    "timestamp": "2026-04-18T09:09:17.316321+00:00",
    "host_id": "coverage-host-01",
    "session_id": "coverage-ai_pivot_contain_01"
  },
  {
    "execution_id": "exec_dc5414e910ae",
    "playbook_id": "ai_pivot_contain_01",
    "playbook_name": "AI Lateral Movement - Contain Fast",
    "action": "lock_sensitive_resources",
    "status": "completed",
    "timestamp": "2026-04-18T09:09:17.316327+00:00",
    "host_id": "coverage-host-01",
    "session_id": "coverage-ai_pivot_contain_01"
  },
  {
    "execution_id": "exec_dc5414e910ae",
    "playbook_id": "ai_pivot_contain_01",
    "playbook_name": "AI Lateral Movement - Contain Fast",
    "action": "disable_user",
    "status": "completed",
    "timestamp": "2026-04-18T09:09:17.316333+00:00",
    "host_id": "coverage-host-01",
    "session_id": "coverage-ai_pivot_contain_01"
  },
  {
    "execution_id": "exec_dc5414e910ae",
    "playbook_id": "ai_pivot_contain_01",
    "playbook_name": "AI Lateral Movement - Contain Fast",
    "action": "capture_triage_bundle",
    "status": "completed",
    "timestamp": "2026-04-18T09:09:17.316343+00:00",
    "host_id": "coverage-host-01",
    "session_id": "coverage-ai_pivot_contain_01"
  },
  {
    "execution_id": "exec_dc5414e910ae",
    "playbook_id": "ai_pivot_contain_01",
    "playbook_name": "AI Lateral Movement - Contain Fast",
    "action": "sync_threat_intel",
    "status": "completed",
    "timestamp": "2026-04-18T09:09:17.316350+00:00",
    "host_id": "coverage-host-01",
    "session_id": "coverage-ai_pivot_contain_01"
  },
  {
    "execution_id": "exec_dc5414e910ae",
    "playbook_id": "ai_pivot_contain_01",
    "playbook_name": "AI Lateral Movement - Contain Fast",
    "action": "send_alert",
    "status": "completed",
    "timestamp": "2026-04-18T09:09:17.316355+00:00",
    "host_id": "coverage-host-01",
    "session_id": "coverage-ai_pivot_contain_01"
  },
  {
    "execution_id": "exec_dc5414e910ae",
    "playbook_id": "ai_pivot_contain_01",
    "playbook_name": "AI Lateral Movement - Contain Fast",
    "action": "create_ticket",
    "status": "completed",
    "timestamp": "2026-04-18T09:09:17.316362+00:00",
    "host_id": "coverage-host-01",
    "session_id": "coverage-ai_pivot_contain_01"
  }
]