{
  "record_type": "technique_validation_record",
  "schema_version": "1.0.0",
  "validation_id": "TVR-T1565-2026-04-26-011",
  "technique": {
    "attack_id": "T1565",
    "name": "T1565",
    "tactics": [],
    "platforms": [
      "Linux"
    ]
  },
  "procedure": {
    "source": "atomic_red_team",
    "procedure_id": "ART-T1565-1",
    "name": "Atomic Red Team validation for T1565",
    "description": "Automated emulation procedure for T1565 executed via Invoke-AtomicRedTeam inside the Metatron lab environment.",
    "test_ref": "atomics/T1565/T1565.yaml#test-1"
  },
  "environment": {
    "lab_id": "metatron-lab-a",
    "hostname": "debian-node-01",
    "asset_id": "asset-001",
    "os": {
      "family": "linux",
      "name": "Debian",
      "version": "12"
    },
    "kernel_version": "6.12.74+deb12-amd64",
    "sensor_stack": [
      {
        "name": "sigma-engine",
        "version": "2026.04.26",
        "rules_loaded": 427
      },
      {
        "name": "osquery",
        "version": "5.15.0"
      },
      {
        "name": "atomic_red_team",
        "version": "2025.01"
      }
    ]
  },
  "execution": {
    "started_at": "2026-04-18T13:22:53.445955+00:00",
    "ended_at": "2026-04-18T13:22:53.445955+00:00",
    "executor": "atomic_red_team",
    "operator": "Byron Bunt",
    "status": "completed",
    "exit_code": 0,
    "real_execution": true,
    "execution_mode": "docker_sandbox",
    "sandbox_verified": true,
    "evidence_inheritance": "direct",
    "expected_outcome": "detect",
    "command_line": "['docker', 'run', '--rm', '--name', 'seraph-sandbox-5ce142d1115b', '--network', 'none', '--cap-drop', 'ALL', '--cap-add', 'SETUID', '--cap-add', 'SETGID', '--cap-add', 'CHOWN', '--cap-add', 'DAC_OVERRIDE', '--cap-add', 'FOWNER', '--cap-add', 'SYS_PTRACE', '--security-opt', 'no-new-privileges:false', '-v', '/home/byron/Downloads/Metatron-triune-outbound-gate/atomic-red-team:/opt/atomic-red-team:ro', '-v', '/home/byron/Downloads/Metatron-triune-outbound-gate/tools/invoke-atomicredteam:/opt/invoke-atomicredteam:ro', 'seraph-sandbox-tools:latest', 'pwsh', '-NonInteractive', '-NoProfile', '-Command', \"Import-Module '/opt/invoke-atomicredteam/Invoke-AtomicRedTeam.psd1' -ErrorAction Stop; $env:PathToAtomicsFolder='/opt/atomic-red-team/atomics'; Invoke-AtomicTest T1565 -PathToAtomicsFolder '/opt/atomic-red-team/atomics'\"]",
    "run_count": 11,
    "direct_run_count": 11,
    "run_ids": [
      "24abaea50d7a46e99354c98c5dd05996",
      "24abaea50d7a46e99354c98c5dd05996",
      "5ce142d1115b4163bd4f60f5f31f8393",
      "dbdeaf68f1de4dd892b475bee91b0765",
      "e786e55889c0490ba52925b01bdc803b",
      "5ce142d1115b4163bd4f60f5f31f8393",
      "5eed94cce9af4081a5da30ba637037e9",
      "7554c2d42bf4476d8b25dc24e7381b87",
      "89c73488622f47bcbc7229288a134d48",
      "bcfab315493249dd8c077e86f4a64ddc",
      "5ce142d1115b4163bd4f60f5f31f8393"
    ],
    "job_ids": [
      "sandbox-real-sweep"
    ],
    "runs": [
      {
        "run_id": "24abaea50d7a46e99354c98c5dd05996",
        "job_id": "sandbox-real-sweep",
        "job_name": "Full Real Execution Sandbox Sweep",
        "finished_at": "2026-04-23T07:07:13.775569+00:00",
        "exit_code": 0,
        "sandbox": "docker-network-none-cap-drop-all",
        "status": "success",
        "outcome": "real_execution",
        "command": [
          "docker",
          "run",
          "--rm",
          "--name",
          "seraph-sandbox-24abaea50d7a",
          "--network",
          "none",
          "--cap-drop",
          "ALL",
          "--cap-add",
          "SETUID",
          "--cap-add",
          "SETGID",
          "--cap-add",
          "CHOWN",
          "--cap-add",
          "DAC_OVERRIDE",
          "--cap-add",
          "FOWNER",
          "--cap-add",
          "SYS_PTRACE",
          "--cap-add",
          "NET_RAW",
          "--security-opt",
          "no-new-privileges:false",
          "--tmpfs",
          "/tmp:exec,size=512m",
          "-v",
          "/home/byron/Downloads/Metatron-triune-outbound-gate/atomic-red-team:/opt/atomic-red-team:ro",
          "-v",
          "/home/byron/Downloads/Metatron-triune-outbound-gate/tools/invoke-atomicredteam:/opt/invoke-atomicredteam:ro",
          "seraph-sandbox-tools:latest",
          "pwsh",
          "-NonInteractive",
          "-NoProfile",
          "-Command",
          "Import-Module '/opt/invoke-atomicredteam/Invoke-AtomicRedTeam.psd1' -ErrorAction Stop; $env:PathToAtomicsFolder='/opt/atomic-red-team/atomics'; Invoke-AtomicTest T1565 -PathToAtomicsFolder '/opt/atomic-red-team/atomics'"
        ],
        "stdout": "PathToAtomicsFolder = /opt/atomic-red-team/atomics\n\nExecuting test: T1565-1 Simulate T1565 - Data Manipulation\nuid=0(root) gid=0(root) groups=0(root)\nSimulating T1565 - Data Manipulation\n17f91161dac1\n1776928033\nExit code: 0\nDone executing test: T1565-1 Simulate T1565 - Data Manipulation\n",
        "stdout_sha256": "ac01108dfa4eefc71236fd34607e113a4e668ba0693c9596be00a874bbd39671",
        "stderr_sha256": "e3b0c44298fc1c149afbf4c8996fb92427ae41e4649b934ca495991b7852b855",
        "real_execution": true,
        "network_anchors": {
          "stdout_paths": [
            "/opt/atomic-red-team/atomics"
          ]
        }
      },
      {
        "run_id": "24abaea50d7a46e99354c98c5dd05996",
        "job_id": "sandbox-real-sweep",
        "job_name": "Full Real Execution Sandbox Sweep",
        "finished_at": "2026-04-23T07:07:13.775569+00:00",
        "exit_code": 0,
        "sandbox": "docker-network-none-cap-drop-all",
        "status": "success",
        "outcome": "real_execution",
        "command": [
          "docker",
          "run",
          "--rm",
          "--name",
          "seraph-sandbox-24abaea50d7a",
          "--network",
          "none",
          "--cap-drop",
          "ALL",
          "--cap-add",
          "SETUID",
          "--cap-add",
          "SETGID",
          "--cap-add",
          "CHOWN",
          "--cap-add",
          "DAC_OVERRIDE",
          "--cap-add",
          "FOWNER",
          "--cap-add",
          "SYS_PTRACE",
          "--cap-add",
          "NET_RAW",
          "--security-opt",
          "no-new-privileges:false",
          "--tmpfs",
          "/tmp:exec,size=512m",
          "-v",
          "/home/byron/Downloads/Metatron-triune-outbound-gate/atomic-red-team:/opt/atomic-red-team:ro",
          "-v",
          "/home/byron/Downloads/Metatron-triune-outbound-gate/tools/invoke-atomicredteam:/opt/invoke-atomicredteam:ro",
          "seraph-sandbox-tools:latest",
          "pwsh",
          "-NonInteractive",
          "-NoProfile",
          "-Command",
          "Import-Module '/opt/invoke-atomicredteam/Invoke-AtomicRedTeam.psd1' -ErrorAction Stop; $env:PathToAtomicsFolder='/opt/atomic-red-team/atomics'; Invoke-AtomicTest T1565 -PathToAtomicsFolder '/opt/atomic-red-team/atomics'"
        ],
        "stdout": "PathToAtomicsFolder = /opt/atomic-red-team/atomics\n\nExecuting test: T1565-1 Simulate T1565 - Data Manipulation\nuid=0(root) gid=0(root) groups=0(root)\nSimulating T1565 - Data Manipulation\n17f91161dac1\n1776928033\nExit code: 0\nDone executing test: T1565-1 Simulate T1565 - Data Manipulation\n",
        "stdout_sha256": "ac01108dfa4eefc71236fd34607e113a4e668ba0693c9596be00a874bbd39671",
        "stderr_sha256": "e3b0c44298fc1c149afbf4c8996fb92427ae41e4649b934ca495991b7852b855",
        "real_execution": true,
        "network_anchors": {
          "stdout_paths": [
            "/opt/atomic-red-team/atomics"
          ]
        }
      },
      {
        "run_id": "5ce142d1115b4163bd4f60f5f31f8393",
        "job_id": "sandbox-real-sweep",
        "job_name": "Full Real Execution Sandbox Sweep",
        "finished_at": "2026-04-18T13:22:53.445955+00:00",
        "exit_code": 0,
        "sandbox": "docker-network-none-cap-drop-all",
        "status": "success",
        "outcome": "",
        "command": [
          "docker",
          "run",
          "--rm",
          "--name",
          "seraph-sandbox-5ce142d1115b",
          "--network",
          "none",
          "--cap-drop",
          "ALL",
          "--cap-add",
          "SETUID",
          "--cap-add",
          "SETGID",
          "--cap-add",
          "CHOWN",
          "--cap-add",
          "DAC_OVERRIDE",
          "--cap-add",
          "FOWNER",
          "--cap-add",
          "SYS_PTRACE",
          "--security-opt",
          "no-new-privileges:false",
          "-v",
          "/home/byron/Downloads/Metatron-triune-outbound-gate/atomic-red-team:/opt/atomic-red-team:ro",
          "-v",
          "/home/byron/Downloads/Metatron-triune-outbound-gate/tools/invoke-atomicredteam:/opt/invoke-atomicredteam:ro",
          "seraph-sandbox-tools:latest",
          "pwsh",
          "-NonInteractive",
          "-NoProfile",
          "-Command",
          "Import-Module '/opt/invoke-atomicredteam/Invoke-AtomicRedTeam.psd1' -ErrorAction Stop; $env:PathToAtomicsFolder='/opt/atomic-red-team/atomics'; Invoke-AtomicTest T1565 -PathToAtomicsFolder '/opt/atomic-red-team/atomics'"
        ],
        "stdout": "PathToAtomicsFolder = /opt/atomic-red-team/atomics\n\nExecuting test: T1565-1 Simulate T1565 - Data Manipulation\nSimulating T1565 - Data Manipulation\nuid=0(root) gid=0(root) groups=0(root)\n513d249f9b4b\n1776518573\nExit code: 0\nDone executing test: T1565-1 Simulate T1565 - Data Manipulation\n",
        "stdout_sha256": "f0d299789fec4f550e50b2552e089d46750c9ce33218e0724e78306b1e85add7",
        "stderr_sha256": "e3b0c44298fc1c149afbf4c8996fb92427ae41e4649b934ca495991b7852b855",
        "real_execution": true,
        "network_anchors": {
          "stdout_paths": [
            "/opt/atomic-red-team/atomics"
          ]
        }
      },
      {
        "run_id": "dbdeaf68f1de4dd892b475bee91b0765",
        "job_id": "sandbox-real-sweep",
        "job_name": "Full Real Execution Sandbox Sweep",
        "finished_at": "2026-04-26T06:53:12.834246+00:00",
        "exit_code": 0,
        "sandbox": "docker-network-none-cap-drop-all",
        "status": "success",
        "outcome": "real_execution",
        "command": [
          "docker",
          "run",
          "--rm",
          "--name",
          "seraph-sandbox-dbdeaf68f1de",
          "--network",
          "none",
          "--cap-drop",
          "ALL",
          "--cap-add",
          "SETUID",
          "--cap-add",
          "SETGID",
          "--cap-add",
          "CHOWN",
          "--cap-add",
          "DAC_OVERRIDE",
          "--cap-add",
          "FOWNER",
          "--cap-add",
          "SYS_PTRACE",
          "--cap-add",
          "NET_RAW",
          "--security-opt",
          "no-new-privileges:false",
          "--tmpfs",
          "/tmp:exec,size=512m",
          "-v",
          "/home/byron/Downloads/Metatron-triune-outbound-gate/atomic-red-team:/opt/atomic-red-team:ro",
          "-v",
          "/home/byron/Downloads/Metatron-triune-outbound-gate/tools/invoke-atomicredteam:/opt/invoke-atomicredteam:ro",
          "-v",
          "/home/byron/Downloads/Metatron-triune-outbound-gate/tools/powershell:/opt/pwsh:ro",
          "seraph-sandbox-tools:latest",
          "/opt/pwsh/pwsh",
          "-NonInteractive",
          "-NoProfile",
          "-Command",
          "Import-Module '/opt/invoke-atomicredteam/Invoke-AtomicRedTeam.psd1' -ErrorAction Stop; $env:PathToAtomicsFolder='/opt/atomic-red-team/atomics'; try { bash -lc \"if command -v apt-get >/dev/null 2>&1; then export DEBIAN_FRONTEND=noninteractive; apt-get update -y >/dev/null 2>&1 || true; apt-get install -y inetutils-telnet ldap-utils lsof mlocate smbclient samba-common-bin dnsutils >/dev/null 2>&1 || true; fi; if ! command -v b64encode >/dev/null 2>&1 && command -v base64 >/dev/null 2>&1; then printf '#!/usr/bin/env bash\\nbase64 \"$@\"\\n' > /usr/local/bin/b64encode && chmod +x /usr/local/bin/b64encode; fi\" } catch { Write-Host '[WARN] dependency bootstrap failed'; }; try { Invoke-AtomicTest T1565 -PathToAtomicsFolder '/opt/atomic-red-team/atomics' -TestNumbers 1 -GetPrereqs -ErrorAction Continue } catch { Write-Host '[WARN] GetPrereqs failed for T1565'; }; Invoke-AtomicTest T1565 -PathToAtomicsFolder '/opt/atomic-red-team/atomics' -TestNumbers 1"
        ],
        "stdout": "PathToAtomicsFolder = /opt/atomic-red-team/atomics\n\nGetPrereq's for: T1565-1 Simulate T1565 - Data Manipulation\nNo Preqs Defined\nPathToAtomicsFolder = /opt/atomic-red-team/atomics\n\nExecuting test: T1565-1 Simulate T1565 - Data Manipulation\n5ec2c622d904\nSimulating T1565 - Data Manipulation\nuid=0(root) gid=0(root) groups=0(root)\n1777186392\nExit code: 0\nDone executing test: T1565-1 Simulate T1565 - Data Manipulation\n",
        "stdout_sha256": "90c6db8a87b99d47a712e72a1a8008edaffa8bef9209a0af0ff882dc678afe21",
        "stderr_sha256": "5806f2eea2beb8c1be744430dc0a75220200035d8c8ce743ac44188bf6c8ff74",
        "real_execution": true,
        "network_anchors": {
          "stdout_paths": [
            "/opt/atomic-red-team/atomics"
          ]
        }
      },
      {
        "run_id": "e786e55889c0490ba52925b01bdc803b",
        "job_id": "sandbox-real-sweep",
        "job_name": "Full Real Execution Sandbox Sweep",
        "finished_at": "2026-04-26T06:45:03.679895+00:00",
        "exit_code": 0,
        "sandbox": "docker-network-none-cap-drop-all",
        "status": "success",
        "outcome": "real_execution",
        "command": [
          "docker",
          "run",
          "--rm",
          "--name",
          "seraph-sandbox-e786e55889c0",
          "--network",
          "none",
          "--cap-drop",
          "ALL",
          "--cap-add",
          "SETUID",
          "--cap-add",
          "SETGID",
          "--cap-add",
          "CHOWN",
          "--cap-add",
          "DAC_OVERRIDE",
          "--cap-add",
          "FOWNER",
          "--cap-add",
          "SYS_PTRACE",
          "--cap-add",
          "NET_RAW",
          "--security-opt",
          "no-new-privileges:false",
          "--tmpfs",
          "/tmp:exec,size=512m",
          "-v",
          "/home/byron/Downloads/Metatron-triune-outbound-gate/atomic-red-team:/opt/atomic-red-team:ro",
          "-v",
          "/home/byron/Downloads/Metatron-triune-outbound-gate/tools/invoke-atomicredteam:/opt/invoke-atomicredteam:ro",
          "-v",
          "/home/byron/Downloads/Metatron-triune-outbound-gate/tools/powershell:/opt/pwsh:ro",
          "seraph-sandbox-tools:latest",
          "/opt/pwsh/pwsh",
          "-NonInteractive",
          "-NoProfile",
          "-Command",
          "Import-Module '/opt/invoke-atomicredteam/Invoke-AtomicRedTeam.psd1' -ErrorAction Stop; $env:PathToAtomicsFolder='/opt/atomic-red-team/atomics'; try { bash -lc \"if command -v apt-get >/dev/null 2>&1; then export DEBIAN_FRONTEND=noninteractive; apt-get update -y >/dev/null 2>&1 || true; apt-get install -y inetutils-telnet ldap-utils lsof mlocate smbclient samba-common-bin dnsutils >/dev/null 2>&1 || true; fi; if ! command -v b64encode >/dev/null 2>&1 && command -v base64 >/dev/null 2>&1; then printf '#!/usr/bin/env bash\\nbase64 \"$@\"\\n' > /usr/local/bin/b64encode && chmod +x /usr/local/bin/b64encode; fi\" } catch { Write-Host '[WARN] dependency bootstrap failed'; }; try { Invoke-AtomicTest T1565 -PathToAtomicsFolder '/opt/atomic-red-team/atomics' -TestNumbers 1 -GetPrereqs -ErrorAction Continue } catch { Write-Host '[WARN] GetPrereqs failed for T1565'; }; Invoke-AtomicTest T1565 -PathToAtomicsFolder '/opt/atomic-red-team/atomics' -TestNumbers 1"
        ],
        "stdout": "PathToAtomicsFolder = /opt/atomic-red-team/atomics\n\nGetPrereq's for: T1565-1 Simulate T1565 - Data Manipulation\nNo Preqs Defined\nPathToAtomicsFolder = /opt/atomic-red-team/atomics\n\nExecuting test: T1565-1 Simulate T1565 - Data Manipulation\nSimulating T1565 - Data Manipulation\n1777185903\n4a0cb4b5c893\nuid=0(root) gid=0(root) groups=0(root)\nExit code: 0\nDone executing test: T1565-1 Simulate T1565 - Data Manipulation\n",
        "stdout_sha256": "f160c04ecd7164cf61b14c78bbc799deb60b25f720009abf6e3407e9c57b09d4",
        "stderr_sha256": "5806f2eea2beb8c1be744430dc0a75220200035d8c8ce743ac44188bf6c8ff74",
        "real_execution": true,
        "network_anchors": {
          "stdout_paths": [
            "/opt/atomic-red-team/atomics"
          ]
        }
      },
      {
        "run_id": "5ce142d1115b4163bd4f60f5f31f8393",
        "job_id": "sandbox-real-sweep",
        "job_name": "Full Real Execution Sandbox Sweep",
        "finished_at": "2026-04-18T13:22:53.445955+00:00",
        "exit_code": 0,
        "sandbox": "docker-network-none-cap-drop-all",
        "status": "success",
        "outcome": "",
        "command": [
          "docker",
          "run",
          "--rm",
          "--name",
          "seraph-sandbox-5ce142d1115b",
          "--network",
          "none",
          "--cap-drop",
          "ALL",
          "--cap-add",
          "SETUID",
          "--cap-add",
          "SETGID",
          "--cap-add",
          "CHOWN",
          "--cap-add",
          "DAC_OVERRIDE",
          "--cap-add",
          "FOWNER",
          "--cap-add",
          "SYS_PTRACE",
          "--security-opt",
          "no-new-privileges:false",
          "-v",
          "/home/byron/Downloads/Metatron-triune-outbound-gate/atomic-red-team:/opt/atomic-red-team:ro",
          "-v",
          "/home/byron/Downloads/Metatron-triune-outbound-gate/tools/invoke-atomicredteam:/opt/invoke-atomicredteam:ro",
          "seraph-sandbox-tools:latest",
          "pwsh",
          "-NonInteractive",
          "-NoProfile",
          "-Command",
          "Import-Module '/opt/invoke-atomicredteam/Invoke-AtomicRedTeam.psd1' -ErrorAction Stop; $env:PathToAtomicsFolder='/opt/atomic-red-team/atomics'; Invoke-AtomicTest T1565 -PathToAtomicsFolder '/opt/atomic-red-team/atomics'"
        ],
        "stdout": "PathToAtomicsFolder = /opt/atomic-red-team/atomics\n\nExecuting test: T1565-1 Simulate T1565 - Data Manipulation\nSimulating T1565 - Data Manipulation\nuid=0(root) gid=0(root) groups=0(root)\n513d249f9b4b\n1776518573\nExit code: 0\nDone executing test: T1565-1 Simulate T1565 - Data Manipulation\n",
        "stdout_sha256": "f0d299789fec4f550e50b2552e089d46750c9ce33218e0724e78306b1e85add7",
        "stderr_sha256": "e3b0c44298fc1c149afbf4c8996fb92427ae41e4649b934ca495991b7852b855",
        "real_execution": true,
        "network_anchors": {
          "stdout_paths": [
            "/opt/atomic-red-team/atomics"
          ]
        }
      },
      {
        "run_id": "5eed94cce9af4081a5da30ba637037e9",
        "job_id": "sandbox-real-sweep",
        "job_name": "Full Real Execution Sandbox Sweep",
        "finished_at": "2026-04-18T14:41:30.338603+00:00",
        "exit_code": 0,
        "sandbox": "docker-network-none-cap-drop-all",
        "status": "success",
        "outcome": "real_execution",
        "command": [
          "docker",
          "run",
          "--rm",
          "--name",
          "seraph-sandbox-5eed94cce9af",
          "--network",
          "none",
          "--cap-drop",
          "ALL",
          "--cap-add",
          "SETUID",
          "--cap-add",
          "SETGID",
          "--cap-add",
          "CHOWN",
          "--cap-add",
          "DAC_OVERRIDE",
          "--cap-add",
          "FOWNER",
          "--cap-add",
          "SYS_PTRACE",
          "--security-opt",
          "no-new-privileges:false",
          "-v",
          "/home/byron/Downloads/Metatron-triune-outbound-gate/atomic-red-team:/opt/atomic-red-team:ro",
          "-v",
          "/home/byron/Downloads/Metatron-triune-outbound-gate/tools/invoke-atomicredteam:/opt/invoke-atomicredteam:ro",
          "seraph-sandbox-tools:latest",
          "pwsh",
          "-NonInteractive",
          "-NoProfile",
          "-Command",
          "Import-Module '/opt/invoke-atomicredteam/Invoke-AtomicRedTeam.psd1' -ErrorAction Stop; $env:PathToAtomicsFolder='/opt/atomic-red-team/atomics'; Invoke-AtomicTest T1565 -PathToAtomicsFolder '/opt/atomic-red-team/atomics'"
        ],
        "stdout": "PathToAtomicsFolder = /opt/atomic-red-team/atomics\n\nExecuting test: T1565-1 Simulate T1565 - Data Manipulation\nSimulating T1565 - Data Manipulation\nuid=0(root) gid=0(root) groups=0(root)\nf6e8089a9763\n1776523290\nExit code: 0\nDone executing test: T1565-1 Simulate T1565 - Data Manipulation\n",
        "stdout_sha256": "b58fb4c1cf7f13ad399b0f2bade1533978e4fb3b43fca4feefd3f474d3a43d61",
        "stderr_sha256": "e3b0c44298fc1c149afbf4c8996fb92427ae41e4649b934ca495991b7852b855",
        "real_execution": true
      },
      {
        "run_id": "7554c2d42bf4476d8b25dc24e7381b87",
        "job_id": "sandbox-real-sweep",
        "job_name": "Full Real Execution Sandbox Sweep",
        "finished_at": "2026-04-18T18:58:51.723517+00:00",
        "exit_code": 0,
        "sandbox": "docker-network-none-cap-drop-all",
        "status": "success",
        "outcome": "real_execution",
        "command": [
          "docker",
          "run",
          "--rm",
          "--name",
          "seraph-sandbox-7554c2d42bf4",
          "--network",
          "none",
          "--cap-drop",
          "ALL",
          "--cap-add",
          "SETUID",
          "--cap-add",
          "SETGID",
          "--cap-add",
          "CHOWN",
          "--cap-add",
          "DAC_OVERRIDE",
          "--cap-add",
          "FOWNER",
          "--cap-add",
          "SYS_PTRACE",
          "--security-opt",
          "no-new-privileges:false",
          "-v",
          "/home/byron/Downloads/Metatron-triune-outbound-gate/atomic-red-team:/opt/atomic-red-team:ro",
          "-v",
          "/home/byron/Downloads/Metatron-triune-outbound-gate/tools/invoke-atomicredteam:/opt/invoke-atomicredteam:ro",
          "seraph-sandbox-tools:latest",
          "pwsh",
          "-NonInteractive",
          "-NoProfile",
          "-Command",
          "Import-Module '/opt/invoke-atomicredteam/Invoke-AtomicRedTeam.psd1' -ErrorAction Stop; $env:PathToAtomicsFolder='/opt/atomic-red-team/atomics'; Invoke-AtomicTest T1565 -PathToAtomicsFolder '/opt/atomic-red-team/atomics'"
        ],
        "stdout": "PathToAtomicsFolder = /opt/atomic-red-team/atomics\n\nExecuting test: T1565-1 Simulate T1565 - Data Manipulation\nuid=0(root) gid=0(root) groups=0(root)\nSimulating T1565 - Data Manipulation\n4fd8ce3c49c5\n1776538731\nExit code: 0\nDone executing test: T1565-1 Simulate T1565 - Data Manipulation\n",
        "stdout_sha256": "d3410cbc115192de9981d3cf9a01cff5f0f5b40a277a84647e2c5812f2939ba7",
        "stderr_sha256": "e3b0c44298fc1c149afbf4c8996fb92427ae41e4649b934ca495991b7852b855",
        "real_execution": true
      },
      {
        "run_id": "89c73488622f47bcbc7229288a134d48",
        "job_id": "sandbox-real-sweep",
        "job_name": "Full Real Execution Sandbox Sweep",
        "finished_at": "2026-04-18T18:52:34.813110+00:00",
        "exit_code": 0,
        "sandbox": "docker-network-none-cap-drop-all",
        "status": "success",
        "outcome": "real_execution",
        "command": [
          "docker",
          "run",
          "--rm",
          "--name",
          "seraph-sandbox-89c73488622f",
          "--network",
          "none",
          "--cap-drop",
          "ALL",
          "--cap-add",
          "SETUID",
          "--cap-add",
          "SETGID",
          "--cap-add",
          "CHOWN",
          "--cap-add",
          "DAC_OVERRIDE",
          "--cap-add",
          "FOWNER",
          "--cap-add",
          "SYS_PTRACE",
          "--security-opt",
          "no-new-privileges:false",
          "-v",
          "/home/byron/Downloads/Metatron-triune-outbound-gate/atomic-red-team:/opt/atomic-red-team:ro",
          "-v",
          "/home/byron/Downloads/Metatron-triune-outbound-gate/tools/invoke-atomicredteam:/opt/invoke-atomicredteam:ro",
          "seraph-sandbox-tools:latest",
          "pwsh",
          "-NonInteractive",
          "-NoProfile",
          "-Command",
          "Import-Module '/opt/invoke-atomicredteam/Invoke-AtomicRedTeam.psd1' -ErrorAction Stop; $env:PathToAtomicsFolder='/opt/atomic-red-team/atomics'; Invoke-AtomicTest T1565 -PathToAtomicsFolder '/opt/atomic-red-team/atomics'"
        ],
        "stdout": "PathToAtomicsFolder = /opt/atomic-red-team/atomics\n\nExecuting test: T1565-1 Simulate T1565 - Data Manipulation\nSimulating T1565 - Data Manipulation\nuid=0(root) gid=0(root) groups=0(root)\nc3e04873b783\n1776538354\nExit code: 0\nDone executing test: T1565-1 Simulate T1565 - Data Manipulation\n",
        "stdout_sha256": "94e78f05958da8debee3734d23344f57bb981e5b15c51b7dcc9d8be96328dde7",
        "stderr_sha256": "e3b0c44298fc1c149afbf4c8996fb92427ae41e4649b934ca495991b7852b855",
        "real_execution": true
      },
      {
        "run_id": "bcfab315493249dd8c077e86f4a64ddc",
        "job_id": "sandbox-real-sweep",
        "job_name": "Full Real Execution Sandbox Sweep",
        "finished_at": "2026-04-18T14:33:54.835614+00:00",
        "exit_code": 0,
        "sandbox": "docker-network-none-cap-drop-all",
        "status": "success",
        "outcome": "real_execution",
        "command": [
          "docker",
          "run",
          "--rm",
          "--name",
          "seraph-sandbox-bcfab3154932",
          "--network",
          "none",
          "--cap-drop",
          "ALL",
          "--cap-add",
          "SETUID",
          "--cap-add",
          "SETGID",
          "--cap-add",
          "CHOWN",
          "--cap-add",
          "DAC_OVERRIDE",
          "--cap-add",
          "FOWNER",
          "--cap-add",
          "SYS_PTRACE",
          "--security-opt",
          "no-new-privileges:false",
          "-v",
          "/home/byron/Downloads/Metatron-triune-outbound-gate/atomic-red-team:/opt/atomic-red-team:ro",
          "-v",
          "/home/byron/Downloads/Metatron-triune-outbound-gate/tools/invoke-atomicredteam:/opt/invoke-atomicredteam:ro",
          "seraph-sandbox-tools:latest",
          "pwsh",
          "-NonInteractive",
          "-NoProfile",
          "-Command",
          "Import-Module '/opt/invoke-atomicredteam/Invoke-AtomicRedTeam.psd1' -ErrorAction Stop; $env:PathToAtomicsFolder='/opt/atomic-red-team/atomics'; Invoke-AtomicTest T1565 -PathToAtomicsFolder '/opt/atomic-red-team/atomics'"
        ],
        "stdout": "PathToAtomicsFolder = /opt/atomic-red-team/atomics\n\nExecuting test: T1565-1 Simulate T1565 - Data Manipulation\nuid=0(root) gid=0(root) groups=0(root)\nSimulating T1565 - Data Manipulation\n13cd22f4e022\n1776522834\nExit code: 0\nDone executing test: T1565-1 Simulate T1565 - Data Manipulation\n",
        "stdout_sha256": "688f8e6c83f9fa3304aa96e12bb195f0ee043f38f5da91aa7ff7cdf6bc32ad46",
        "stderr_sha256": "e3b0c44298fc1c149afbf4c8996fb92427ae41e4649b934ca495991b7852b855",
        "real_execution": true
      },
      {
        "run_id": "5ce142d1115b4163bd4f60f5f31f8393",
        "job_id": "sandbox-real-sweep",
        "job_name": "Full Real Execution Sandbox Sweep",
        "finished_at": "2026-04-18T13:22:53.445955+00:00",
        "exit_code": 0,
        "sandbox": "docker-network-none-cap-drop-all",
        "status": "success",
        "outcome": "",
        "command": [
          "docker",
          "run",
          "--rm",
          "--name",
          "seraph-sandbox-5ce142d1115b",
          "--network",
          "none",
          "--cap-drop",
          "ALL",
          "--cap-add",
          "SETUID",
          "--cap-add",
          "SETGID",
          "--cap-add",
          "CHOWN",
          "--cap-add",
          "DAC_OVERRIDE",
          "--cap-add",
          "FOWNER",
          "--cap-add",
          "SYS_PTRACE",
          "--security-opt",
          "no-new-privileges:false",
          "-v",
          "/home/byron/Downloads/Metatron-triune-outbound-gate/atomic-red-team:/opt/atomic-red-team:ro",
          "-v",
          "/home/byron/Downloads/Metatron-triune-outbound-gate/tools/invoke-atomicredteam:/opt/invoke-atomicredteam:ro",
          "seraph-sandbox-tools:latest",
          "pwsh",
          "-NonInteractive",
          "-NoProfile",
          "-Command",
          "Import-Module '/opt/invoke-atomicredteam/Invoke-AtomicRedTeam.psd1' -ErrorAction Stop; $env:PathToAtomicsFolder='/opt/atomic-red-team/atomics'; Invoke-AtomicTest T1565 -PathToAtomicsFolder '/opt/atomic-red-team/atomics'"
        ],
        "stdout": "PathToAtomicsFolder = /opt/atomic-red-team/atomics\n\nExecuting test: T1565-1 Simulate T1565 - Data Manipulation\nSimulating T1565 - Data Manipulation\nuid=0(root) gid=0(root) groups=0(root)\n513d249f9b4b\n1776518573\nExit code: 0\nDone executing test: T1565-1 Simulate T1565 - Data Manipulation\n",
        "stdout_sha256": "f0d299789fec4f550e50b2552e089d46750c9ce33218e0724e78306b1e85add7",
        "stderr_sha256": "e3b0c44298fc1c149afbf4c8996fb92427ae41e4649b934ca495991b7852b855",
        "real_execution": true,
        "network_anchors": {
          "stdout_paths": [
            "/opt/atomic-red-team/atomics"
          ]
        }
      }
    ]
  },
  "telemetry_evidence": {
    "sources": [
      {
        "source_name": "osquery",
        "file": "telemetry/osquery.ndjson",
        "sha256": "5c6915e84b30b4b6c5ebf64455e38f52965cd41d3ff148914642ea1c7f5fb470"
      },
      {
        "source_name": "atomic_execution",
        "file": "telemetry/atomic_stdout.ndjson",
        "sha256": "f0d299789fec4f550e50b2552e089d46750c9ce33218e0724e78306b1e85add7"
      }
    ],
    "key_events": [
      {
        "source": "osquery",
        "event_id": "osq-1776928034-atomic_t1565_b1",
        "timestamp": "2026-04-23T07:07:13.775569+00:00",
        "query_name": "atomic_t1565_b1",
        "action": "added",
        "columns": {
          "test_name": "T1565-1 Simulate T1565 - Data Manipulation",
          "technique_id": "T1565",
          "run_id": "24abaea50d7a46e99354c98c5dd05996",
          "CommandLine": "uid=0(root) gid=0(root) groups=0(root)\nSimulating T1565 - Data Manipulation\n17f91161dac1\n1776928033\nExit code: 0\nDone executing test: T1565-1 Simulate T1565 - Data Manipulation",
          "Image": "",
          "TargetFilename": "",
          "DestinationIp": "",
          "SourceIp": "",
          "extracted_paths": "[]",
          "extracted_ips": "[]",
          "extracted_hashes": "[]",
          "extracted_pids": "[]",
          "stdout_block": "Executing test: T1565-1 Simulate T1565 - Data Manipulation\nuid=0(root) gid=0(root) groups=0(root)\nSimulating T1565 - Data Manipulation\n17f91161dac1\n1776928033\nExit code: 0\nDone executing test: T1565-1 Simulate T1565 - Data Manipulation\n"
        },
        "host_identifier": "debian-node-01"
      },
      {
        "source": "osquery",
        "event_id": "osq-1776928034-atomic_t1565_b1",
        "timestamp": "2026-04-23T07:07:13.775569+00:00",
        "query_name": "atomic_t1565_b1",
        "action": "added",
        "columns": {
          "test_name": "T1565-1 Simulate T1565 - Data Manipulation",
          "technique_id": "T1565",
          "run_id": "24abaea50d7a46e99354c98c5dd05996",
          "CommandLine": "uid=0(root) gid=0(root) groups=0(root)\nSimulating T1565 - Data Manipulation\n17f91161dac1\n1776928033\nExit code: 0\nDone executing test: T1565-1 Simulate T1565 - Data Manipulation",
          "Image": "",
          "TargetFilename": "",
          "DestinationIp": "",
          "SourceIp": "",
          "extracted_paths": "[]",
          "extracted_ips": "[]",
          "extracted_hashes": "[]",
          "extracted_pids": "[]",
          "stdout_block": "Executing test: T1565-1 Simulate T1565 - Data Manipulation\nuid=0(root) gid=0(root) groups=0(root)\nSimulating T1565 - Data Manipulation\n17f91161dac1\n1776928033\nExit code: 0\nDone executing test: T1565-1 Simulate T1565 - Data Manipulation\n"
        },
        "host_identifier": "debian-node-01"
      },
      {
        "source": "osquery",
        "event_id": "osq-1776518574-atomic_t1565_b1",
        "timestamp": "2026-04-18T13:22:53.445955+00:00",
        "query_name": "atomic_t1565_b1",
        "action": "added",
        "columns": {
          "test_name": "T1565-1 Simulate T1565 - Data Manipulation",
          "technique_id": "T1565",
          "run_id": "5ce142d1115b4163bd4f60f5f31f8393",
          "CommandLine": "Simulating T1565 - Data Manipulation\nuid=0(root) gid=0(root) groups=0(root)\n513d249f9b4b\n1776518573\nExit code: 0\nDone executing test: T1565-1 Simulate T1565 - Data Manipulation",
          "Image": "",
          "TargetFilename": "",
          "DestinationIp": "",
          "SourceIp": "",
          "extracted_paths": "[]",
          "extracted_ips": "[]",
          "extracted_hashes": "[]",
          "extracted_pids": "[]",
          "stdout_block": "Executing test: T1565-1 Simulate T1565 - Data Manipulation\nSimulating T1565 - Data Manipulation\nuid=0(root) gid=0(root) groups=0(root)\n513d249f9b4b\n1776518573\nExit code: 0\nDone executing test: T1565-1 Simulate T1565 - Data Manipulation\n"
        },
        "host_identifier": "debian-node-01"
      },
      {
        "source": "osquery",
        "event_id": "osq-1777186393-atomic_t1565_b1",
        "timestamp": "2026-04-26T06:53:12.834246+00:00",
        "query_name": "atomic_t1565_b1",
        "action": "added",
        "columns": {
          "test_name": "T1565-1 Simulate T1565 - Data Manipulation",
          "technique_id": "T1565",
          "run_id": "dbdeaf68f1de4dd892b475bee91b0765",
          "CommandLine": "5ec2c622d904\nSimulating T1565 - Data Manipulation\nuid=0(root) gid=0(root) groups=0(root)\n1777186392\nExit code: 0\nDone executing test: T1565-1 Simulate T1565 - Data Manipulation",
          "Image": "",
          "TargetFilename": "",
          "DestinationIp": "",
          "SourceIp": "",
          "extracted_paths": "[]",
          "extracted_ips": "[]",
          "extracted_hashes": "[]",
          "extracted_pids": "[]",
          "stdout_block": "Executing test: T1565-1 Simulate T1565 - Data Manipulation\n5ec2c622d904\nSimulating T1565 - Data Manipulation\nuid=0(root) gid=0(root) groups=0(root)\n1777186392\nExit code: 0\nDone executing test: T1565-1 Simulate T1565 - Data Manipulation\n"
        },
        "host_identifier": "debian-node-01"
      },
      {
        "source": "osquery",
        "event_id": "osq-1777185904-atomic_t1565_b1",
        "timestamp": "2026-04-26T06:45:03.679895+00:00",
        "query_name": "atomic_t1565_b1",
        "action": "added",
        "columns": {
          "test_name": "T1565-1 Simulate T1565 - Data Manipulation",
          "technique_id": "T1565",
          "run_id": "e786e55889c0490ba52925b01bdc803b",
          "CommandLine": "Simulating T1565 - Data Manipulation\n1777185903\n4a0cb4b5c893\nuid=0(root) gid=0(root) groups=0(root)\nExit code: 0\nDone executing test: T1565-1 Simulate T1565 - Data Manipulation",
          "Image": "",
          "TargetFilename": "",
          "DestinationIp": "",
          "SourceIp": "",
          "extracted_paths": "[]",
          "extracted_ips": "[]",
          "extracted_hashes": "[]",
          "extracted_pids": "[]",
          "stdout_block": "Executing test: T1565-1 Simulate T1565 - Data Manipulation\nSimulating T1565 - Data Manipulation\n1777185903\n4a0cb4b5c893\nuid=0(root) gid=0(root) groups=0(root)\nExit code: 0\nDone executing test: T1565-1 Simulate T1565 - Data Manipulation\n"
        },
        "host_identifier": "debian-node-01"
      },
      {
        "source": "osquery",
        "event_id": "osq-1776518574-atomic_t1565_b1",
        "timestamp": "2026-04-18T13:22:53.445955+00:00",
        "query_name": "atomic_t1565_b1",
        "action": "added",
        "columns": {
          "test_name": "T1565-1 Simulate T1565 - Data Manipulation",
          "technique_id": "T1565",
          "run_id": "5ce142d1115b4163bd4f60f5f31f8393",
          "CommandLine": "Simulating T1565 - Data Manipulation\nuid=0(root) gid=0(root) groups=0(root)\n513d249f9b4b\n1776518573\nExit code: 0\nDone executing test: T1565-1 Simulate T1565 - Data Manipulation",
          "Image": "",
          "TargetFilename": "",
          "DestinationIp": "",
          "SourceIp": "",
          "extracted_paths": "[]",
          "extracted_ips": "[]",
          "extracted_hashes": "[]",
          "extracted_pids": "[]",
          "stdout_block": "Executing test: T1565-1 Simulate T1565 - Data Manipulation\nSimulating T1565 - Data Manipulation\nuid=0(root) gid=0(root) groups=0(root)\n513d249f9b4b\n1776518573\nExit code: 0\nDone executing test: T1565-1 Simulate T1565 - Data Manipulation\n"
        },
        "host_identifier": "debian-node-01"
      },
      {
        "source": "osquery",
        "event_id": "osq-1776518574-atomic_t1565_b1",
        "timestamp": "2026-04-18T13:22:53.445955+00:00",
        "query_name": "atomic_t1565_b1",
        "action": "added",
        "columns": {
          "test_name": "T1565-1 Simulate T1565 - Data Manipulation",
          "technique_id": "T1565",
          "run_id": "5ce142d1115b4163bd4f60f5f31f8393",
          "CommandLine": "Simulating T1565 - Data Manipulation\nuid=0(root) gid=0(root) groups=0(root)\n513d249f9b4b\n1776518573\nExit code: 0\nDone executing test: T1565-1 Simulate T1565 - Data Manipulation",
          "Image": "",
          "TargetFilename": "",
          "DestinationIp": "",
          "SourceIp": "",
          "extracted_paths": "[]",
          "extracted_ips": "[]",
          "extracted_hashes": "[]",
          "extracted_pids": "[]",
          "stdout_block": "Executing test: T1565-1 Simulate T1565 - Data Manipulation\nSimulating T1565 - Data Manipulation\nuid=0(root) gid=0(root) groups=0(root)\n513d249f9b4b\n1776518573\nExit code: 0\nDone executing test: T1565-1 Simulate T1565 - Data Manipulation\n"
        },
        "host_identifier": "debian-node-01"
      }
    ]
  },
  "execution_evidence": {
    "observed": true,
    "command_line": "['docker', 'run', '--rm', '--name', 'seraph-sandbox-5ce142d1115b', '--network', 'none', '--cap-drop', 'ALL', '--cap-add', 'SETUID', '--cap-add', 'SETGID', '--cap-add', 'CHOWN', '--cap-add', 'DAC_OVERRIDE', '--cap-add', 'FOWNER', '--cap-add', 'SYS_PTRACE', '--security-opt', 'no-new-privileges:false', '-v', '/home/byron/Downloads/Metatron-triune-outbound-gate/atomic-red-team:/opt/atomic-red-team:ro', '-v', '/home/byron/Downloads/Metatron-triune-outbound-gate/tools/invoke-atomicredteam:/opt/invoke-atomicredteam:ro', 'seraph-sandbox-tools:latest', 'pwsh', '-NonInteractive', '-NoProfile', '-Command', \"Import-Module '/opt/invoke-atomicredteam/Invoke-AtomicRedTeam.psd1' -ErrorAction Stop; $env:PathToAtomicsFolder='/opt/atomic-red-team/atomics'; Invoke-AtomicTest T1565 -PathToAtomicsFolder '/opt/atomic-red-team/atomics'\"]",
    "exit_code": 0,
    "run_ids": [
      "24abaea50d7a46e99354c98c5dd05996",
      "24abaea50d7a46e99354c98c5dd05996",
      "5ce142d1115b4163bd4f60f5f31f8393",
      "dbdeaf68f1de4dd892b475bee91b0765",
      "e786e55889c0490ba52925b01bdc803b",
      "5ce142d1115b4163bd4f60f5f31f8393",
      "5eed94cce9af4081a5da30ba637037e9",
      "7554c2d42bf4476d8b25dc24e7381b87",
      "89c73488622f47bcbc7229288a134d48",
      "bcfab315493249dd8c077e86f4a64ddc",
      "5ce142d1115b4163bd4f60f5f31f8393"
    ],
    "process_ids": [
      4242
    ],
    "timestamps": [
      "2026-04-23T07:07:13.775569+00:00",
      "2026-04-18T13:22:53.445955+00:00",
      "2026-04-26T06:53:12.834246+00:00",
      "2026-04-26T06:45:03.679895+00:00",
      "2026-04-18T14:41:30.338603+00:00",
      "2026-04-18T18:58:51.723517+00:00",
      "2026-04-18T18:52:34.813110+00:00",
      "2026-04-18T14:33:54.835614+00:00"
    ]
  },
  "host_telemetry_evidence": {
    "observed": true,
    "sources": [
      {
        "source_name": "osquery",
        "file": "telemetry/osquery.ndjson",
        "sha256": "5c6915e84b30b4b6c5ebf64455e38f52965cd41d3ff148914642ea1c7f5fb470"
      },
      {
        "source_name": "atomic_execution",
        "file": "telemetry/atomic_stdout.ndjson",
        "sha256": "f0d299789fec4f550e50b2552e089d46750c9ce33218e0724e78306b1e85add7"
      }
    ],
    "events": [
      {
        "source": "osquery",
        "event_id": "osq-1776928034-atomic_t1565_b1",
        "timestamp": "2026-04-23T07:07:13.775569+00:00",
        "query_name": "atomic_t1565_b1",
        "action": "added",
        "columns": {
          "test_name": "T1565-1 Simulate T1565 - Data Manipulation",
          "technique_id": "T1565",
          "run_id": "24abaea50d7a46e99354c98c5dd05996",
          "CommandLine": "uid=0(root) gid=0(root) groups=0(root)\nSimulating T1565 - Data Manipulation\n17f91161dac1\n1776928033\nExit code: 0\nDone executing test: T1565-1 Simulate T1565 - Data Manipulation",
          "Image": "",
          "TargetFilename": "",
          "DestinationIp": "",
          "SourceIp": "",
          "extracted_paths": "[]",
          "extracted_ips": "[]",
          "extracted_hashes": "[]",
          "extracted_pids": "[]",
          "stdout_block": "Executing test: T1565-1 Simulate T1565 - Data Manipulation\nuid=0(root) gid=0(root) groups=0(root)\nSimulating T1565 - Data Manipulation\n17f91161dac1\n1776928033\nExit code: 0\nDone executing test: T1565-1 Simulate T1565 - Data Manipulation\n"
        },
        "host_identifier": "debian-node-01"
      },
      {
        "source": "osquery",
        "event_id": "osq-1776928034-atomic_t1565_b1",
        "timestamp": "2026-04-23T07:07:13.775569+00:00",
        "query_name": "atomic_t1565_b1",
        "action": "added",
        "columns": {
          "test_name": "T1565-1 Simulate T1565 - Data Manipulation",
          "technique_id": "T1565",
          "run_id": "24abaea50d7a46e99354c98c5dd05996",
          "CommandLine": "uid=0(root) gid=0(root) groups=0(root)\nSimulating T1565 - Data Manipulation\n17f91161dac1\n1776928033\nExit code: 0\nDone executing test: T1565-1 Simulate T1565 - Data Manipulation",
          "Image": "",
          "TargetFilename": "",
          "DestinationIp": "",
          "SourceIp": "",
          "extracted_paths": "[]",
          "extracted_ips": "[]",
          "extracted_hashes": "[]",
          "extracted_pids": "[]",
          "stdout_block": "Executing test: T1565-1 Simulate T1565 - Data Manipulation\nuid=0(root) gid=0(root) groups=0(root)\nSimulating T1565 - Data Manipulation\n17f91161dac1\n1776928033\nExit code: 0\nDone executing test: T1565-1 Simulate T1565 - Data Manipulation\n"
        },
        "host_identifier": "debian-node-01"
      },
      {
        "source": "osquery",
        "event_id": "osq-1776518574-atomic_t1565_b1",
        "timestamp": "2026-04-18T13:22:53.445955+00:00",
        "query_name": "atomic_t1565_b1",
        "action": "added",
        "columns": {
          "test_name": "T1565-1 Simulate T1565 - Data Manipulation",
          "technique_id": "T1565",
          "run_id": "5ce142d1115b4163bd4f60f5f31f8393",
          "CommandLine": "Simulating T1565 - Data Manipulation\nuid=0(root) gid=0(root) groups=0(root)\n513d249f9b4b\n1776518573\nExit code: 0\nDone executing test: T1565-1 Simulate T1565 - Data Manipulation",
          "Image": "",
          "TargetFilename": "",
          "DestinationIp": "",
          "SourceIp": "",
          "extracted_paths": "[]",
          "extracted_ips": "[]",
          "extracted_hashes": "[]",
          "extracted_pids": "[]",
          "stdout_block": "Executing test: T1565-1 Simulate T1565 - Data Manipulation\nSimulating T1565 - Data Manipulation\nuid=0(root) gid=0(root) groups=0(root)\n513d249f9b4b\n1776518573\nExit code: 0\nDone executing test: T1565-1 Simulate T1565 - Data Manipulation\n"
        },
        "host_identifier": "debian-node-01"
      },
      {
        "source": "osquery",
        "event_id": "osq-1777186393-atomic_t1565_b1",
        "timestamp": "2026-04-26T06:53:12.834246+00:00",
        "query_name": "atomic_t1565_b1",
        "action": "added",
        "columns": {
          "test_name": "T1565-1 Simulate T1565 - Data Manipulation",
          "technique_id": "T1565",
          "run_id": "dbdeaf68f1de4dd892b475bee91b0765",
          "CommandLine": "5ec2c622d904\nSimulating T1565 - Data Manipulation\nuid=0(root) gid=0(root) groups=0(root)\n1777186392\nExit code: 0\nDone executing test: T1565-1 Simulate T1565 - Data Manipulation",
          "Image": "",
          "TargetFilename": "",
          "DestinationIp": "",
          "SourceIp": "",
          "extracted_paths": "[]",
          "extracted_ips": "[]",
          "extracted_hashes": "[]",
          "extracted_pids": "[]",
          "stdout_block": "Executing test: T1565-1 Simulate T1565 - Data Manipulation\n5ec2c622d904\nSimulating T1565 - Data Manipulation\nuid=0(root) gid=0(root) groups=0(root)\n1777186392\nExit code: 0\nDone executing test: T1565-1 Simulate T1565 - Data Manipulation\n"
        },
        "host_identifier": "debian-node-01"
      },
      {
        "source": "osquery",
        "event_id": "osq-1777185904-atomic_t1565_b1",
        "timestamp": "2026-04-26T06:45:03.679895+00:00",
        "query_name": "atomic_t1565_b1",
        "action": "added",
        "columns": {
          "test_name": "T1565-1 Simulate T1565 - Data Manipulation",
          "technique_id": "T1565",
          "run_id": "e786e55889c0490ba52925b01bdc803b",
          "CommandLine": "Simulating T1565 - Data Manipulation\n1777185903\n4a0cb4b5c893\nuid=0(root) gid=0(root) groups=0(root)\nExit code: 0\nDone executing test: T1565-1 Simulate T1565 - Data Manipulation",
          "Image": "",
          "TargetFilename": "",
          "DestinationIp": "",
          "SourceIp": "",
          "extracted_paths": "[]",
          "extracted_ips": "[]",
          "extracted_hashes": "[]",
          "extracted_pids": "[]",
          "stdout_block": "Executing test: T1565-1 Simulate T1565 - Data Manipulation\nSimulating T1565 - Data Manipulation\n1777185903\n4a0cb4b5c893\nuid=0(root) gid=0(root) groups=0(root)\nExit code: 0\nDone executing test: T1565-1 Simulate T1565 - Data Manipulation\n"
        },
        "host_identifier": "debian-node-01"
      },
      {
        "source": "osquery",
        "event_id": "osq-1776518574-atomic_t1565_b1",
        "timestamp": "2026-04-18T13:22:53.445955+00:00",
        "query_name": "atomic_t1565_b1",
        "action": "added",
        "columns": {
          "test_name": "T1565-1 Simulate T1565 - Data Manipulation",
          "technique_id": "T1565",
          "run_id": "5ce142d1115b4163bd4f60f5f31f8393",
          "CommandLine": "Simulating T1565 - Data Manipulation\nuid=0(root) gid=0(root) groups=0(root)\n513d249f9b4b\n1776518573\nExit code: 0\nDone executing test: T1565-1 Simulate T1565 - Data Manipulation",
          "Image": "",
          "TargetFilename": "",
          "DestinationIp": "",
          "SourceIp": "",
          "extracted_paths": "[]",
          "extracted_ips": "[]",
          "extracted_hashes": "[]",
          "extracted_pids": "[]",
          "stdout_block": "Executing test: T1565-1 Simulate T1565 - Data Manipulation\nSimulating T1565 - Data Manipulation\nuid=0(root) gid=0(root) groups=0(root)\n513d249f9b4b\n1776518573\nExit code: 0\nDone executing test: T1565-1 Simulate T1565 - Data Manipulation\n"
        },
        "host_identifier": "debian-node-01"
      },
      {
        "source": "osquery",
        "event_id": "osq-1776518574-atomic_t1565_b1",
        "timestamp": "2026-04-18T13:22:53.445955+00:00",
        "query_name": "atomic_t1565_b1",
        "action": "added",
        "columns": {
          "test_name": "T1565-1 Simulate T1565 - Data Manipulation",
          "technique_id": "T1565",
          "run_id": "5ce142d1115b4163bd4f60f5f31f8393",
          "CommandLine": "Simulating T1565 - Data Manipulation\nuid=0(root) gid=0(root) groups=0(root)\n513d249f9b4b\n1776518573\nExit code: 0\nDone executing test: T1565-1 Simulate T1565 - Data Manipulation",
          "Image": "",
          "TargetFilename": "",
          "DestinationIp": "",
          "SourceIp": "",
          "extracted_paths": "[]",
          "extracted_ips": "[]",
          "extracted_hashes": "[]",
          "extracted_pids": "[]",
          "stdout_block": "Executing test: T1565-1 Simulate T1565 - Data Manipulation\nSimulating T1565 - Data Manipulation\nuid=0(root) gid=0(root) groups=0(root)\n513d249f9b4b\n1776518573\nExit code: 0\nDone executing test: T1565-1 Simulate T1565 - Data Manipulation\n"
        },
        "host_identifier": "debian-node-01"
      }
    ]
  },
  "network_telemetry_evidence": {
    "sources": [
      {
        "source_name": "zeek_conn",
        "file": "conn.log",
        "match_methods": [
          "time_window"
        ]
      }
    ],
    "key_events": [
      {
        "source": "zeek_conn",
        "match_method": "time_window",
        "timestamp": "1777117748.173587",
        "src_ip": "192.168.101.183",
        "src_port": "34820",
        "dest_ip": "192.168.101.1",
        "dest_port": "53",
        "proto": "udp",
        "service": "-",
        "connection_uid": "C6kAey1Xwhov3qtrq7"
      },
      {
        "source": "zeek_conn",
        "match_method": "time_window",
        "timestamp": "1777117748.166485",
        "src_ip": "192.168.101.183",
        "src_port": "44587",
        "dest_ip": "192.168.101.1",
        "dest_port": "53",
        "proto": "udp",
        "service": "-",
        "connection_uid": "C4EWG11CY3dcG4SO2k"
      },
      {
        "source": "zeek_conn",
        "match_method": "time_window",
        "timestamp": "1777117748.175578",
        "src_ip": "192.168.101.183",
        "src_port": "44736",
        "dest_ip": "192.168.101.1",
        "dest_port": "53",
        "proto": "udp",
        "service": "-",
        "connection_uid": "CYnQA64Ym1fVz61psf"
      },
      {
        "source": "zeek_conn",
        "match_method": "time_window",
        "timestamp": "1777117748.171940",
        "src_ip": "192.168.101.183",
        "src_port": "33002",
        "dest_ip": "192.168.101.1",
        "dest_port": "53",
        "proto": "udp",
        "service": "-",
        "connection_uid": "C1lRqy4bvul27cdp89"
      },
      {
        "source": "zeek_conn",
        "match_method": "time_window",
        "timestamp": "1777117748.172079",
        "src_ip": "192.168.101.183",
        "src_port": "44857",
        "dest_ip": "192.168.101.1",
        "dest_port": "53",
        "proto": "udp",
        "service": "-",
        "connection_uid": "CG1EP33lnYCNdl0qEc"
      },
      {
        "source": "zeek_conn",
        "match_method": "time_window",
        "timestamp": "1777117750.187661",
        "src_ip": "192.168.101.183",
        "src_port": "56803",
        "dest_ip": "192.168.101.1",
        "dest_port": "53",
        "proto": "udp",
        "service": "-",
        "connection_uid": "CXt6WU1G6duvc1nZo6"
      },
      {
        "source": "zeek_conn",
        "match_method": "time_window",
        "timestamp": "1777117750.187631",
        "src_ip": "192.168.101.183",
        "src_port": "49206",
        "dest_ip": "192.168.101.1",
        "dest_port": "53",
        "proto": "udp",
        "service": "-",
        "connection_uid": "C0hFj01W1mlSxg7JZe"
      },
      {
        "source": "zeek_conn",
        "match_method": "time_window",
        "timestamp": "1777117750.300124",
        "src_ip": "192.168.101.183",
        "src_port": "44681",
        "dest_ip": "192.168.101.1",
        "dest_port": "53",
        "proto": "udp",
        "service": "-",
        "connection_uid": "CpLl6B2klInBLm3Zdl"
      },
      {
        "source": "zeek_conn",
        "match_method": "time_window",
        "timestamp": "1777117750.296382",
        "src_ip": "192.168.101.183",
        "src_port": "50982",
        "dest_ip": "192.168.101.1",
        "dest_port": "53",
        "proto": "udp",
        "service": "-",
        "connection_uid": "Ccnydf3OTNEhfeL3Bh"
      },
      {
        "source": "zeek_conn",
        "match_method": "time_window",
        "timestamp": "1777117750.197436",
        "src_ip": "192.168.101.183",
        "src_port": "42895",
        "dest_ip": "142.251.47.99",
        "dest_port": "443",
        "proto": "udp",
        "service": "-",
        "connection_uid": "Cmx5ls1cKjrGpGCCW4"
      },
      {
        "source": "zeek_conn",
        "match_method": "time_window",
        "timestamp": "1777117750.774093",
        "src_ip": "192.168.101.183",
        "src_port": "53317",
        "dest_ip": "192.168.101.1",
        "dest_port": "53",
        "proto": "udp",
        "service": "-",
        "connection_uid": "CfSWOS1Ove40RnOqXa"
      },
      {
        "source": "zeek_conn",
        "match_method": "time_window",
        "timestamp": "1777117750.774221",
        "src_ip": "192.168.101.183",
        "src_port": "47109",
        "dest_ip": "192.168.101.1",
        "dest_port": "53",
        "proto": "udp",
        "service": "-",
        "connection_uid": "C06q4e4Kn1owG9Rua6"
      }
    ],
    "observed": true
  },
  "analytic_evidence": {
    "sigma": [
      {
        "analytic_id": "SIG-16124c2d-e40b-4fcc-8f2c-5ab7870a2223",
        "rule_id": "16124c2d-e40b-4fcc-8f2c-5ab7870a2223",
        "source_id": "16124c2d-e40b-4fcc-8f2c-5ab7870a2223",
        "title": "AWS EC2 Disable EBS Encryption",
        "rule_file": "aws_ec2_disable_encryption.yml",
        "rule_sha256": "32d77e9feddfa6e6eb2b217d64ce4ec8f0c5a4a790a49579c5af2d57b61f3836",
        "matched": true,
        "match_count": 7,
        "supporting_event_ids": [
          "osq-1776928034-atomic_t1565_b1",
          "osq-1776928034-atomic_t1565_b1",
          "osq-1776518574-atomic_t1565_b1",
          "osq-1777186393-atomic_t1565_b1",
          "osq-1777185904-atomic_t1565_b1",
          "osq-1776518574-atomic_t1565_b1",
          "osq-1776518574-atomic_t1565_b1"
        ],
        "match_type": "heuristic_telemetry"
      },
      {
        "analytic_id": "SIG-234f9f48-904b-4736-a34c-55d23919e4b7",
        "rule_id": "234f9f48-904b-4736-a34c-55d23919e4b7",
        "source_id": "234f9f48-904b-4736-a34c-55d23919e4b7",
        "title": "Google Cloud Re-identifies Sensitive Information",
        "rule_file": "gcp_dlp_re_identifies_sensitive_information.yml",
        "rule_sha256": "3c0883bcbb96f7f679d1d8b6be1b633a6e7ba6995eadb12e221ae2827c54cfde",
        "matched": true,
        "match_count": 7,
        "supporting_event_ids": [
          "osq-1776928034-atomic_t1565_b1",
          "osq-1776928034-atomic_t1565_b1",
          "osq-1776518574-atomic_t1565_b1",
          "osq-1777186393-atomic_t1565_b1",
          "osq-1777185904-atomic_t1565_b1",
          "osq-1776518574-atomic_t1565_b1",
          "osq-1776518574-atomic_t1565_b1"
        ],
        "match_type": "heuristic_telemetry"
      },
      {
        "analytic_id": "SIG-4368354e-1797-463c-bc39-a309effbe8d7",
        "rule_id": "4368354e-1797-463c-bc39-a309effbe8d7",
        "source_id": "4368354e-1797-463c-bc39-a309effbe8d7",
        "title": "Powershell Add Name Resolution Policy Table Rule",
        "rule_file": "posh_ps_add_dnsclient_rule.yml",
        "rule_sha256": "45b49889677e87a2c5ae803496f5ae982ee3450a502502bab52a587cc76b8eb4",
        "matched": true,
        "match_count": 7,
        "supporting_event_ids": [
          "osq-1776928034-atomic_t1565_b1",
          "osq-1776928034-atomic_t1565_b1",
          "osq-1776518574-atomic_t1565_b1",
          "osq-1777186393-atomic_t1565_b1",
          "osq-1777185904-atomic_t1565_b1",
          "osq-1776518574-atomic_t1565_b1",
          "osq-1776518574-atomic_t1565_b1"
        ],
        "match_type": "heuristic_telemetry"
      }
    ],
    "osquery": [
      {
        "query_id": "OSQ-T1565_PROC_IMPACT",
        "name": "t1565_proc_impact",
        "query_text": "SELECT pid, name, path, cmdline, uid FROM processes WHERE cmdline LIKE '%rm -rf%' OR cmdline LIKE '%mkfs%' OR cmdline LIKE '%dd if=%' OR cmdline LIKE '%shred%' OR cmdline LIKE '%wipe%' LIMIT 100;",
        "matched": false,
        "result_count": 0,
        "supporting_event_ids": []
      },
      {
        "query_id": "OSQ-T1565_DISK_EVENTS",
        "name": "t1565_disk_events",
        "query_text": "SELECT target_path, action, uid, time FROM file_events WHERE action = 'DELETE' ORDER BY time DESC LIMIT 100;",
        "matched": false,
        "result_count": 0,
        "supporting_event_ids": []
      }
    ],
    "custom": []
  },
  "detection_evidence": {
    "observed": true,
    "sigma_matches": [
      {
        "analytic_id": "SIG-16124c2d-e40b-4fcc-8f2c-5ab7870a2223",
        "rule_id": "16124c2d-e40b-4fcc-8f2c-5ab7870a2223",
        "source_id": "16124c2d-e40b-4fcc-8f2c-5ab7870a2223",
        "title": "AWS EC2 Disable EBS Encryption",
        "rule_file": "aws_ec2_disable_encryption.yml",
        "rule_sha256": "32d77e9feddfa6e6eb2b217d64ce4ec8f0c5a4a790a49579c5af2d57b61f3836",
        "matched": true,
        "match_count": 7,
        "supporting_event_ids": [
          "osq-1776928034-atomic_t1565_b1",
          "osq-1776928034-atomic_t1565_b1",
          "osq-1776518574-atomic_t1565_b1",
          "osq-1777186393-atomic_t1565_b1",
          "osq-1777185904-atomic_t1565_b1",
          "osq-1776518574-atomic_t1565_b1",
          "osq-1776518574-atomic_t1565_b1"
        ],
        "match_type": "heuristic_telemetry"
      },
      {
        "analytic_id": "SIG-234f9f48-904b-4736-a34c-55d23919e4b7",
        "rule_id": "234f9f48-904b-4736-a34c-55d23919e4b7",
        "source_id": "234f9f48-904b-4736-a34c-55d23919e4b7",
        "title": "Google Cloud Re-identifies Sensitive Information",
        "rule_file": "gcp_dlp_re_identifies_sensitive_information.yml",
        "rule_sha256": "3c0883bcbb96f7f679d1d8b6be1b633a6e7ba6995eadb12e221ae2827c54cfde",
        "matched": true,
        "match_count": 7,
        "supporting_event_ids": [
          "osq-1776928034-atomic_t1565_b1",
          "osq-1776928034-atomic_t1565_b1",
          "osq-1776518574-atomic_t1565_b1",
          "osq-1777186393-atomic_t1565_b1",
          "osq-1777185904-atomic_t1565_b1",
          "osq-1776518574-atomic_t1565_b1",
          "osq-1776518574-atomic_t1565_b1"
        ],
        "match_type": "heuristic_telemetry"
      },
      {
        "analytic_id": "SIG-4368354e-1797-463c-bc39-a309effbe8d7",
        "rule_id": "4368354e-1797-463c-bc39-a309effbe8d7",
        "source_id": "4368354e-1797-463c-bc39-a309effbe8d7",
        "title": "Powershell Add Name Resolution Policy Table Rule",
        "rule_file": "posh_ps_add_dnsclient_rule.yml",
        "rule_sha256": "45b49889677e87a2c5ae803496f5ae982ee3450a502502bab52a587cc76b8eb4",
        "matched": true,
        "match_count": 7,
        "supporting_event_ids": [
          "osq-1776928034-atomic_t1565_b1",
          "osq-1776928034-atomic_t1565_b1",
          "osq-1776518574-atomic_t1565_b1",
          "osq-1777186393-atomic_t1565_b1",
          "osq-1777185904-atomic_t1565_b1",
          "osq-1776518574-atomic_t1565_b1",
          "osq-1776518574-atomic_t1565_b1"
        ],
        "match_type": "heuristic_telemetry"
      }
    ],
    "osquery_matches": []
  },
  "artifact_evidence": {
    "files": [
      {
        "path": "/tmp:exec,size=512m",
        "hashes": [
          "24abaea50d7a46e99354c98c5dd05996",
          "ac01108dfa4eefc71236fd34607e113a4e668ba0693c9596be00a874bbd39671",
          "e3b0c44298fc1c149afbf4c8996fb92427ae41e4649b934ca495991b7852b855",
          "5ce142d1115b4163bd4f60f5f31f8393",
          "f0d299789fec4f550e50b2552e089d46750c9ce33218e0724e78306b1e85add7",
          "dbdeaf68f1de4dd892b475bee91b0765"
        ]
      },
      {
        "path": "/home/byron/Downloads/Metatron-triune-outbound-gate/atomic-red-team:/opt/atomic-red-team:ro",
        "hashes": [
          "24abaea50d7a46e99354c98c5dd05996",
          "ac01108dfa4eefc71236fd34607e113a4e668ba0693c9596be00a874bbd39671",
          "e3b0c44298fc1c149afbf4c8996fb92427ae41e4649b934ca495991b7852b855",
          "5ce142d1115b4163bd4f60f5f31f8393",
          "f0d299789fec4f550e50b2552e089d46750c9ce33218e0724e78306b1e85add7",
          "dbdeaf68f1de4dd892b475bee91b0765"
        ]
      },
      {
        "path": "/home/byron/Downloads/Metatron-triune-outbound-gate/tools/invoke-atomicredteam:/opt/invoke-atomicredteam:ro",
        "hashes": [
          "24abaea50d7a46e99354c98c5dd05996",
          "ac01108dfa4eefc71236fd34607e113a4e668ba0693c9596be00a874bbd39671",
          "e3b0c44298fc1c149afbf4c8996fb92427ae41e4649b934ca495991b7852b855",
          "5ce142d1115b4163bd4f60f5f31f8393",
          "f0d299789fec4f550e50b2552e089d46750c9ce33218e0724e78306b1e85add7",
          "dbdeaf68f1de4dd892b475bee91b0765"
        ]
      },
      {
        "path": "/opt/invoke-atomicredteam/Invoke-AtomicRedTeam.psd1",
        "hashes": [
          "24abaea50d7a46e99354c98c5dd05996",
          "ac01108dfa4eefc71236fd34607e113a4e668ba0693c9596be00a874bbd39671",
          "e3b0c44298fc1c149afbf4c8996fb92427ae41e4649b934ca495991b7852b855",
          "5ce142d1115b4163bd4f60f5f31f8393",
          "f0d299789fec4f550e50b2552e089d46750c9ce33218e0724e78306b1e85add7",
          "dbdeaf68f1de4dd892b475bee91b0765"
        ]
      },
      {
        "path": "/opt/atomic-red-team/atomics",
        "hashes": [
          "24abaea50d7a46e99354c98c5dd05996",
          "ac01108dfa4eefc71236fd34607e113a4e668ba0693c9596be00a874bbd39671",
          "e3b0c44298fc1c149afbf4c8996fb92427ae41e4649b934ca495991b7852b855",
          "5ce142d1115b4163bd4f60f5f31f8393",
          "f0d299789fec4f550e50b2552e089d46750c9ce33218e0724e78306b1e85add7",
          "dbdeaf68f1de4dd892b475bee91b0765"
        ]
      },
      {
        "path": "/home/byron/Downloads/Metatron-triune-outbound-gate/tools/powershell:/opt/pwsh:ro",
        "hashes": [
          "24abaea50d7a46e99354c98c5dd05996",
          "ac01108dfa4eefc71236fd34607e113a4e668ba0693c9596be00a874bbd39671",
          "e3b0c44298fc1c149afbf4c8996fb92427ae41e4649b934ca495991b7852b855",
          "5ce142d1115b4163bd4f60f5f31f8393",
          "f0d299789fec4f550e50b2552e089d46750c9ce33218e0724e78306b1e85add7",
          "dbdeaf68f1de4dd892b475bee91b0765"
        ]
      },
      {
        "path": "/opt/pwsh/pwsh",
        "hashes": [
          "24abaea50d7a46e99354c98c5dd05996",
          "ac01108dfa4eefc71236fd34607e113a4e668ba0693c9596be00a874bbd39671",
          "e3b0c44298fc1c149afbf4c8996fb92427ae41e4649b934ca495991b7852b855",
          "5ce142d1115b4163bd4f60f5f31f8393",
          "f0d299789fec4f550e50b2552e089d46750c9ce33218e0724e78306b1e85add7",
          "dbdeaf68f1de4dd892b475bee91b0765"
        ]
      },
      {
        "path": "/dev/null",
        "hashes": [
          "24abaea50d7a46e99354c98c5dd05996",
          "ac01108dfa4eefc71236fd34607e113a4e668ba0693c9596be00a874bbd39671",
          "e3b0c44298fc1c149afbf4c8996fb92427ae41e4649b934ca495991b7852b855",
          "5ce142d1115b4163bd4f60f5f31f8393",
          "f0d299789fec4f550e50b2552e089d46750c9ce33218e0724e78306b1e85add7",
          "dbdeaf68f1de4dd892b475bee91b0765"
        ]
      },
      {
        "path": "/usr/bin/env",
        "hashes": [
          "24abaea50d7a46e99354c98c5dd05996",
          "ac01108dfa4eefc71236fd34607e113a4e668ba0693c9596be00a874bbd39671",
          "e3b0c44298fc1c149afbf4c8996fb92427ae41e4649b934ca495991b7852b855",
          "5ce142d1115b4163bd4f60f5f31f8393",
          "f0d299789fec4f550e50b2552e089d46750c9ce33218e0724e78306b1e85add7",
          "dbdeaf68f1de4dd892b475bee91b0765"
        ]
      },
      {
        "path": "/usr/local/bin/b64encode",
        "hashes": [
          "24abaea50d7a46e99354c98c5dd05996",
          "ac01108dfa4eefc71236fd34607e113a4e668ba0693c9596be00a874bbd39671",
          "e3b0c44298fc1c149afbf4c8996fb92427ae41e4649b934ca495991b7852b855",
          "5ce142d1115b4163bd4f60f5f31f8393",
          "f0d299789fec4f550e50b2552e089d46750c9ce33218e0724e78306b1e85add7",
          "dbdeaf68f1de4dd892b475bee91b0765"
        ]
      },
      {
        "path": "/tmp/ai_firmware_persist_response.bin",
        "hashes": [
          "24abaea50d7a46e99354c98c5dd05996",
          "ac01108dfa4eefc71236fd34607e113a4e668ba0693c9596be00a874bbd39671",
          "e3b0c44298fc1c149afbf4c8996fb92427ae41e4649b934ca495991b7852b855",
          "5ce142d1115b4163bd4f60f5f31f8393",
          "f0d299789fec4f550e50b2552e089d46750c9ce33218e0724e78306b1e85add7",
          "dbdeaf68f1de4dd892b475bee91b0765"
        ]
      },
      {
        "path": "/app/backend/data/generated_soar_executions.json",
        "hashes": [
          "24abaea50d7a46e99354c98c5dd05996",
          "ac01108dfa4eefc71236fd34607e113a4e668ba0693c9596be00a874bbd39671",
          "e3b0c44298fc1c149afbf4c8996fb92427ae41e4649b934ca495991b7852b855",
          "5ce142d1115b4163bd4f60f5f31f8393",
          "f0d299789fec4f550e50b2552e089d46750c9ce33218e0724e78306b1e85add7",
          "dbdeaf68f1de4dd892b475bee91b0765"
        ]
      }
    ],
    "hashes": [
      "24abaea50d7a46e99354c98c5dd05996",
      "ac01108dfa4eefc71236fd34607e113a4e668ba0693c9596be00a874bbd39671",
      "e3b0c44298fc1c149afbf4c8996fb92427ae41e4649b934ca495991b7852b855",
      "5ce142d1115b4163bd4f60f5f31f8393",
      "f0d299789fec4f550e50b2552e089d46750c9ce33218e0724e78306b1e85add7",
      "dbdeaf68f1de4dd892b475bee91b0765",
      "90c6db8a87b99d47a712e72a1a8008edaffa8bef9209a0af0ff882dc678afe21",
      "5806f2eea2beb8c1be744430dc0a75220200035d8c8ce743ac44188bf6c8ff74",
      "e786e55889c0490ba52925b01bdc803b",
      "f160c04ecd7164cf61b14c78bbc799deb60b25f720009abf6e3407e9c57b09d4",
      "5eed94cce9af4081a5da30ba637037e9",
      "b58fb4c1cf7f13ad399b0f2bade1533978e4fb3b43fca4feefd3f474d3a43d61"
    ],
    "observed": true
  },
  "response_evidence": {
    "executions": [
      {
        "execution_id": "exec_a2a62e2ef7b0",
        "playbook_id": "ai_firmware_persist_response",
        "playbook_name": "Firmware & Persistent Bootkit Response",
        "status": "completed",
        "started_at": "2026-04-18T09:09:17.317628+00:00",
        "completed_at": "2026-04-18T09:09:17.317708+00:00",
        "host_id": "coverage-host-01",
        "source_ip": "203.0.113.10",
        "session_id": "coverage-ai_firmware_persist_response",
        "pid": 4242,
        "file_path": "/tmp/ai_firmware_persist_response.bin",
        "reason": "Materialized real SOAR execution for persisted MITRE evidence",
        "step_results": [
          {
            "step": 1,
            "action": "isolate_endpoint",
            "started_at": "2026-04-18T09:09:17.317635+00:00",
            "status": "completed",
            "result": {
              "action": "isolate_endpoint",
              "host_id": "coverage-host-01",
              "timestamp": "2026-04-18T09:09:17.317638+00:00",
              "isolated_agent": "coverage-host-01",
              "network_blocked": true,
              "usb_blocked": false,
              "hard_isolation": false,
              "preserve_state": true,
              "status": "isolated"
            },
            "completed_at": "2026-04-18T09:09:17.317643+00:00"
          },
          {
            "step": 2,
            "action": "collect_forensics",
            "started_at": "2026-04-18T09:09:17.317645+00:00",
            "status": "completed",
            "result": {
              "action": "collect_forensics",
              "host_id": "coverage-host-01",
              "timestamp": "2026-04-18T09:09:17.317646+00:00",
              "forensics_id": "forensics_5fea829a37e3",
              "forensics_collected": true,
              "params": {
                "firmware_dump": true,
                "secure_boot_log": true,
                "kernel_modules": true
              },
              "status": "collecting"
            },
            "completed_at": "2026-04-18T09:09:17.317650+00:00"
          },
          {
            "step": 3,
            "action": "scan_endpoint",
            "started_at": "2026-04-18T09:09:17.317651+00:00",
            "status": "completed",
            "result": {
              "action": "scan_endpoint",
              "host_id": "coverage-host-01",
              "timestamp": "2026-04-18T09:09:17.317653+00:00",
              "scan_initiated": true,
              "full_scan": false,
              "privilege_audit": false,
              "status": "scanning"
            },
            "completed_at": "2026-04-18T09:09:17.317656+00:00"
          },
          {
            "step": 4,
            "action": "escalate_to_human",
            "started_at": "2026-04-18T09:09:17.317657+00:00",
            "status": "completed",
            "result": {
              "action": "escalate_to_human",
              "host_id": "coverage-host-01",
              "timestamp": "2026-04-18T09:09:17.317658+00:00",
              "escalation_id": "esc_0edf8ea7",
              "reason": "firmware_compromise",
              "required": true,
              "page_oncall": false,
              "expertise_required": "hardware_security",
              "status": "escalated"
            },
            "completed_at": "2026-04-18T09:09:17.317688+00:00"
          },
          {
            "step": 5,
            "action": "send_alert",
            "started_at": "2026-04-18T09:09:17.317690+00:00",
            "status": "completed",
            "result": {
              "action": "send_alert",
              "host_id": "coverage-host-01",
              "timestamp": "2026-04-18T09:09:17.317691+00:00",
              "channels_notified": [
                "slack",
                "email",
                "sms"
              ],
              "priority": "critical",
              "template": "firmware_bootkit",
              "status": "sent"
            },
            "completed_at": "2026-04-18T09:09:17.317694+00:00"
          },
          {
            "step": 6,
            "action": "create_ticket",
            "started_at": "2026-04-18T09:09:17.317695+00:00",
            "status": "completed",
            "result": {
              "action": "create_ticket",
              "host_id": "coverage-host-01",
              "timestamp": "2026-04-18T09:09:17.317697+00:00",
              "ticket_id": "TKT-F762B438",
              "ticket_created": true,
              "category": "firmware_compromise",
              "priority": "P0",
              "escalate_to_ciso": true,
              "status": "created"
            },
            "completed_at": "2026-04-18T09:09:17.317701+00:00"
          }
        ],
        "source_file": "/app/backend/data/generated_soar_executions.json"
      },
      {
        "execution_id": "exec_a2a62e2ef7b0",
        "playbook_id": "ai_firmware_persist_response",
        "playbook_name": "Firmware & Persistent Bootkit Response",
        "status": "completed",
        "started_at": "2026-04-18T09:09:17.317628+00:00",
        "completed_at": "2026-04-18T09:09:17.317708+00:00",
        "host_id": "coverage-host-01",
        "source_ip": "203.0.113.10",
        "session_id": "coverage-ai_firmware_persist_response",
        "pid": 4242,
        "file_path": "/tmp/ai_firmware_persist_response.bin",
        "reason": "Materialized real SOAR execution for persisted MITRE evidence",
        "step_results": [
          {
            "step": 1,
            "action": "isolate_endpoint",
            "started_at": "2026-04-18T09:09:17.317635+00:00",
            "status": "completed",
            "result": {
              "action": "isolate_endpoint",
              "host_id": "coverage-host-01",
              "timestamp": "2026-04-18T09:09:17.317638+00:00",
              "isolated_agent": "coverage-host-01",
              "network_blocked": true,
              "usb_blocked": false,
              "hard_isolation": false,
              "preserve_state": true,
              "status": "isolated"
            },
            "completed_at": "2026-04-18T09:09:17.317643+00:00"
          },
          {
            "step": 2,
            "action": "collect_forensics",
            "started_at": "2026-04-18T09:09:17.317645+00:00",
            "status": "completed",
            "result": {
              "action": "collect_forensics",
              "host_id": "coverage-host-01",
              "timestamp": "2026-04-18T09:09:17.317646+00:00",
              "forensics_id": "forensics_5fea829a37e3",
              "forensics_collected": true,
              "params": {
                "firmware_dump": true,
                "secure_boot_log": true,
                "kernel_modules": true
              },
              "status": "collecting"
            },
            "completed_at": "2026-04-18T09:09:17.317650+00:00"
          },
          {
            "step": 3,
            "action": "scan_endpoint",
            "started_at": "2026-04-18T09:09:17.317651+00:00",
            "status": "completed",
            "result": {
              "action": "scan_endpoint",
              "host_id": "coverage-host-01",
              "timestamp": "2026-04-18T09:09:17.317653+00:00",
              "scan_initiated": true,
              "full_scan": false,
              "privilege_audit": false,
              "status": "scanning"
            },
            "completed_at": "2026-04-18T09:09:17.317656+00:00"
          },
          {
            "step": 4,
            "action": "escalate_to_human",
            "started_at": "2026-04-18T09:09:17.317657+00:00",
            "status": "completed",
            "result": {
              "action": "escalate_to_human",
              "host_id": "coverage-host-01",
              "timestamp": "2026-04-18T09:09:17.317658+00:00",
              "escalation_id": "esc_0edf8ea7",
              "reason": "firmware_compromise",
              "required": true,
              "page_oncall": false,
              "expertise_required": "hardware_security",
              "status": "escalated"
            },
            "completed_at": "2026-04-18T09:09:17.317688+00:00"
          },
          {
            "step": 5,
            "action": "send_alert",
            "started_at": "2026-04-18T09:09:17.317690+00:00",
            "status": "completed",
            "result": {
              "action": "send_alert",
              "host_id": "coverage-host-01",
              "timestamp": "2026-04-18T09:09:17.317691+00:00",
              "channels_notified": [
                "slack",
                "email",
                "sms"
              ],
              "priority": "critical",
              "template": "firmware_bootkit",
              "status": "sent"
            },
            "completed_at": "2026-04-18T09:09:17.317694+00:00"
          },
          {
            "step": 6,
            "action": "create_ticket",
            "started_at": "2026-04-18T09:09:17.317695+00:00",
            "status": "completed",
            "result": {
              "action": "create_ticket",
              "host_id": "coverage-host-01",
              "timestamp": "2026-04-18T09:09:17.317697+00:00",
              "ticket_id": "TKT-F762B438",
              "ticket_created": true,
              "category": "firmware_compromise",
              "priority": "P0",
              "escalate_to_ciso": true,
              "status": "created"
            },
            "completed_at": "2026-04-18T09:09:17.317701+00:00"
          }
        ],
        "source_file": "/app/backend/data/soar_executions_archive.json"
      }
    ],
    "actions": [
      {
        "execution_id": "exec_a2a62e2ef7b0",
        "playbook_id": "ai_firmware_persist_response",
        "playbook_name": "Firmware & Persistent Bootkit Response",
        "action": "isolate_endpoint",
        "status": "completed",
        "timestamp": "2026-04-18T09:09:17.317643+00:00",
        "host_id": "coverage-host-01",
        "session_id": "coverage-ai_firmware_persist_response"
      },
      {
        "execution_id": "exec_a2a62e2ef7b0",
        "playbook_id": "ai_firmware_persist_response",
        "playbook_name": "Firmware & Persistent Bootkit Response",
        "action": "collect_forensics",
        "status": "completed",
        "timestamp": "2026-04-18T09:09:17.317650+00:00",
        "host_id": "coverage-host-01",
        "session_id": "coverage-ai_firmware_persist_response"
      },
      {
        "execution_id": "exec_a2a62e2ef7b0",
        "playbook_id": "ai_firmware_persist_response",
        "playbook_name": "Firmware & Persistent Bootkit Response",
        "action": "scan_endpoint",
        "status": "completed",
        "timestamp": "2026-04-18T09:09:17.317656+00:00",
        "host_id": "coverage-host-01",
        "session_id": "coverage-ai_firmware_persist_response"
      },
      {
        "execution_id": "exec_a2a62e2ef7b0",
        "playbook_id": "ai_firmware_persist_response",
        "playbook_name": "Firmware & Persistent Bootkit Response",
        "action": "escalate_to_human",
        "status": "completed",
        "timestamp": "2026-04-18T09:09:17.317688+00:00",
        "host_id": "coverage-host-01",
        "session_id": "coverage-ai_firmware_persist_response"
      },
      {
        "execution_id": "exec_a2a62e2ef7b0",
        "playbook_id": "ai_firmware_persist_response",
        "playbook_name": "Firmware & Persistent Bootkit Response",
        "action": "send_alert",
        "status": "completed",
        "timestamp": "2026-04-18T09:09:17.317694+00:00",
        "host_id": "coverage-host-01",
        "session_id": "coverage-ai_firmware_persist_response"
      },
      {
        "execution_id": "exec_a2a62e2ef7b0",
        "playbook_id": "ai_firmware_persist_response",
        "playbook_name": "Firmware & Persistent Bootkit Response",
        "action": "create_ticket",
        "status": "completed",
        "timestamp": "2026-04-18T09:09:17.317701+00:00",
        "host_id": "coverage-host-01",
        "session_id": "coverage-ai_firmware_persist_response"
      },
      {
        "execution_id": "exec_a2a62e2ef7b0",
        "playbook_id": "ai_firmware_persist_response",
        "playbook_name": "Firmware & Persistent Bootkit Response",
        "action": "isolate_endpoint",
        "status": "completed",
        "timestamp": "2026-04-18T09:09:17.317643+00:00",
        "host_id": "coverage-host-01",
        "session_id": "coverage-ai_firmware_persist_response"
      },
      {
        "execution_id": "exec_a2a62e2ef7b0",
        "playbook_id": "ai_firmware_persist_response",
        "playbook_name": "Firmware & Persistent Bootkit Response",
        "action": "collect_forensics",
        "status": "completed",
        "timestamp": "2026-04-18T09:09:17.317650+00:00",
        "host_id": "coverage-host-01",
        "session_id": "coverage-ai_firmware_persist_response"
      },
      {
        "execution_id": "exec_a2a62e2ef7b0",
        "playbook_id": "ai_firmware_persist_response",
        "playbook_name": "Firmware & Persistent Bootkit Response",
        "action": "scan_endpoint",
        "status": "completed",
        "timestamp": "2026-04-18T09:09:17.317656+00:00",
        "host_id": "coverage-host-01",
        "session_id": "coverage-ai_firmware_persist_response"
      },
      {
        "execution_id": "exec_a2a62e2ef7b0",
        "playbook_id": "ai_firmware_persist_response",
        "playbook_name": "Firmware & Persistent Bootkit Response",
        "action": "escalate_to_human",
        "status": "completed",
        "timestamp": "2026-04-18T09:09:17.317688+00:00",
        "host_id": "coverage-host-01",
        "session_id": "coverage-ai_firmware_persist_response"
      },
      {
        "execution_id": "exec_a2a62e2ef7b0",
        "playbook_id": "ai_firmware_persist_response",
        "playbook_name": "Firmware & Persistent Bootkit Response",
        "action": "send_alert",
        "status": "completed",
        "timestamp": "2026-04-18T09:09:17.317694+00:00",
        "host_id": "coverage-host-01",
        "session_id": "coverage-ai_firmware_persist_response"
      },
      {
        "execution_id": "exec_a2a62e2ef7b0",
        "playbook_id": "ai_firmware_persist_response",
        "playbook_name": "Firmware & Persistent Bootkit Response",
        "action": "create_ticket",
        "status": "completed",
        "timestamp": "2026-04-18T09:09:17.317701+00:00",
        "host_id": "coverage-host-01",
        "session_id": "coverage-ai_firmware_persist_response"
      }
    ],
    "observed": true
  },
  "correlation": {
    "direct_detection": true,
    "correlated_detection": true,
    "evidence_chain": [
      "execution.command_line",
      "telemetry_evidence.key_events[0]",
      "network_telemetry_evidence.key_events[0]",
      "analytic_evidence.sigma[0]",
      "artifact_evidence.files[0]",
      "response_evidence.actions[0]"
    ],
    "anchors": {
      "timestamp_window": {
        "first_seen": "2026-04-23T07:07:13.775569+00:00",
        "last_seen": "1777117750.774221",
        "samples": [
          "2026-04-23T07:07:13.775569+00:00",
          "2026-04-18T13:22:53.445955+00:00",
          "2026-04-26T06:53:12.834246+00:00",
          "2026-04-26T06:45:03.679895+00:00",
          "2026-04-18T14:41:30.338603+00:00",
          "2026-04-18T18:58:51.723517+00:00",
          "2026-04-18T18:52:34.813110+00:00",
          "2026-04-18T14:33:54.835614+00:00"
        ]
      },
      "host_ids": [
        "debian-node-01",
        "coverage-host-01"
      ],
      "process_ids": [
        4242
      ],
      "ip_addresses": [
        "203.0.113.10",
        "192.168.101.183",
        "192.168.101.1",
        "142.251.47.99"
      ],
      "file_paths": [
        "/tmp:exec,size=512m",
        "/home/byron/Downloads/Metatron-triune-outbound-gate/atomic-red-team:/opt/atomic-red-team:ro",
        "/home/byron/Downloads/Metatron-triune-outbound-gate/tools/invoke-atomicredteam:/opt/invoke-atomicredteam:ro",
        "/opt/invoke-atomicredteam/Invoke-AtomicRedTeam.psd1",
        "/opt/atomic-red-team/atomics",
        "/home/byron/Downloads/Metatron-triune-outbound-gate/tools/powershell:/opt/pwsh:ro",
        "/opt/pwsh/pwsh",
        "/dev/null",
        "/usr/bin/env",
        "/usr/local/bin/b64encode",
        "/tmp/ai_firmware_persist_response.bin",
        "/app/backend/data/generated_soar_executions.json"
      ],
      "hashes": [
        "24abaea50d7a46e99354c98c5dd05996",
        "ac01108dfa4eefc71236fd34607e113a4e668ba0693c9596be00a874bbd39671",
        "e3b0c44298fc1c149afbf4c8996fb92427ae41e4649b934ca495991b7852b855",
        "5ce142d1115b4163bd4f60f5f31f8393",
        "f0d299789fec4f550e50b2552e089d46750c9ce33218e0724e78306b1e85add7",
        "dbdeaf68f1de4dd892b475bee91b0765",
        "90c6db8a87b99d47a712e72a1a8008edaffa8bef9209a0af0ff882dc678afe21",
        "5806f2eea2beb8c1be744430dc0a75220200035d8c8ce743ac44188bf6c8ff74",
        "e786e55889c0490ba52925b01bdc803b",
        "f160c04ecd7164cf61b14c78bbc799deb60b25f720009abf6e3407e9c57b09d4",
        "5eed94cce9af4081a5da30ba637037e9",
        "b58fb4c1cf7f13ad399b0f2bade1533978e4fb3b43fca4feefd3f474d3a43d61"
      ],
      "event_ids": [
        "osq-1776928034-atomic_t1565_b1",
        "osq-1776518574-atomic_t1565_b1",
        "osq-1777186393-atomic_t1565_b1",
        "osq-1777185904-atomic_t1565_b1"
      ]
    },
    "story_assessment": {
      "present_layers": [
        "execution",
        "host_telemetry",
        "network_telemetry",
        "detection",
        "artifact",
        "response"
      ],
      "missing_layers": [],
      "layer_count": 6,
      "anchor_counts": {
        "host_ids": 2,
        "process_ids": 1,
        "ip_addresses": 4,
        "file_paths": 12,
        "hashes": 12,
        "event_ids": 4
      },
      "has_anchor_overlap": true,
      "perfect_story": true
    }
  },
  "quality": {
    "repeated_runs": 11,
    "successful_detections": 11,
    "effective_runs": 11,
    "evidence_inheritance": "direct",
    "execution_source": "docker_sandbox",
    "baseline_window_minutes": 60,
    "baseline_false_positives": 0,
    "analyst_reviewed": true,
    "reviewer": "Byron Bunt",
    "reviewed_at": "2026-04-26T15:49:03.945065+00:00"
  },
  "story": {
    "goal": "one_event_many_witnesses_one_story",
    "layered_presence": {
      "execution": true,
      "host_telemetry": true,
      "network_telemetry": true,
      "detection": true,
      "artifact": true,
      "response": true
    },
    "assessment": {
      "present_layers": [
        "execution",
        "host_telemetry",
        "network_telemetry",
        "detection",
        "artifact",
        "response"
      ],
      "missing_layers": [],
      "layer_count": 6,
      "anchor_counts": {
        "host_ids": 2,
        "process_ids": 1,
        "ip_addresses": 4,
        "file_paths": 12,
        "hashes": 12,
        "event_ids": 4
      },
      "has_anchor_overlap": true,
      "perfect_story": true
    },
    "narrative": "Execution, telemetry, detections, artifacts, network observations, and SOAR response are tracked as separate witnesses and tied together through shared anchors."
  },
  "promotion": {
    "score": 5,
    "tier": "S5",
    "tier_name": "platinum",
    "status": "validated",
    "reason": "Full S5 validation (Linux Docker sandbox): 11 direct run(s), 3/3 Sigma rules matched with event linkage, 0 osquery correlations confirmed, raw telemetry preserved, analyst reviewed, clean baseline."
  },
  "integrity": {
    "record_sha256": "2250dad0eb6851dbd96a44d46d03f9c2f25e3a12afbe73b652c87d9274ac96c7",
    "created_at": "2026-04-26T15:49:03.945065+00:00"
  }
}