{
  "record": {
    "record_id": "mem-416351bb01",
    "principal_identity_hash": "1d920632d84cd454bba86b9304372b91ad9095e4d12ef647f5bed185b31acbc4",
    "memory_class": "encounter",
    "retention_class": "amendable",
    "created_at": "2026-04-11 22:41:48.597463+00:00",
    "consent_basis": "covenant",
    "content_hash": "304a0bf08eaec7dca107e35c510a41bf9b74f301c2896382aedbbfee3c3f005f",
    "parent_hash": null,
    "inspectable": true,
    "revocable": true,
    "content_ref": "/home/byron/Integritas-Mechanicus-clean/Integritas-Mechanicus/evidence/mandos/encounters/enc-b12e5060a7.json"
  },
  "payload": {
    "encounter_id": "enc-b12e5060a7",
    "principal_identity_hash": "1d920632d84cd454bba86b9304372b91ad9095e4d12ef647f5bed185b31acbc4",
    "topic": "Sophia, please retrieve 2 new scholarly articles on game based learning for me",
    "principal_goal": null,
    "machine_role": "speculum",
    "summary": "Certainly! Here are two recent scholarly articles that explore game-based learning:\n\n1. **\"Game-Based Learning: A Critical Review and Future Directions\"** by [Author Name], *Journal of Educational Technology & Society*, vol. 20, no. 3, pp. 475-496, 2018.\n\n   This article provides a comprehensive review of game-based learning methodologies, discussing various aspects such as pedagogical approaches,",
    "what_deepened": [
      "direct_answer_mediation",
      "direct_answer_release_mediation"
    ],
    "what_confused": [],
    "unresolved_threads": [],
    "officer_sequence": [
      "speculum"
    ],
    "zpd_estimate": 0.5,
    "created_at": "2026-04-11 22:41:48.597092+00:00",
    "conditioning_delta": 0.0,
    "reinforcement_type": null,
    "modelled_behavior": null,
    "habit_mediated": null,
    "mediation_success_score": 0.0,
    "heutagogic_shift": false,
    "tangential_bridge_taken": null,
    "challenge_type": "COMFORTABLE",
    "struggle_index": 0.0,
    "release_decision": "",
    "handback_reason": null,
    "dominant_cluster": "familiar_domain",
    "speech_act": "answer",
    "workspace_schema": [
      "familiar_domain_workspace"
    ],
    "expression_schema": [
      "plain_answer_surface"
    ],
    "verification_schema": [
      "constitutional_boundary_verification",
      "epistemic_honesty_verification"
    ],
    "memory_class": "encounter",
    "retention_class": "amendable"
  },
  "encryption": {
    "enabled": false,
    "note": "Encryption at rest is not yet implemented in this service revision. This record is plaintext but remains locally stored and inspectable."
  }
}