{
  "direct_detection": true,
  "correlated_detection": true,
  "evidence_chain": [
    "execution.command_line",
    "telemetry_evidence.key_events[0]",
    "network_telemetry_evidence.key_events[0]",
    "analytic_evidence.sigma[0]",
    "artifact_evidence.files[0]",
    "response_evidence.actions[0]"
  ],
  "anchors": {
    "timestamp_window": {
      "first_seen": "2026-04-25T07:49:33.645358+00:00",
      "last_seen": "1777117750.774221",
      "samples": [
        "2026-04-25T07:49:33.645358+00:00",
        "2026-04-25T07:20:23.799911+00:00",
        "2026-04-25T08:25:25.448043+00:00",
        "2026-04-25T08:17:44.349144+00:00",
        "2026-04-25T07:57:11.093380+00:00",
        "2026-04-25T08:31:08.848973+00:00",
        "2026-04-18T13:22:03.185355+00:00",
        "2026-04-18T18:52:43.827374+00:00"
      ]
    },
    "host_ids": [
      "debian-node-01",
      "mitre-host-f0736972-aea7-4c46-a0a2-144eb5e812c2",
      "coverage-host-01"
    ],
    "process_ids": [
      4242
    ],
    "ip_addresses": [
      "203.0.113.10",
      "192.168.101.183",
      "192.168.101.1",
      "142.251.47.99"
    ],
    "file_paths": [
      "/macOS",
      "/opt/atomic-red-team/atomics/../ExternalPayloads/devtunnel:",
      "/opt/atomic-red-team/atomics",
      "/8",
      "/tmp/T1572.bin",
      "/var/lib/seraph-ai/artifacts/soar_executions_archive.json",
      "/tmp/pb_ioc_response.bin",
      "/app/backend/data/generated_soar_executions.json",
      "/tmp/ai_exfil_cut_01.bin",
      "/app/backend/data/soar_executions_archive.json"
    ],
    "hashes": [
      "4456d9eba221489599ded27fa494a3d4",
      "c82c795d141959ffb042f025688141b5c4fee035078dfbae871994c1a4944b0e",
      "e3b0c44298fc1c149afbf4c8996fb92427ae41e4649b934ca495991b7852b855"
    ],
    "event_ids": [
      "osq-1777101624-atomic_t1572_b1",
      "osq-1777101625-atomic_t1572_b2",
      "osq-1777101626-atomic_t1572_b3",
      "osq-1777105526-atomic_t1572_b1",
      "osq-1777105527-atomic_t1572_b2",
      "osq-1777105528-atomic_t1572_b3",
      "osq-1777105065-atomic_t1572_b1",
      "osq-1777105066-atomic_t1572_b2",
      "osq-1777105067-atomic_t1572_b3",
      "osq-1777103374-atomic_t1572_b1",
      "osq-1777103832-atomic_t1572_b1",
      "osq-1777103833-atomic_t1572_b2",
      "osq-1777103834-atomic_t1572_b3",
      "osq-1777105869-atomic_t1572_b1",
      "osq-1776518524-atomic_t1572_b1",
      "osq-1776518525-atomic_t1572_b2",
      "osq-1776518526-atomic_t1572_b3",
      "osq-1776538364-atomic_t1572_b1",
      "osq-1776538365-atomic_t1572_b2",
      "osq-1776538366-atomic_t1572_b3"
    ]
  },
  "story_assessment": {
    "present_layers": [
      "execution",
      "host_telemetry",
      "network_telemetry",
      "detection",
      "artifact",
      "response"
    ],
    "missing_layers": [],
    "layer_count": 6,
    "anchor_counts": {
      "host_ids": 3,
      "process_ids": 1,
      "ip_addresses": 4,
      "file_paths": 10,
      "hashes": 3,
      "event_ids": 20
    },
    "has_anchor_overlap": true,
    "perfect_story": true
  }
}